Workbook

Sheet Yuya 2027
A1: Responsable:
A2: Pao Oropeza
CJ15: SEGUIMIENTO DE FECHAS
CJ16: PPEDIDOS | CL16: PREPRODCCION | CN16: AUTORIZACIÓN MARCA | CP16: DISPONIBILIDAD | CR16: DOCUMENTOS PROVEEDOR | CT16: PICK UP DE MERCANCIA | CV16: SALIDA DE LIS | CX16: LLEGADA A ADUANA | CZ16: DISPONIBILIDAD EN ALMACEN
A17: # | B17: Fecha confirmada de Lanzamiento | C17: Mes de Lanzamiento (Esperado) | D17: Estatus | E17: EAN | F17: Código interno | G17: Nombre Comercial | H17: Imagen | I17: Contenido | J17: Marca | K17: Canales | L17: Fase | M17: Costo real (USD) | N17: Moneda | O17: Piezas cotizadas (MOQ) | P17: Costo Esperado en MXN | Q17: IGI | R17: Incrementables | S17: Costo final en MXN (FOB en almacén PT) | T17: Precio Benchmark | U17: Precio publico C/IVA | V17: Facturación por unidad | W17: Factor costo | X17: Margen de utilidad bruta | Y17: MU Cliente | Z17: Categoria | AA17: Pais de origen | AB17: Benchmark | AC17: Comentarios | AD17: Disponibilidad en Almacén | BA17: Line Up | BB17: Costo Autorizado | BC17: PVP Autorizado | BD17: Formula autorizada | BE17: Vobo CEO + VPs | BF17: Arte Final | BG17: PO | BH17: Salida de LIS | BI17: Disponibilidad en almacén | BJ17: Total | BK17: Estatus | BL17: % de Avance | BS17: Comentarios (Qué falta) | BT17: Disponibilidad en almacén | BU17: LIS # | BV17: Responsable Siguiente paso | CJ17: ESPERADA | CK17: REAL | CL17: ESPERADA | CM17: REAL | CN17: ESPERADA | CO17: REAL | CP17: ESPERADA | CQ17: REAL | CR17: ESPERADA | CS17: REAL | CT17: ESPERADA | CU17: REAL | CV17: ESPERADA | CW17: REAL | CX17: ESPERADA | CY17: REAL | CZ17: ESPERADA | DA17: REAL
A18: 33 | B18: TBC | C18: TBC | F18: Y-TC03 | G18: GEL LIMPIADOR FACIAL Y CORPORAL | H18: #VALUE! | I18: 100 mL | J18: Yuya | K18: Multicanal | L18: 1 | N18: MXN | O18: 20000 | P18: 0 | S18: 0 | T18: OGX $148 Tree Hut $178 Dove $294 | U18: 189 | V18: =(U18/1.16)*0.6 -> 97.758621 | W18: =+S18/V18 -> 0 | X18: =1-(S18/V18) -> 1 | Y18: 0.4 | Z18: Color | AA18: MX | AC18: Trabajando en igualación de fragancias. | BA18: 1 | BJ18: 9 | BK18: =SUM(BA18:BI18) -> 1 | BL18: =+BK18/BJ18 -> 0.11111111 | BS18: Autorización de fórmula y fragancia | BT18: =+AD18 -> 0 | BV18: NP
A19: 34 | B19: TBC | C19: TBC | E19: 7506110691594 | F19: Y-SBR01 | G19: Set brochas departamental (10 piezas) | H19: #VALUE! | I19: 10 brochas | J19: Yuya | K19: Multicanal | L19: 1 | N19: USD | O19: 20000 | P19: 0 | R19: 0 | S19: 0 | T19: Beauty Creations $599 Cosmetic Lab $249 ProCore $279 | U19: 899 | V19: =(U19/1.16)*0.6 -> 465 | W19: =+S19/V19 -> 0 | X19: =1-(S19/V19) -> 1 | Y19: 0.4 | Z19: Color | AA19: MX | BA19: 1 | BJ19: 9 | BK19: =SUM(BA19:BI19) -> 1 | BL19: =+BK19/BJ19 -> 0.11111111 | BS19: Elección de brochas del set de 24 | BT19: =+AD19 -> 0 | BV19: Sasu-Ari Glz
A20: 35 | B20: TBC | C20: TBC | E20: 7506110691600 | F20: Y-SBR02 | G20: Set brochas Autoservicio (5 piezas) | H20: #VALUE! | I20: 5 brochas | J20: Yuya | K20: Multicanal | L20: 1 | N20: USD | O20: 20000 | P20: 0 | R20: 0 | S20: 0 | T20: Ecotools $197 Cosmetic Lab $89 Kiss 189.90 Cala $360 | U20: 399 | V20: =(U20/1.16)*0.6 -> 206.37931 | W20: =+S20/V20 -> 0 | X20: =1-(S20/V20) -> 1 | Y20: 0.4 | Z20: Color | AA20: MX | AC20: Stand By | BA20: 1 | BJ20: 9 | BK20: =SUM(BA20:BI20) -> 1 | BL20: =+BK20/BJ20 -> 0.11111111 | BS20: Stand By | BT20: =+AD20 -> 0
A21: 36 | B21: TBC | C21: TBC | F21: Y-GC02 | G21: GEL DE CEJAS DE COLOR MEDIO | H21: #VALUE! | I21: 1.3 mL | J21: Yuya | K21: Multicanal | L21: 1 | N21: MXN | O21: 10000 | P21: 15.99 | S21: 15.99 | T21: NYX $258 Renova $150 Maybelline $239 | U21: 199 | V21: =(U21/1.16)*0.6 -> 102.93103 | W21: =+S21/V21 -> 0.15534673 | X21: =1-(S21/V21) -> 0.84465327 | Y21: 0.4 | AC21: Autorización de tono | BA21: 1 | BJ21: 9 | BK21: =SUM(BA21:BI21) -> 1 | BL21: =+BK21/BJ21 -> 0.11111111 | BS21: Autorización de tono | BT21: =+AD21 -> 0 | BV21: Sasu-Ari Glz
A22: 37 | B22: TBC | C22: TBC | F22: Y-GC03 | G22: GEL DE CEJAS DE COLOR OSCURO | H22: #VALUE! | I22: 1.3 mL | J22: Yuya | K22: Multicanal | L22: 1 | N22: MXN | O22: 10000 | P22: 15.99 | S22: 15.99 | T22: NYX $258 Renova $150 Maybelline $239 | U22: 199 | V22: =(U22/1.16)*0.6 -> 102.93103 | W22: =+S22/V22 -> 0.15534673 | X22: =1-(S22/V22) -> 0.84465327 | Y22: 0.4 | AC22: Autorización de tono | BA22: 1 | BJ22: 9 | BK22: =SUM(BA22:BI22) -> 1 | BL22: =+BK22/BJ22 -> 0.11111111 | BS22: Autorización de tono | BT22: =+AD22 -> 0 | BV22: Sasu-Ari Glz
A23: 38 | B23: TBC | C23: TBC | E23: 7506110694830 | F23: Y-SI01 | G23: SET DE 4 ILUMINADORES EN POLVO | H23: #VALUE! | J23: Yuya | K23: Multicanal | L23: 1 | N23: USD | O23: 20000 | P23: 0 | S23: 0 | T23: Pink Up $689 Milani $188 | U23: 299 | V23: =(U23/1.16)*0.6 -> 154.65517 | W23: =+S23/V23 -> 0 | X23: =1-(S23/V23) -> 1 | Y23: 0.4 | Z23: Color | AA23: MX | BA23: 1 | BJ23: 9 | BK23: =SUM(BA23:BI23) -> 1 | BL23: =+BK23/BJ23 -> 0.11111111 | BS23: Stand By | BT23: =+AD23 -> 0
A24: 39 | B24: TBC | C24: TBC | E24: 7506110694052 | F24: Y-CO01 | G24: Cosmetiquera Departamental 1 | H24: #VALUE! | I24: 1 pieza | J24: Yuya | K24: Multicanal | L24: 1 | M24: 4.2 | N24: USD | O24: 10000 | P24: 75.6 | S24: 90.72 | T24: Beauty Creations $107 Mytagalongs $499 Cloe $549 | U24: 499 | V24: =(U24/1.16)*0.6 -> 258.10345 | W24: =+S24/V24 -> 0.35148697 | X24: =1-(S24/V24) -> 0.64851303 | Y24: 0.3 | BA24: 1 | BJ24: 9 | BK24: =SUM(BA24:BI24) -> 1 | BL24: =+BK24/BJ24 -> 0.11111111 | BS24: Stand By | BT24: =+AD24 -> 0
A25: 40 | B25: TBC | C25: TBC | E25: 7506110694076 | F25: Y-CO03 | G25: Cosmetiquera de Regalo | H25: #VALUE! | I25: 1 pieza | J25: Yuya | K25: Multicanal | L25: 1 | M25: 2 | N25: USD | O25: 10000 | P25: 36 | S25: 43.2 | T25: Miniso $149 Conair $399 Beauty Creations $299 | U25: 229 | V25: =(U25/1.16)*0.6 -> 118.44828 | W25: =+S25/V25 -> 0.36471616 | X25: =1-(S25/V25) -> 0.63528384 | Y25: 0.3 | Z25: Color | AA25: MX | BA25: 1 | BJ25: 9 | BK25: =SUM(BA25:BI25) -> 1 | BL25: =+BK25/BJ25 -> 0.11111111 | BS25: Stand By | BT25: =+AD25 -> 0
A26: 46 | B26: TBC | C26: TBC | E26: 7506110694014 | F26: Y-JB01 | G26: JABON EN BARRA 1 | H26: #VALUE! | I26: 90 g | J26: Yuya | K26: Multicanal | L26: 1 | N26: USD | O26: 20000 | P26: 0 | S26: 0 | T26: Dove $33 Natura $88 Palmolive $23 | U26: 79 | V26: =(U26/1.16)*0.6 -> 40.862069 | W26: =+S26/V26 -> 0 | X26: =1-(S26/V26) -> 1 | Y26: 0.4 | Z26: Color | AA26: MX | BA26: 1 | BJ26: 9 | BK26: =SUM(BA26:BI26) -> 1 | BL26: =+BK26/BJ26 -> 0.11111111 | BT26: =+AD26 -> 0
A27: 47 | B27: TBC | C27: TBC | E27: 7506110694021 | F27: Y-JB02 | G27: JABON EN BARRA 2 | H27: #VALUE! | I27: 90 g | J27: Yuya | K27: Multicanal | L27: 1 | N27: USD | O27: 20000 | P27: 0 | S27: 0 | T27: Dove $33 Natura $88 Palmolive $23 | U27: 79 | V27: =(U27/1.16)*0.6 -> 40.862069 | W27: =+S27/V27 -> 0 | X27: =1-(S27/V27) -> 1 | Y27: 0.4 | Z27: Color | AA27: MX | BA27: 1 | BJ27: 9 | BK27: =SUM(BA27:BI27) -> 1 | BL27: =+BK27/BJ27 -> 0.11111111 | BS27: 0 | BT27: =+AD27 -> 0
A28: 48 | B28: TBC | C28: TBC | F28: Y-CF01 | G28: CREMA FACIAL EN GEL | H28: #VALUE! | I28: 50 g | J28: Yuya | K28: Multicanal | L28: 1 | N28: USD | O28: 20000 | P28: 0 | S28: 0 | T28: Ponds $154 Garnier $119 Ponds $120 | U28: 119 | V28: =(U28/1.16)*0.6 -> 61.551724 | W28: =+S28/V28 -> 0 | X28: =1-(S28/V28) -> 1 | Y28: 0.4 | BA28: 1 | BJ28: 9 | BK28: =SUM(BA28:BI28) -> 1 | BL28: =+BK28/BJ28 -> 0.11111111 | BS28: 0 | BT28: =+AD28 -> 0
A29: 49 | B29: TBC | C29: TBC | G29: PLANCHA ALACIADORA | H29: #VALUE! | I29: 1 pieza | J29: Yuya | K29: Multicanal | L29: 1 | N29: USD | O29: 10000 | P29: 0 | S29: 0 | T29: Revlon $475 Remington $559 Conair $499 | U29: 699 | V29: =(U29/1.16)*0.6 -> 361.55172 | W29: =+S29/V29 -> 0 | X29: =1-(S29/V29) -> 1 | Y29: 0.4 | BA29: 1 | BJ29: 9 | BK29: =SUM(BA29:BI29) -> 1 | BL29: =+BK29/BJ29 -> 0.11111111 | BS29: 0 | BT29: =+AD29 -> 0
A30: 50 | B30: TBC | C30: TBC | G30: CEPILLO SECADOR | H30: #VALUE! | I30: 1 pieza | J30: Yuya | K30: Multicanal | L30: 1 | N30: USD | O30: 10000 | P30: 0 | S30: 0 | T30: Revlon $929 Timco $526 Conair $399 | U30: 599 | V30: =(U30/1.16)*0.6 -> 309.82759 | W30: =+S30/V30 -> 0 | X30: =1-(S30/V30) -> 1 | Y30: 0.4 | BA30: 1 | BJ30: 9 | BK30: =SUM(BA30:BI30) -> 1 | BL30: =+BK30/BJ30 -> 0.11111111 | BS30: 0 | BT30: =+AD30 -> 0
A31: 51 | B31: TBC | C31: TBC | G31: BEAUTY BLENDER | H31: #VALUE! | I31: 1 pieza | J31: Yuya | K31: Multicanal | L31: 1 | M31: 0.42 | N31: USD | O31: 10000 | P31: 7.56 | Q31: 0.5292 | R31: 0.161784 | S31: 8.250984 | T31: Real Techniques $156 Beauty Cretions $56.84 | U31: 599 | V31: =(U31/1.16)*0.6 -> 309.82759 | W31: =+S31/V31 -> 0.026630889 | X31: =1-(S31/V31) -> 0.97336911 | Y31: 0.4 | BA31: 1 | BJ31: 9 | BK31: =SUM(BA31:BI31) -> 1 | BL31: =+BK31/BJ31 -> 0.11111111 | BS31: 0 | BT31: =+AD31 -> 0
A32: 52 | B32: TBC | C32: TBC | F32: Y-SH05 | G32: Shampoo protección calor | K32: Multicanal | L32: 1 | N32: USD | O32: 20002 | P32: 0 | S32: 16.53 | T32: 249 | U32: 89 | V32: =(U32/1.16)*0.6 -> 46.034483 | W32: =+S32/V32 -> 0.35907865 | X32: =1-(S32/V32) -> 0.64092135 | Y32: 0.4 | BA32: 1 | BJ32: 9 | BK32: =SUM(BA32:BI32) -> 1 | BL32: =+BK32/BJ32 -> 0.11111111 | BS32: 0 | BT32: =+AD32 -> 0
A33: 53 | B33: TBC | C33: TBC | F33: Y-SH06 | G33: Shampoo anticaida | K33: Multicanal | L33: 1 | N33: USD | O33: 20003 | P33: 0 | S33: 17.89 | T33: 249 | U33: 89 | V33: =(U33/1.16)*0.6 -> 46.034483 | W33: =+S33/V33 -> 0.38862172 | X33: =1-(S33/V33) -> 0.61137828 | Y33: 0.4 | BA33: 1 | BJ33: 9 | BK33: =SUM(BA33:BI33) -> 1 | BL33: =+BK33/BJ33 -> 0.11111111 | BS33: 0 | BT33: =+AD33 -> 0
A34: 54 | B34: TBC | C34: TBC | F34: Y-AC05 | G34: Acondicionador protección calor | K34: Multicanal | L34: 1 | N34: USD | O34: 20005 | P34: 0 | S34: 17.89 | T34: 249 | U34: 89 | V34: =(U34/1.16)*0.6 -> 46.034483 | W34: =+S34/V34 -> 0.38862172 | X34: =1-(S34/V34) -> 0.61137828 | Y34: 0.4 | BA34: 1 | BJ34: 9 | BK34: =SUM(BA34:BI34) -> 1 | BL34: =+BK34/BJ34 -> 0.11111111 | BS34: 0 | BT34: =+AD34 -> 0
A35: 55 | B35: TBC | C35: TBC | F35: Y-AC06 | G35: Acondicionador anticaida | K35: Multicanal | L35: 1 | N35: USD | O35: 20006 | P35: 0 | S35: 17.89 | T35: 249 | U35: 89 | V35: =(U35/1.16)*0.6 -> 46.034483 | W35: =+S35/V35 -> 0.38862172 | X35: =1-(S35/V35) -> 0.61137828 | Y35: 0.4 | BA35: 1 | BJ35: 9 | BK35: =SUM(BA35:BI35) -> 1 | BL35: =+BK35/BJ35 -> 0.11111111 | BS35: 0 | BT35: =+AD35 -> 0
A36: 56 | B36: TBC | C36: TBC | F36: Y-MC05 | G36: Tratamiento Capilar protección calor | K36: Multicanal | L36: 1 | N36: USD | O36: 20008 | P36: 0 | S36: 15.9 | T36: 249 | U36: 79 | V36: =(U36/1.16)*0.6 -> 40.862069 | W36: =+S36/V36 -> 0.38911392 | X36: =1-(S36/V36) -> 0.61088608 | Y36: 0.4 | BA36: 1 | BJ36: 9 | BK36: =SUM(BA36:BI36) -> 1 | BL36: =+BK36/BJ36 -> 0.11111111 | BS36: 0 | BT36: =+AD36 -> 0
A37: 57 | B37: TBC | C37: TBC | F37: Y-MC06 | G37: Tratamiento Capilar anticaida | K37: Multicanal | L37: 1 | N37: USD | O37: 20009 | P37: 0 | S37: 15.9 | T37: 249 | U37: 79 | V37: =(U37/1.16)*0.6 -> 40.862069 | W37: =+S37/V37 -> 0.38911392 | X37: =1-(S37/V37) -> 0.61088608 | Y37: 0.4 | BA37: 1 | BJ37: 9 | BK37: =SUM(BA37:BI37) -> 1 | BL37: =+BK37/BJ37 -> 0.11111111 | BS37: 0 | BT37: =+AD37 -> 0
A38: 20 | B38: TBC | C38: 46447 | D38: En tiempo | E38: 7506110694786 | F38: Y-G28 | G38: LABIAL LIQUIDO Nueva Formula | H38: #VALUE! | I38: 4 g | J38: Yuya | K38: Multicanal | L38: 1 | M38: 0.98 | N38: USD | O38: 20000 | P38: 17.64 | Q38: 6.3504 | R38: 1.4034384 | S38: 25.393838 | T38: Maybelline $279 Spectra $277 Vixen $145 | U38: 179 | V38: =(U38/1.16)*0.6 -> 92.586207 | W38: =+S38/V38 -> 0.27427237 | X38: =1-(S38/V38) -> 0.72572763 | Y38: 0.4 | Z38: Color | AA38: MX | AC38: Proveedor está proponiendo tonos | AD38: tbc | BA38: 1 | BJ38: 9 | BK38: =SUM(BA38:BI38) -> 1 | BL38: =+BK38/BJ38 -> 0.11111111 | BS38: Viabilidad | BT38: =+AD38 -> tbc | BV38: MKT
A39: 21 | B39: TBC | C39: 46447 | D39: En tiempo | E39: 7506110694793 | F39: Y-G29 | G39: LABIAL LIQUIDO Nueva Formula | H39: #VALUE! | I39: 4 g | J39: Yuya | K39: Multicanal | L39: 1 | M39: 0.98 | N39: USD | O39: 20000 | P39: 17.64 | Q39: 6.3504 | R39: 1.4034384 | S39: 25.393838 | T39: Maybelline $279 Spectra $277 Vixen $145 | U39: 179 | V39: =(U39/1.16)*0.6 -> 92.586207 | W39: =+S39/V39 -> 0.27427237 | X39: =1-(S39/V39) -> 0.72572763 | Y39: 0.4 | Z39: Color | AA39: MX | AC39: Proveedor está proponiendo tonos | AD39: tbc | BA39: 1 | BJ39: 9 | BK39: =SUM(BA39:BI39) -> 1 | BL39: =+BK39/BJ39 -> 0.11111111 | BS39: Viabilidad | BT39: =+AD39 -> tbc | BV39: MKT
A40: 22 | B40: TBC | C40: 46447 | D40: En tiempo | E40: 7506110694809 | F40: Y-G30 | G40: LABIAL LIQUIDO Nueva Formula | H40: #VALUE! | I40: 4 g | J40: Yuya | K40: Multicanal | L40: 1 | M40: 0.98 | N40: USD | O40: 20000 | P40: 17.64 | Q40: 6.3504 | R40: 1.4034384 | S40: 25.393838 | T40: Maybelline $279 Spectra $277 Vixen $145 | U40: 179 | V40: =(U40/1.16)*0.6 -> 92.586207 | W40: =+S40/V40 -> 0.27427237 | X40: =1-(S40/V40) -> 0.72572763 | Y40: 0.4 | Z40: Color | AA40: MX | AC40: Proveedor está proponiendo tonos | AD40: tbc | BA40: 1 | BJ40: 9 | BK40: =SUM(BA40:BI40) -> 1 | BL40: =+BK40/BJ40 -> 0.11111111 | BS40: Viabilidad | BT40: =+AD40 -> tbc | BV40: MKT
A41: 23 | B41: TBC | C41: 46447 | D41: En tiempo | E41: 7506110694816 | F41: Y-G31 | G41: LABIAL LIQUIDO Nueva Formula | H41: #VALUE! | I41: 4 g | J41: Yuya | K41: Multicanal | L41: 1 | M41: 0.98 | N41: USD | O41: 20000 | P41: 17.64 | Q41: 6.3504 | R41: 1.4034384 | S41: 25.393838 | T41: Maybelline $279 Spectra $277 Vixen $145 | U41: 179 | V41: =(U41/1.16)*0.6 -> 92.586207 | W41: =+S41/V41 -> 0.27427237 | X41: =1-(S41/V41) -> 0.72572763 | Y41: 0.4 | Z41: Color | AA41: MX | AC41: Proveedor está proponiendo tonos | AD41: tbc | BA41: 1 | BJ41: 9 | BK41: =SUM(BA41:BI41) -> 1 | BL41: =+BK41/BJ41 -> 0.11111111 | BS41: Viabilidad | BT41: =+AD41 -> tbc | BV41: MKT
A42: 24 | B42: TBC | C42: 46447 | D42: En tiempo | E42: 7506110694823 | F42: Y-G32 | G42: LABIAL LIQUIDO Nueva Formula | H42: #VALUE! | I42: 4 g | J42: Yuya | K42: Multicanal | L42: 1 | M42: 0.98 | N42: USD | O42: 20000 | P42: 17.64 | Q42: 6.3504 | R42: 1.4034384 | S42: 25.393838 | T42: Maybelline $279 Spectra $277 Vixen $145 | U42: 179 | V42: =(U42/1.16)*0.6 -> 92.586207 | W42: =+S42/V42 -> 0.27427237 | X42: =1-(S42/V42) -> 0.72572763 | Y42: 0.4 | Z42: Color | AA42: MX | AC42: Proveedor está proponiendo tonos | AD42: tbc | BA42: 1 | BJ42: 9 | BK42: =SUM(BA42:BI42) -> 1 | BL42: =+BK42/BJ42 -> 0.11111111 | BS42: Viabilidad | BT42: =+AD42 -> tbc | BV42: MKT
A43: 25 | B43: TBC | C43: 46478 | D43: En tiempo | E43: 7506110694830 | F43: Y-LGB01 | G43: LABIAL GLOSS EN BARRA | H43: #VALUE! | J43: Yuya | K43: Multicanal | L43: 1 | N43: USD | O43: 10000 | P43: 0 | Q43: 0 | R43: 0 | S43: 25.39 | T43: NYX $177 ELF $302 Loreal $387 | U43: 179 | V43: =(U43/1.16)*0.6 -> 92.586207 | W43: =+S43/V43 -> 0.27423091 | X43: =1-(S43/V43) -> 0.72576909 | Y43: 0.4 | Z43: Color | AA43: MX | AC43: Proveedor está proponiendo tonos | AD43: tbc | BA43: 1 | BJ43: 9 | BK43: =SUM(BA43:BI43) -> 1 | BL43: =+BK43/BJ43 -> 0.11111111 | BS43: Viabilidad | BT43: =+AD43 -> tbc | BV43: MKT
A44: 26 | B44: TBC | C44: 46478 | D44: En tiempo | F44: Y-LGB02 | G44: LABIAL GLOSS EN BARRA | H44: #VALUE! | J44: Yuya | K44: Multicanal | L44: 1 | N44: USD | O44: 10000 | P44: 0 | Q44: 0 | R44: 0 | S44: 25.39 | U44: 179 | V44: =(U44/1.16)*0.6 -> 92.586207 | W44: =+S44/V44 -> 0.27423091 | X44: =1-(S44/V44) -> 0.72576909 | Y44: 0.4 | AC44: Proveedor está proponiendo tonos | AD44: tbc | BA44: 1 | BJ44: 9 | BK44: =SUM(BA44:BI44) -> 1 | BL44: =+BK44/BJ44 -> 0.11111111 | BS44: Viabilidad | BT44: =+AD44 -> tbc | BV44: MKT
A45: 17 | B45: TBC | C45: 46419 | D45: En tiempo | E45: 7502327992752 | F45: Y-DE2 | G45: BÁLSAMO DESMAQUILLANTE | H45: #VALUE! | I45: 140 g | J45: Yuya | K45: Multicanal | L45: 1 | M45: 1.65 | N45: USD | O45: 20000 | P45: 29.7 | Q45: 7.425 | R45: 2.0010375 | S45: 39.126038 | T45: Beauty Creations $258 L.A Girl $220 Cerave $390 Neutrogena $395 | U45: 259 | V45: =(U45/1.16)*0.6 -> 133.96552 | W45: =+S45/V45 -> 0.29206051 | X45: =1-(S45/V45) -> 0.70793949 | Y45: 0.4 | Z45: Color | AA45: MX | AC45: Render para enviar a autorización en proceso | AD45: 46366 | BA45: 1 | BB45: 1 | BC45: 1 | BD45: 1 | BE45: 1 | BJ45: 9 | BK45: =SUM(BA45:BI45) -> 5 | BL45: =+BK45/BJ45 -> 0.55555556 | BS45: Autorización de render | BT45: =+AD45 -> 46366 | BV45: Sasu-Ari Glz
A46: 10 | B46: TBC | C46: 46388 | D46: En tiempo | E46: 7502327992646 | F46: Y-D01 | G46: Delineador en lápiz negro | H46: #VALUE! | I46: 1.2 g | J46: Yuya | K46: Multicanal | L46: 1 | M46: 18.31 | N46: MXN | O46: 20000 | P46: 18.31 | S46: 18.31 | T46: Revlon $114 NYX $169 Renova $110 | U46: 149 | V46: =(U46/1.16)*0.6 -> 77.068966 | W46: =+S46/V46 -> 0.23757942 | X46: =1-(S46/V46) -> 0.76242058 | Y46: 0.4 | Z46: Color | AA46: MX | AC46: En espera de aprobacion final | AD46: 46329 | BA46: 1 | BB46: 1 | BC46: 1 | BD46: 1 | BE46: 1 | BF46: 1 | BG46: 1 | BJ46: 9 | BK46: =SUM(BA46:BI46) -> 7 | BL46: =+BK46/BJ46 -> 0.77777778 | BS46: Se envío a Yuya para vobo. | BT46: =+AD46 -> 46329 | BV46: Sasu-Ari Glz
A47: 11 | B47: TBC | C47: 46388 | D47: En tiempo | E47: 7502327992653 | F47: Y-D02 | G47: Delineador en lápiz café | H47: #VALUE! | I47: 1.2 g | J47: Yuya | K47: Multicanal | L47: 1 | M47: 18.31 | N47: MXN | O47: 20000 | P47: 18.31 | S47: 18.31 | T47: Revlon $114 NYX $169 Renova $111 | U47: 149 | V47: =(U47/1.16)*0.6 -> 77.068966 | W47: =+S47/V47 -> 0.23757942 | X47: =1-(S47/V47) -> 0.76242058 | Y47: 0.4 | Z47: Color | AA47: MX | AC47: En espera de aprobacion final | AD47: 46329 | BA47: 1 | BB47: 1 | BC47: 1 | BD47: 1 | BE47: 1 | BF47: 1 | BG47: 1 | BJ47: 9 | BK47: =SUM(BA47:BI47) -> 7 | BL47: =+BK47/BJ47 -> 0.77777778 | BS47: Se envío a Yuya para vobo. | BT47: =+AD47 -> 46329 | BV47: Sasu-Ari Glz
A48: 12 | B48: TBC | C48: 46388 | D48: En tiempo | E48: 7502327992660 | F48: Y-D03 | G48: Delineador en lápiz bronce claro | H48: #VALUE! | I48: 1.2 g | J48: Yuya | K48: Multicanal | L48: 1 | M48: 18.31 | N48: MXN | O48: 20000 | P48: 18.31 | S48: 18.31 | T48: Revlon $114 NYX $169 Renova $112 | U48: 149 | V48: =(U48/1.16)*0.6 -> 77.068966 | W48: =+S48/V48 -> 0.23757942 | X48: =1-(S48/V48) -> 0.76242058 | Y48: 0.4 | Z48: Color | AA48: MX | AC48: En espera de aprobacion final | AD48: 46329 | BA48: 1 | BB48: 1 | BC48: 1 | BD48: 1 | BE48: 1 | BF48: 1 | BG48: 1 | BJ48: 9 | BK48: =SUM(BA48:BI48) -> 7 | BL48: =+BK48/BJ48 -> 0.77777778 | BS48: Se envío a Yuya para vobo. | BT48: =+AD48 -> 46329 | BV48: Sasu-Ari Glz
A49: 13 | B49: TBC | C49: 46388 | D49: En tiempo | E49: 7502327992677 | F49: Y-D04 | G49: Delineador en lápiz café - morado | H49: #VALUE! | I49: 1.2 g | J49: Yuya | K49: Multicanal | L49: 1 | M49: 18.31 | N49: MXN | O49: 20000 | P49: 18.31 | S49: 18.31 | T49: Revlon $114 NYX $169 Renova $113 | U49: 149 | V49: =(U49/1.16)*0.6 -> 77.068966 | W49: =+S49/V49 -> 0.23757942 | X49: =1-(S49/V49) -> 0.76242058 | Y49: 0.4 | Z49: Color | AA49: MX | AC49: En espera de aprobacion final | AD49: 46329 | BA49: 1 | BB49: 1 | BC49: 1 | BD49: 1 | BE49: 1 | BF49: 1 | BG49: 1 | BJ49: 9 | BK49: =SUM(BA49:BI49) -> 7 | BL49: =+BK49/BJ49 -> 0.77777778 | BS49: Se envío a Yuya para vobo. | BT49: =+AD49 -> 46329 | BV49: Sasu-Ari Glz
A50: 14 | B50: TBC | C50: 46388 | D50: En tiempo | E50: 7502327992684 | F50: Y-D05 | G50: Delineador en lápiz café nude | H50: #VALUE! | I50: 1.2 g | J50: Yuya | K50: Multicanal | L50: 1 | M50: 18.31 | N50: MXN | O50: 20000 | P50: 18.31 | S50: 18.31 | T50: Revlon $114 NYX $169 Renova $114 | U50: 149 | V50: =(U50/1.16)*0.6 -> 77.068966 | W50: =+S50/V50 -> 0.23757942 | X50: =1-(S50/V50) -> 0.76242058 | Y50: 0.4 | Z50: Color | AA50: MX | AC50: En espera de aprobacion final | AD50: 46329 | BA50: 1 | BB50: 1 | BC50: 1 | BD50: 1 | BE50: 1 | BF50: 1 | BG50: 1 | BJ50: 9 | BK50: =SUM(BA50:BI50) -> 7 | BL50: =+BK50/BJ50 -> 0.77777778 | BS50: Se envío a Yuya para vobo. | BT50: =+AD50 -> 46329 | BV50: Sasu-Ari Glz
A51: 15 | B51: TBC | C51: 46388 | D51: En tiempo | E51: 7502327992691 | F51: Y-D06 | G51: Delineador en lápiz verde olivo | H51: #VALUE! | I51: 1.2 g | J51: Yuya | K51: Multicanal | L51: 1 | M51: 18.31 | N51: MXN | O51: 20000 | P51: 18.31 | S51: 18.31 | T51: Revlon $114 NYX $169 Renova $110 | U51: 149 | V51: =(U51/1.16)*0.6 -> 77.068966 | W51: =+S51/V51 -> 0.23757942 | X51: =1-(S51/V51) -> 0.76242058 | Y51: 0.4 | Z51: Color | AA51: MX | AC51: En espera de aprobacion final | AD51: 46329 | BA51: 1 | BB51: 1 | BC51: 1 | BD51: 1 | BE51: 1 | BF51: 1 | BG51: 1 | BJ51: 9 | BK51: =SUM(BA51:BI51) -> 7 | BL51: =+BK51/BJ51 -> 0.77777778 | BS51: Se envío a Yuya para vobo. | BT51: =+AD51 -> 46329 | BV51: Sasu-Ari Glz

Sheet Yuya 2026
CJ14: SEGUIMIENTO DE FECHAS
CJ15: PPEDIDOS | CL15: PREPRODCCION | CN15: AUTORIZACIÓN MARCA | CP15: DISPONIBILIDAD | CR15: DOCUMENTOS PROVEEDOR | CT15: PICK UP DE MERCANCIA | CV15: SALIDA DE LIS | CX15: LLEGADA A ADUANA | CZ15: DISPONIBILIDAD EN ALMACEN
A16: # | B16: Fecha confirmada de Lanzamiento | C16: Mes de Lanzamiento (Esperado) | D16: Estatus | E16: EAN | F16: Código interno | G16: Nombre Comercial | H16: Imagen | I16: Contenido | J16: Marca | K16: Canales | L16: Fase | M16: Costo real (USD) | N16: Moneda | O16: Piezas cotizadas (MOQ) | P16: Costo Esperado en MXN | Q16: IGI | R16: Incrementables | S16: Costo final en MXN (FOB en almacén PT) | T16: Precio Benchmark | U16: Precio publico C/IVA | V16: Facturación por unidad | W16: Factor costo | X16: Margen de utilidad bruta | Y16: MU Cliente | Z16: Categoria | AA16: Pais de origen | AB16: Benchmark | AC16: Comentarios | AD16: Disponibilidad en Almacén | BA16: Line Up | BB16: Costo Autorizado | BC16: PVP Autorizado | BD16: Formula autorizada | BE16: Vobo CEO + VPs | BF16: Arte Final | BG16: PO | BH16: Salida de LIS | BI16: Disponibilidad en almacén | BJ16: Total | BK16: Estatus | BL16: % de Avance | BS16: Comentarios (Qué falta) | BT16: Disponibilidad en almacén | BU16: LIS # | BV16: Responsable Siguiente paso | CJ16: ESPERADA | CK16: REAL | CL16: ESPERADA | CM16: REAL | CN16: ESPERADA | CO16: REAL | CP16: ESPERADA | CQ16: REAL | CR16: ESPERADA | CS16: REAL | CT16: ESPERADA | CU16: REAL | CV16: ESPERADA | CW16: REAL | CX16: ESPERADA | CY16: REAL | CZ16: ESPERADA | DA16: REAL
A17: 1 | B17: 46044 | C17: Enero | D17: Completado | E17: 7506110695028 | F17: Y-PP02 | G17: PARCHES AUXILIAR PARA GRANITOS ESTRELLAS | H17: #VALUE! | I17: 36 Parches | J17: Yuya | K17: Multicanal | L17: 1 | M17: 0.43 | N17: USD | O17: 30000 | P17: 7.74 | R17: 1.548 | S17: 10.16 | T17: Garnier $150 StarFace $300 | U17: 89 | V17: =(U17/1.16)*0.6 -> 46.034483 | W17: =+S17/V17 -> 0.22070412 | X17: =1-(S17/V17) -> 0.77929588 | Y17: 0.4 | Z17: Color | AA17: CN | AC17: Terminado | AD17: 45992 | BA17: 1 | BB17: 1 | BC17: 1 | BD17: 1 | BE17: 1 | BF17: 1 | BG17: 1 | BH17: 1 | BI17: 1 | BJ17: 9 | BK17: =SUM(BA17:BI17) -> 9 | BL17: =+BK17/BJ17 -> 1 | BS17: Terminado | BT17: =+AD17 -> 45992 | BV17: Comercial | CJ17: 45809 | CK17: 45809 | CL17: =+CJ17+10 -> 45819 | CM17: =+CK17+10 -> 45819 | CN17: =+CL17+14 -> 45833 | CO17: =+CM17+14 -> 45833 | CP17: =+CN17+40 -> 45873 | CQ17: =+CO17+40 -> 45873 | CR17: =+CP17-15 -> 45858 | CT17: =+CP17+7 -> 45880 | CV17: =+CT17+5 -> 45885 | CX17: =+CV17+45 -> 45930 | CZ17: =+CX17+8 -> 45938
A18: 2 | B18: 46044 | C18: Enero | D18: Completado | E18: 7506110695035 | F18: Y-PP03 | G18: PARCHES AUXILIAR PARA GRANITOS CORAZONES | H18: #VALUE! | I18: 24 Parches | J18: Yuya | K18: Multicanal | L18: 1 | M18: 0.43 | N18: USD | O18: 30000 | P18: 7.74 | R18: 1.548 | S18: 10.16 | T18: Garnier $150 StarFace $300 | U18: 89 | V18: =(U18/1.16)*0.6 -> 46.034483 | W18: =+S18/V18 -> 0.22070412 | X18: =1-(S18/V18) -> 0.77929588 | Y18: 0.4 | Z18: Color | AA18: CN | AC18: Terminado | AD18: 45992 | BA18: 1 | BB18: 1 | BC18: 1 | BD18: 1 | BE18: 1 | BF18: 1 | BG18: 1 | BH18: 1 | BI18: 1 | BJ18: 9 | BK18: =SUM(BA18:BI18) -> 9 | BL18: =+BK18/BJ18 -> 1 | BS18: Terminado | BT18: =+AD18 -> 45992 | BV18: Comercial
A19: 3 | B19: 46044 | C19: Enero | D19: Completado | E19: 7506110695042 | F19: Y-PP04 | G19: PARCHES AUXILIAR PARA GRANITOS FLORES CON DIAMANTES | H19: #VALUE! | I19: 24 Parches | J19: Yuya | K19: Multicanal | L19: 1 | M19: 0.77 | N19: USD | O19: 30000 | P19: 13.86 | R19: 2.772 | S19: 18.19 | T19: Garnier $150 StarFace $300 | U19: 139 | V19: =(U19/1.16)*0.6 -> 71.896552 | W19: =+S19/V19 -> 0.2530024 | X19: =1-(S19/V19) -> 0.7469976 | Y19: 0.4 | Z19: Color | AA19: CN | AC19: Terminado | AD19: 45992 | BA19: 1 | BB19: 1 | BC19: 1 | BD19: 1 | BE19: 1 | BF19: 1 | BG19: 1 | BH19: 1 | BI19: 1 | BJ19: 9 | BK19: =SUM(BA19:BI19) -> 9 | BL19: =+BK19/BJ19 -> 1 | BS19: Terminado | BT19: =+AD19 -> 45992 | BV19: Comercial
A20: 4 | C20: Mayo | D20: Completado | F20: Y-SW012 | G20: Set Trío Body Mist Yuya (60 mL) "Jardín Silvestre" | J20: Yuya | S20: 30.98 | U20: 199 | V20: =(U20/1.16)*0.6 -> 102.93103 | W20: =+S20/V20 -> 0.30097822 | X20: =1-(S20/V20) -> 0.69902178 | Y20: 1.4 | Z20: Sets | AA20: MX | AD20: 46143 | BA20: 1 | BB20: 1 | BC20: 1 | BD20: 1 | BE20: 1 | BF20: 1 | BG20: 1 | BH20: 1 | BI20: 1 | BJ20: 9 | BK20: =SUM(BA20:BI20) -> 9 | BL20: =+BK20/BJ20 -> 1 | BS20: Terminado | BT20: =+AD20 -> 46143 | BV20: Comercial
A21: 5 | C21: Mayo | D21: Completado | F21: Y-SW011 | G21: Set Duo Body Mist Yuya (236 mL) "Néctar de Nubes" | J21: Yuya | S21: 57.15 | U21: 290 | V21: =(U21/1.16)*0.6 -> 150 | W21: =+S21/V21 -> 0.381 | X21: =1-(S21/V21) -> 0.619 | Y21: 2.4 | Z21: Sets | AA21: MX | AD21: 46143 | BA21: 1 | BB21: 1 | BC21: 1 | BD21: 1 | BE21: 1 | BF21: 1 | BG21: 1 | BH21: 1 | BI21: 1 | BJ21: 9 | BK21: =SUM(BA21:BI21) -> 9 | BL21: =+BK21/BJ21 -> 1 | BS21: Terminado | BT21: =+AD21 -> 46143 | BV21: Comercial
A22: 6 | C22: Mayo | D22: Completado | F22: Y-SD001 | G22: Jardin Vivo (Máscara para pestañas "10 aceites Naturales + Enchinador "Verde" + Desmaquillante 3 en 1) | J22: Yuya | S22: 72.65 | U22: 459 | V22: =(U22/1.16)*0.6 -> 237.41379 | W22: =+S22/V22 -> 0.30600581 | X22: =1-(S22/V22) -> 0.69399419 | Y22: 3.4 | Z22: Sets | AA22: MX | AD22: 46143 | BA22: 1 | BB22: 1 | BC22: 1 | BD22: 1 | BE22: 1 | BF22: 1 | BG22: 1 | BH22: 1 | BI22: 1 | BJ22: 9 | BK22: =SUM(BA22:BI22) -> 9 | BL22: =+BK22/BJ22 -> 1 | BS22: Terminado | BT22: =+AD22 -> 46143 | BV22: Comercial
C23: Mayo | D23: Completado | F23: Y-SD002 | G23: Alta Frecuencia (Máscara para pestañas "10 aceites Naturales" Negra + Máscara de pestañas Borgoña + Enchinador Borgoña) | J23: Yuya | S23: 67.53 | U23: 499 | V23: =(U23/1.16)*0.6 -> 258.10345 | W23: =+S23/V23 -> 0.26163928 | X23: =1-(S23/V23) -> 0.73836072 | Y23: 4.4 | Z23: Sets | AA23: MX | AD23: 46143 | BA23: 1 | BB23: 1 | BC23: 1 | BD23: 1 | BE23: 1 | BF23: 1 | BG23: 1 | BH23: 1 | BI23: 1 | BJ23: 9 | BK23: =SUM(BA23:BI23) -> 9 | BL23: =+BK23/BJ23 -> 1 | BS23: Terminado | BT23: =+AD23 -> 46143 | BV23: Comercial
C24: Mayo | D24: Completado | F24: Y-SD003 | G24: Ciclo (Máscara 10 aceites negra + Desmaquillante 3 en 1 + Gel para cejas Yuya) | J24: Yuya | S24: 69.93 | U24: 499 | V24: =(U24/1.16)*0.6 -> 258.10345 | W24: =+S24/V24 -> 0.27093788 | X24: =1-(S24/V24) -> 0.72906212 | Y24: 5.4 | Z24: Sets | AA24: MX | AD24: 46143 | BA24: 1 | BB24: 1 | BC24: 1 | BD24: 1 | BE24: 1 | BF24: 1 | BG24: 1 | BH24: 1 | BI24: 1 | BJ24: 9 | BK24: =SUM(BA24:BI24) -> 9 | BL24: =+BK24/BJ24 -> 1 | BS24: Terminado | BT24: =+AD24 -> 46143 | BV24: Comercial
C25: Mayo | D25: Completado | F25: Y-SD004 | G25: Elemental (Máscara para pestañas 10 aceites Yuya + Gel para cejas Yuya) | J25: Yuya | S25: 45.06 | U25: 299 | V25: =(U25/1.16)*0.6 -> 154.65517 | W25: =+S25/V25 -> 0.29135786 | X25: =1-(S25/V25) -> 0.70864214 | Y25: 6.4 | Z25: Sets | AA25: MX | AD25: 46143 | BA25: 1 | BB25: 1 | BC25: 1 | BD25: 1 | BE25: 1 | BF25: 1 | BG25: 1 | BH25: 1 | BI25: 1 | BJ25: 9 | BK25: =SUM(BA25:BI25) -> 9 | BL25: =+BK25/BJ25 -> 1 | BS25: Terminado | BT25: =+AD25 -> 46143 | BV25: Comercial
C26: Mayo | D26: Completado | F26: Y-SD005 | G26: Luz Calida (Máscara para pestañas 10 aceites Yuya + Enchinador Borgoña) | J26: Yuya | S26: 48.59 | U26: 299 | V26: =(U26/1.16)*0.6 -> 154.65517 | W26: =+S26/V26 -> 0.31418283 | X26: =1-(S26/V26) -> 0.68581717 | Y26: 7.4 | Z26: Sets | AA26: MX | AD26: 46143 | BA26: 1 | BB26: 1 | BC26: 1 | BD26: 1 | BE26: 1 | BF26: 1 | BG26: 1 | BH26: 1 | BI26: 1 | BJ26: 9 | BK26: =SUM(BA26:BI26) -> 9 | BL26: =+BK26/BJ26 -> 1 | BS26: Terminado | BT26: =+AD26 -> 46143 | BV26: Comercial
C27: Mayo | D27: Completado | F27: Y-SD006 | G27: Frecuencia (Máscara para pestañas 10 aceites Yuya + Desmaquillante bifásico 10 aceites Yuya) | J27: Yuya | S27: 53.53 | U27: 299 | V27: =(U27/1.16)*0.6 -> 154.65517 | W27: =+S27/V27 -> 0.34612486 | X27: =1-(S27/V27) -> 0.65387514 | Y27: 8.4 | Z27: Sets | AA27: MX | AD27: 46143 | BA27: 1 | BB27: 1 | BC27: 1 | BD27: 1 | BE27: 1 | BF27: 1 | BG27: 1 | BH27: 1 | BI27: 1 | BJ27: 9 | BK27: =SUM(BA27:BI27) -> 9 | BL27: =+BK27/BJ27 -> 1 | BS27: Terminado | BT27: =+AD27 -> 46143 | BV27: Comercial
C28: Mayo | D28: Completado | F28: Y-SD007 | G28: Tres en Loop (Enchinador "Borgoña" + Máscara para pestañas "10 aceites Naturales" negra + Gel para cejas YUYA) | J28: Yuya | S28: 65.33 | U28: 499 | V28: =(U28/1.16)*0.6 -> 258.10345 | W28: =+S28/V28 -> 0.25311556 | X28: =1-(S28/V28) -> 0.74688444 | Y28: 9.4 | Z28: Sets | AA28: MX | AD28: 46143 | BA28: 1 | BB28: 1 | BC28: 1 | BD28: 1 | BE28: 1 | BF28: 1 | BG28: 1 | BH28: 1 | BI28: 1 | BJ28: 9 | BK28: =SUM(BA28:BI28) -> 9 | BL28: =+BK28/BJ28 -> 1 | BS28: Terminado | BT28: =+AD28 -> 46143 | BV28: Comercial
A29: 4 | B29: TBC | C29: Agosto | D29: En tiempo | E29: 7506110691679 | F29: Y-PCC001 | G29: BRUMA PARA CUERPO Y CABELLO "Viento" | H29: #VALUE! | I29: 100 mL | J29: Yuya | K29: Multicanal | L29: 1 | M29: 22.81 | N29: MXN | O29: 35000 | P29: 0 | S29: 22.24 | T29: H6M $199 Grisi $85 Pink Up $118 Red By Kiss $139 | U29: 199 | V29: =(U29/1.16)*0.6 -> 102.93103 | W29: =+S29/V29 -> 0.216067 | X29: =1-(S29/V29) -> 0.783933 | Y29: 0.4 | Z29: Fragancia | AA29: MX/CN | AC29: En Producción | AD29: 46230 | BA29: 1 | BB29: 1 | BC29: 1 | BD29: 1 | BE29: 1 | BF29: 1 | BG29: 1 | BH29: 1 | BI29: 1 | BJ29: 9 | BK29: =SUM(BA29:BI29) -> 9 | BL29: =+BK29/BJ29 -> 1 | BS29: Terminado | BT29: =+AD29 -> 46230 | BV29: Comercial
A30: 5 | B30: TBC | C30: Agosto | D30: En tiempo | E30: 7506110691686 | F30: Y-PCC002 | G30: BRUMA PARA CUERPO Y CABELLO "Mango Luna" | H30: #VALUE! | I30: 100 mL | J30: Yuya | K30: Multicanal | L30: 1 | M30: 22.95 | N30: MXN | O30: 35000 | P30: 0 | S30: 22.4 | T30: H6M $199 Grisi $85 Pink Up $94 Red By Kiss $139 | U30: 199 | V30: =(U30/1.16)*0.6 -> 102.93103 | W30: =+S30/V30 -> 0.21762144 | X30: =1-(S30/V30) -> 0.78237856 | Y30: 0.4 | Z30: Fragancia | AA30: MX/CN | AC30: En Producción | AD30: 46230 | BA30: 1 | BB30: 1 | BC30: 1 | BD30: 1 | BE30: 1 | BF30: 1 | BG30: 1 | BH30: 1 | BI30: 1 | BJ30: 9 | BK30: =SUM(BA30:BI30) -> 9 | BL30: =+BK30/BJ30 -> 1 | BS30: Terminado | BT30: =+AD30 -> 46230 | BV30: Comercial
A31: 6 | B31: TBC | C31: Agosto | D31: En tiempo | E31: 7506110693925 | F31: Y-PCC003 | G31: BRUMA PARA CUERPO Y CABELLO "Vainilla Boreal" | H31: #VALUE! | I31: 100 mL | J31: Yuya | K31: Multicanal | L31: 1 | M31: 23.64 | N31: MXN | O31: 35000 | P31: 0 | S31: 22.76 | T31: H6M $199 Grisi $85 Pink Up $94 Red By Kiss $139 | U31: 199 | V31: =(U31/1.16)*0.6 -> 102.93103 | W31: =+S31/V31 -> 0.22111893 | X31: =1-(S31/V31) -> 0.77888107 | Y31: 0.4 | Z31: Fragancia | AA31: MX/CN | AC31: En Producción | AD31: 46230 | BA31: 1 | BB31: 1 | BC31: 1 | BD31: 1 | BE31: 1 | BF31: 1 | BG31: 1 | BH31: 1 | BI31: 1 | BJ31: 9 | BK31: =SUM(BA31:BI31) -> 9 | BL31: =+BK31/BJ31 -> 1 | BS31: Terminado | BT31: =+AD31 -> 46230 | BV31: Comercial
A32: 7 | B32: TBC | C32: Agosto | D32: En tiempo | E32: 7506110693932 | F32: Y-PCC004 | G32: BRUMA PARA CUERPO Y CABELLO "Bruma tropical" | H32: #VALUE! | I32: 100 mL | J32: Yuya | K32: Multicanal | L32: 1 | M32: 23.57 | N32: MXN | O32: 35000 | P32: 0 | S32: 22.62 | T32: H6M $199 Grisi $85 Pink Up $94 Red By Kiss $139 | U32: 199 | V32: =(U32/1.16)*0.6 -> 102.93103 | W32: =+S32/V32 -> 0.21975879 | X32: =1-(S32/V32) -> 0.78024121 | Y32: 0.4 | Z32: Fragancia | AA32: MX/CN | AC32: En Producción | AD32: 46230 | BA32: 1 | BB32: 1 | BC32: 1 | BD32: 1 | BE32: 1 | BF32: 1 | BG32: 1 | BH32: 1 | BI32: 1 | BJ32: 9 | BK32: =SUM(BA32:BI32) -> 9 | BL32: =+BK32/BJ32 -> 1 | BS32: Terminado | BT32: =+AD32 -> 46230 | BV32: Comercial
A33: 8 | B33: TBC | C33: JULIO | D33: En tiempo | E33: 7502327990765 | F33: Y-REP01 | G33: Repuestos Enchinador Borgoña | I33: 3 repuestos | J33: Yuya | K33: Multicanal | L33: 1 | M33: 0.17 | N33: USD | O33: 25000 | P33: =M33*18.5 -> 3.145 | R33: 0.1053 | S33: 3.5 | T33: By Apple $35 Shiseido $200 | U33: 59 | V33: =(U33/1.16)*0.6 -> 30.517241 | W33: =+S33/V33 -> 0.11468927 | X33: =1-(S33/V33) -> 0.88531073 | Y33: 0.4 | Z33: Color | AA33: MX | AC33: En Producción | AD33: 46207 | BA33: 1 | BB33: 1 | BC33: 1 | BD33: 1 | BE33: 1 | BF33: 1 | BG33: 1 | BH33: 1 | BI33: 1 | BJ33: 9 | BK33: =SUM(BA33:BI33) -> 9 | BL33: =+BK33/BJ33 -> 1 | BS33: Terminado | BT33: =+AD33 -> 46207 | BV33: Comercial
A34: 9 | B34: TBC | C34: JULIO | D34: En tiempo | E34: 7502327990772 | F34: Y-REP02 | G34: Repuestos Enchinador Verde | I34: 3 repuestos | J34: Yuya | K34: Multicanal | L34: 1 | M34: 0.17 | N34: USD | O34: 15000 | P34: =M34*18.5 -> 3.145 | R34: 0.1053 | S34: 3.5 | T34: By Apple $35 Shiseido $200 | U34: 59 | V34: =(U34/1.16)*0.6 -> 30.517241 | W34: =+S34/V34 -> 0.11468927 | X34: =1-(S34/V34) -> 0.88531073 | Y34: 0.4 | Z34: Color | AA34: MX | AC34: En Producción | AD34: 46207 | BA34: 1 | BB34: 1 | BC34: 1 | BD34: 1 | BE34: 1 | BF34: 1 | BG34: 1 | BH34: 1 | BI34: 1 | BJ34: 9 | BK34: =SUM(BA34:BI34) -> 9 | BL34: =+BK34/BJ34 -> 1 | BS34: Terminado | BT34: =+AD34 -> 46207 | BV34: Comercial
A35: 16 | B35: TBC | C35: Septiembre | D35: En tiempo | E35: 7506110694854 | F35: Y-TC01 | G35: Aceite Capilar 10 Aceites | I35: 100 mL | J35: Yuya | K35: Multicanal | L35: 1 | M35: 27.46 | N35: MXN | O35: 10000 | S35: 26.59 | T35: Elvive $195 Biometik $133 Dove $149 OGX $149 | U35: 195 | V35: =(U35/1.16)*0.6 -> 100.86207 | W35: =+S35/V35 -> 0.26362735 | X35: =1-(S35/V35) -> 0.73637265 | Y35: 0.4 | Z35: Color | AA35: MX | AC35: Orden de Compra | AD35: 46282 | BA35: 1 | BB35: 1 | BC35: 1 | BD35: 1 | BE35: 1 | BF35: 1 | BG35: 1 | BH35: 1 | BJ35: 9 | BK35: =SUM(BA35:BI35) -> 8 | BL35: =+BK35/BJ35 -> 0.88888889 | BS35: Terminado | BT35: =+AD35 -> 46282 | BV35: Comercial
A36: 18 | B36: TBC | C36: OCTUBRE | D36: En tiempo | E36: 7502327992707 | F36: Y-SM04 | G36: Paleta de Sombras Metalizada Órbita | H36: #VALUE! | I36: 12.6 g | J36: Yuya | K36: Multicanal | L36: 1 | N36: USD | O36: 20000 | P36: 0 | S36: 45.89 | T36: 295 | U36: 299 | V36: =(U36/1.16)*0.6 -> 154.65517 | W36: =+S36/V36 -> 0.29672464 | X36: =1-(S36/V36) -> 0.70327536 | Y36: 0.4 | Z36: Color | AA36: MX | AC36: Falta autorización en renders. Falta autorizar 2 tonos. | AD36: 46320 | BA36: 1 | BB36: 1 | BC36: 1 | BD36: 1 | BE36: 1 | BF36: 1 | BG36: 1 | BH36: 1 | BJ36: 9 | BK36: =SUM(BA36:BI36) -> 8 | BL36: =+BK36/BJ36 -> 0.88888889 | BS36: Salió el envío marítimo | BT36: =+AD36 -> 46320 | BV36: Logística
A37: 19 | B37: TBC | C37: OCTUBRE | D37: En tiempo | E37: 7502327992714 | F37: Y-SM05 | G37: Paleta de Sombras Metalizada Desvelo | H37: #VALUE! | I37: 12.6 g | J37: Yuya | K37: Multicanal | L37: 1 | N37: USD | O37: 20000 | P37: 0 | S37: 45.89 | T37: 295 | U37: 299 | V37: =(U37/1.16)*0.6 -> 154.65517 | W37: =+S37/V37 -> 0.29672464 | X37: =1-(S37/V37) -> 0.70327536 | Y37: 0.4 | Z37: Color | AA37: MX | AC37: Falta autorización en renders. Falta autorizar 2 tonos. | AD37: 46320 | BA37: 1 | BB37: 1 | BC37: 1 | BD37: 1 | BE37: 1 | BF37: 1 | BG37: 1 | BH37: 1 | BJ37: 9 | BK37: =SUM(BA37:BI37) -> 8 | BL37: =+BK37/BJ37 -> 0.88888889 | BS37: Salió el envío marítimo | BT37: =+AD37 -> 46320 | BV37: Logística
A38: 28 | B38: TBC | C38: Noviembre | D38: En tiempo | F38: Y-CA02 | G38: CALENDARIO DE ADVIENTO | H38: #VALUE! | I38: 1 caja + 12 regalos | J38: Yuya | K38: Multicanal | L38: 1 | N38: USD | O38: 20000 | P38: 0 | S38: 314.71 | U38: 1599 | V38: =(U38/1.16)*0.6 -> 827.06897 | W38: =+S38/V38 -> 0.3805124 | X38: =1-(S38/V38) -> 0.6194876 | Y38: 0.4 | Z38: Color | AA38: MX | AC38: Confirmación de costos con Arturo | AD38: 46335 | BA38: 1 | BB38: 1 | BC38: 1 | BD38: 1 | BE38: 1 | BF38: 1 | BG38: 1 | BH38: 1 | BJ38: 9 | BK38: =SUM(BA38:BI38) -> 8 | BL38: =+BK38/BJ38 -> 0.88888889 | BS38: Salió el envío marítimo | BT38: =+AD38 -> 46335 | BV38: Logística
C39: SEPTIEMBRE | D39: En tiempo | E39: 7506110696704 | F39: Y-SD008 | G39: Trilogía Máscara 10 Aceites Esenciales Negra+ Máscara 10 Aceites Café + Gel Fijador para Cejas | H39: #VALUE! | I39: 19 g | J39: Yuya | K39: Yuya | L39: Yuya | M39: Yuya | N39: Yuya | O39: Yuya | P39: Yuya | Q39: Yuya | R39: Yuya | S39: 59.86 | U39: 499 | V39: =(U39/1.16)*0.6 -> 258.10345 | W39: =+S39/V39 -> 0.23192251 | X39: =1-(S39/V39) -> 0.76807749 | Y39: 0.4 | Z39: Color | AA39: MX | AC39: Falta autorización de espejo | AD39: 46279 | BA39: 1 | BB39: 1 | BC39: 1 | BD39: 1 | BE39: 1 | BF39: 1 | BG39: 1 | BH39: 1 | BJ39: 9 | BK39: =SUM(BA39:BI39) -> 8 | BL39: =+BK39/BJ39 -> 0.88888889 | BS39: Terminado | BT39: =+AD39 -> 46279 | BV39: Comercial
C40: DICIEMBRE | D40: En tiempo | E40: 7506110696711 | F40: Y-SD009 | G40: Un segundo Tinta Multiusos Yin Yang+ Enchinador Verde Máscara 10 Aceites Esenciales Negra+ Espejo | J40: Yuya | K40: Yuya | L40: Yuya | M40: Yuya | N40: Yuya | O40: Yuya | P40: Yuya | Q40: Yuya | R40: Yuya | S40: 93.76 | U40: 499 | V40: =(U40/1.16)*0.6 -> 258.10345 | W40: =+S40/V40 -> 0.3632652 | X40: =1-(S40/V40) -> 0.6367348 | Y40: 1.4 | AA40: MX | AD40: 46286 | BA40: 1 | BB40: 1 | BC40: 1 | BD40: 1 | BE40: 1 | BF40: 1 | BG40: 1 | BH40: 1 | BJ40: 9 | BK40: =SUM(BA40:BI40) -> 8 | BL40: =+BK40/BJ40 -> 0.88888889 | BS40: Terminado | BT40: =+AD40 -> 46286 | BV40: Comercial
C41: SEPTIEMBRE | D41: En tiempo | E41: 7506110696728 | F41: Y-SD010 | G41: Tres momentos Máscara 10 Aceites Esenciales Negra+ Polvo Traslúcido + Gel Fijador para Cejas + Beauty Blender | J41: Yuya | K41: Yuya | L41: Yuya | M41: Yuya | N41: Yuya | O41: Yuya | P41: Yuya | Q41: Yuya | R41: Yuya | S41: 85.18 | U41: 599 | V41: =(U41/1.16)*0.6 -> 309.82759 | W41: =+S41/V41 -> 0.2749271 | X41: =1-(S41/V41) -> 0.7250729 | Y41: 2.4 | AA41: MX | AD41: 46279 | BA41: 1 | BB41: 1 | BC41: 1 | BD41: 1 | BE41: 1 | BF41: 1 | BG41: 1 | BH41: 1 | BJ41: 9 | BK41: =SUM(BA41:BI41) -> 8 | BL41: =+BK41/BJ41 -> 0.88888889 | BS41: Terminado | BT41: =+AD41 -> 46279 | BV41: Comercial
C42: SEPTIEMBRE | D42: En tiempo | E42: 7506110696735 | F42: Y-SD011 | G42: Todo Bien Parche Auxiliar para Granitos + Tratamiento Chau Granitos + Papel Arroz Serendipia | J42: Yuya | K42: Yuya | L42: Yuya | M42: Yuya | N42: Yuya | O42: Yuya | P42: Yuya | Q42: Yuya | R42: Yuya | S42: 55.04 | U42: 349 | V42: =(U42/1.16)*0.6 -> 180.51724 | W42: =+S42/V42 -> 0.30490162 | X42: =1-(S42/V42) -> 0.69509838 | Y42: 3.4 | AA42: MX | AD42: 46279 | BA42: 1 | BB42: 1 | BC42: 1 | BD42: 1 | BE42: 1 | BF42: 1 | BG42: 1 | BH42: 1 | BJ42: 9 | BK42: =SUM(BA42:BI42) -> 8 | BL42: =+BK42/BJ42 -> 0.88888889 | BS42: Terminado | BT42: =+AD42 -> 46279 | BV42: Comercial
C43: SEPTIEMBRE | D43: En tiempo | E43: 7506110696742 | F43: Y-SD012 | G43: Dual Máscara 10 Aceites Esenciales Negra+ Máscara 10 Aceites Borgoña | J43: Yuya | K43: Yuya | L43: Yuya | M43: Yuya | N43: Yuya | O43: Yuya | P43: Yuya | Q43: Yuya | R43: Yuya | S43: 42.48 | U43: 329 | V43: =(U43/1.16)*0.6 -> 170.17241 | W43: =+S43/V43 -> 0.24962918 | X43: =1-(S43/V43) -> 0.75037082 | Y43: 4.4 | AA43: MX | AD43: 46279 | BA43: 1 | BB43: 1 | BC43: 1 | BD43: 1 | BE43: 1 | BF43: 1 | BG43: 1 | BH43: 1 | BJ43: 9 | BK43: =SUM(BA43:BI43) -> 8 | BL43: =+BK43/BJ43 -> 0.88888889 | BS43: Terminado | BT43: =+AD43 -> 46279 | BV43: Comercial
C44: SEPTIEMBRE | D44: En tiempo | E44: 7506110696766 | F44: Y-SD014 | G44: Entre lirios Máscara 10 Aceites Esenciales Negra+ Blush Pequeño Lirio | J44: Yuya | K44: Yuya | L44: Yuya | M44: Yuya | N44: Yuya | O44: Yuya | P44: Yuya | Q44: Yuya | R44: Yuya | S44: 35.69 | U44: 299 | V44: =(U44/1.16)*0.6 -> 154.65517 | W44: =+S44/V44 -> 0.23077146 | X44: =1-(S44/V44) -> 0.76922854 | Y44: 5.4 | AA44: MX | AD44: 46279 | BA44: 1 | BB44: 1 | BC44: 1 | BD44: 1 | BE44: 1 | BF44: 1 | BG44: 1 | BH44: 1 | BJ44: 9 | BK44: =SUM(BA44:BI44) -> 8 | BL44: =+BK44/BJ44 -> 0.88888889 | BS44: Terminado | BT44: =+AD44 -> 46279 | BV44: Comercial
C45: SEPTIEMBRE | D45: En tiempo | E45: 7506110696780 | F45: Y-SW013 | G45: Jardín Secreto Trio Body Mist | J45: Yuya | K45: Yuya | L45: Yuya | M45: Yuya | N45: Yuya | O45: Yuya | P45: Yuya | Q45: Yuya | R45: Yuya | S45: 31.25 | U45: 199 | V45: =(U45/1.16)*0.6 -> 102.93103 | W45: =+S45/V45 -> 0.30360134 | X45: =1-(S45/V45) -> 0.69639866 | Y45: 6.4 | AA45: MX | AD45: 46279 | BA45: 1 | BB45: 1 | BC45: 1 | BD45: 1 | BE45: 1 | BF45: 1 | BG45: 1 | BH45: 1 | BJ45: 9 | BK45: =SUM(BA45:BI45) -> 8 | BL45: =+BK45/BJ45 -> 0.88888889 | BS45: Terminado | BT45: =+AD45 -> 46279 | BV45: Comercial
C46: SEPTIEMBRE | D46: En tiempo | E46: 7506110696797 | F46: Y-SW014 | G46: Pedazo de Cielo Duo Body mist | J46: Yuya | K46: Yuya | L46: Yuya | M46: Yuya | N46: Yuya | O46: Yuya | P46: Yuya | Q46: Yuya | R46: Yuya | S46: 49.97 | U46: 299 | V46: =(U46/1.16)*0.6 -> 154.65517 | W46: =+S46/V46 -> 0.32310591 | X46: =1-(S46/V46) -> 0.67689409 | Y46: 7.4 | AA46: MX | AD46: 46279 | BA46: 1 | BB46: 1 | BC46: 1 | BD46: 1 | BE46: 1 | BF46: 1 | BG46: 1 | BH46: 1 | BJ46: 9 | BK46: =SUM(BA46:BI46) -> 8 | BL46: =+BK46/BJ46 -> 0.88888889 | BS46: Terminado | BT46: =+AD46 -> 46279 | BV46: Comercial
A47: 41 | B47: TBC | C47: 46388 | D47: En tiempo | E47: 7502327992769 | F47: Y-SH04 | G47: Shampoo Nuevo | H47: #VALUE! | I47: 1 pieza | J47: Yuya | K47: Multicanal | L47: 1 | N47: USD | O47: 20000 | P47: 16.88 | S47: 24.98 | T47: Elvive $85 Sedal $85 Grisi $85 | U47: 89 | V47: =(U47/1.16)*0.6 -> 46.034483 | W47: =+S47/V47 -> 0.5426367 | X47: =1-(S47/V47) -> 0.4573633 | Y47: 0.4 | AA47: MX | AC47: Falta autorización de fórmula y fragancia | AD47: Diciembre | BA47: 1 | BB47: 1 | BC47: 1 | BE47: 1 | BJ47: 9 | BK47: =SUM(BA47:BI47) -> 4 | BL47: =+BK47/BJ47 -> 0.44444444 | BS47: Prueblas de eficacia | BT47: Enero | BV47: NP
A48: 42 | B48: TBC | C48: 46388 | D48: En tiempo | E48: 7502327992776 | F48: Y-AC04 | G48: Acondicionador Nuevo | H48: #VALUE! | I48: 1 pieza | J48: Yuya | K48: Multicanal | L48: 1 | N48: USD | O48: 20000 | P48: 16.88 | S48: 26.23 | T48: Loreal $85 Sedal $85 Ann Rottshiel $103 | U48: 89 | V48: =(U48/1.16)*0.6 -> 46.034483 | W48: =+S48/V48 -> 0.56979026 | X48: =1-(S48/V48) -> 0.43020974 | Y48: 0.4 | AA48: MX | AC48: Falta autorización de fórmula y fragancia | AD48: Diciembre | BA48: 1 | BB48: 1 | BC48: 1 | BE48: 1 | BJ48: 9 | BK48: =SUM(BA48:BI48) -> 4 | BL48: =+BK48/BJ48 -> 0.44444444 | BS48: Prueblas de eficacia | BT48: Enero | BV48: NP
A49: 43 | B49: TBC | C49: 46388 | D49: En tiempo | E49: 7502327992783 | F49: Y-MC04 | G49: Tratamiento Capilar Nuevo | H49: #VALUE! | I49: 1 pieza | J49: Yuya | K49: Multicanal | L49: 1 | N49: USD | O49: 20000 | P49: 16.88 | S49: 23.44 | T49: Neffertiti $146 Sedal $64 Elvive $101 | U49: 79 | V49: =(U49/1.16)*0.6 -> 40.862069 | W49: =+S49/V49 -> 0.57363713 | X49: =1-(S49/V49) -> 0.42636287 | Y49: 0.4 | AA49: MX | AC49: Falta autorización de fórmula y fragancia | AD49: Diciembre | BA49: 1 | BB49: 1 | BC49: 1 | BE49: 1 | BJ49: 9 | BK49: =SUM(BA49:BI49) -> 4 | BL49: =+BK49/BJ49 -> 0.44444444 | BS49: Prueblas de eficacia | BT49: Enero | BV49: NP
BL50: =AVERAGE(BL17:BL49) -> 0.90909091

Sheet Velvet 2026 Fase 1
B1: Estatus | C1: Atrasado
A2: Velvet
A3: Agencia | B3: 46113 | C3: 46133
A4: Autorizacion | B4: =+B3+2 -> 46115 | C4: =+C3+2 -> 46135
A5: Diseño final | B5: =+B4+7 -> 46122 | C5: =+C4+7 -> 46142
A6: Autorizaciones | B6: =+B5+5 -> 46127 | C6: =+C5+5 -> 46147
A7: Orden de compra | B7: =+B6+2 -> 46129 | C7: =+C6+2 -> 46149
A8: Fecha Estimada Pago balance | B8: =+B7+45 -> 46174 | C8: =+C7+45 -> 46194
A9: Produccion / envio | B9: =+B7+40 -> 46169 | C9: =+C7+40 -> 46189
A10: Llegada Almacén | B10: =+B9+65 -> 46234 | C10: =+C9+65 -> 46254
A11: Lanzamiento | B11: =+B10+14 -> 46248 | C11: =+C10+14 -> 46268
CJ14: SEGUIMIENTO DE FECHAS
S15: 2.62 | AL15: MEGAOUTLET | BA15: % AVANCE POR PRODUCTOS | CJ15: PPEDIDOS | CL15: PREPRODCCION | CN15: AUTORIZACIÓN MARCA | CP15: DISPONIBILIDAD | CR15: DOCUMENTOS PROVEEDOR | CT15: PICK UP DE MERCANCIA | CV15: SALIDA DE LIS | CX15: LLEGADA A ADUANA | CZ15: DISPONIBILIDAD EN ALMACEN
A16: # | B16: Fecha confirmada de Lanzamiento | C16: Mes de Lanzamiento (Esperado) | D16: Estatus | E16: EAN | F16: Código interno | G16: Nombre Comercial | H16: Imagen | I16: Contenido | J16: Marca | K16: Canales | L16: Fase | M16: Proveedor | N16: Benchmark tonos Amazon/MELI | O16: Categoría | P16: Costo real | Q16: Moneda | R16: Piezas cotizadas (MOQ) | S16: Costo Esperado en MXN | T16: IGI | U16: Incrementables | V16: Costo final en MXN (FOB en almacén PT) | W16: Precio publico C/IVA | X16: Precio Público S/IVA | Y16: Facturación por unidad | Z16: Factor costo | AA16: Margen de utilidad bruta | AB16: MU Cliente | AC16: Pais de Origen | AD16: DUN 14 (INNER) | AE16: Inner | AF16: Master | AG16: Comentarios | AH16: Disponibilidad en Almacén | AL16: Precio publico C/IVA | AM16: Facturación por unidad | AN16: Factor costo | AO16: Margen de utilidad bruta | AP16: Margen MO | BA16: Definición del Line Up | BB16: Costo / PVP Autorizado | BC16: PVP Autorizado | BD16: Colores y formula autorizada | BE16: Vobo CEO + VPs | BF16: Arte Final (Diseño) | BG16: PO | BH16: Salida de LIS | BI16: Disponibilidad en almacén | BJ16: Total | BK16: Estatus | BL16: % de Avance | BR16: Comentarios | BS16: Disponibilidad en Almacén | BT16: Responsable Siguiente paso | CJ16: ESPERADA | CK16: REAL | CL16: ESPERADA | CM16: REAL | CN16: ESPERADA | CO16: REAL | CP16: ESPERADA | CQ16: REAL | CR16: ESPERADA | CS16: REAL | CT16: ESPERADA | CU16: REAL | CV16: ESPERADA | CW16: REAL | CX16: ESPERADA | CY16: REAL | CZ16: ESPERADA | DA16: REAL
A17: 1 | B17: TBC | C17: Diciembre | D17: En tiempo | E17: 7502327990857 | F17: VLT-01 | G17: Base de Maquillaje Velvet "Smooth Foundation - CN1" | H17: #VALUE! | I17: 50 mL | J17: Velvet | K17: Mix de canales | L17: 1 | M17: MUC | N17: https://www.maccosmetics.com.mx/product/13847/119586/productos/maquillaje/rostro/bases-de-maquillaje/studio-radiance-serum-poweredtm-foundation?shade=NC15 | O17: MAKEUP | P17: 6.95 | Q17: RMB | R17: 10000 | S17: =P17*S15 -> 18.209 | T17: =+S17*0.25 -> 4.55225 | U17: =(S17+T17)*0.044 -> 1.001495 | V17: =S17+T17+U17 -> 23.762745 | W17: 249 | X17: =W17/1.16 -> 214.65517 | Y17: =X17*0.6 -> 128.7931 | Z17: =V17/Y17 -> 0.18450324 | AA17: =1-(V17/Y17) -> 0.81549676 | AB17: =1-(Y17/(W17/1.16)) -> 0.4 | AC17: China | AE17: 6 | AF17: 48 | AG17: En revisión de dummy para autorización final | AH17: 46341 | AL17: 161.85 | AM17: =+AL17/1.16 -> 139.52586 | AN17: =+V18/AM17 -> #VALUE! | AO17: =1-V18/AM17 -> #VALUE! | AP17: =1-(AM17/(AL17/1.16)) -> 0 | BA17: 1 | BB17: 1 | BC17: 1 | BD17: 1 | BE17: 1 | BF17: 1 | BG17: 1 | BJ17: 9 | BK17: =SUM(BA17:BI17) -> 7 | BL17: =+BK17/BJ17 -> 0.77777778 | BR17: PPEDIDOS-260727498 Se espera que PT este listo 30 Sept | BS17: 46376 | BT17: Eduardo (Compras) | CJ17: 46188
A18: 2 | B18: TBC | C18: Diciembre | D18: En tiempo | E18: 7502327990864 | F18: VLT-02 | G18: Base de Maquillaje Velvet "Smooth Foundation - CC2" | H18: #VALUE! | I18: 50 mL | J18: Velvet | K18: Mix de canales | L18: 1 | M18: MUC | N18: https://www.maccosmetics.com.mx/product/13847/119586/productos/maquillaje/rostro/bases-de-maquillaje/studio-radiance-serum-poweredtm-foundation?shade=NW2 | O18: MAKEUP | P18: 6.95 | Q18: RMB | R18: 10000 | S18: =+P18*$T$29 -> #VALUE! | T18: =+S18*0.25 -> #VALUE! | U18: =(S18+T18)*0.044 -> #VALUE! | V18: =S18+T18+U18 -> #VALUE! | W18: 249 | X18: =W18/1.16 -> 214.65517 | Y18: =X18*0.6 -> 128.7931 | Z18: =V18/Y18 -> #VALUE! | AA18: =1-(V18/Y18) -> #VALUE! | AB18: =1-(Y18/(W18/1.16)) -> 0.4 | AC18: China | AE18: 6 | AF18: 48 | AG18: En revisión de dummy para autorización final | AH18: 46341 | AL18: 161.85 | AM18: =+AL18/1.16 -> 139.52586 | AN18: =+V19/AM18 -> #VALUE! | AO18: =1-V19/AM18 -> #VALUE! | AP18: =1-(AM18/(AL18/1.16)) -> 0 | BA18: 1 | BB18: 1 | BC18: 1 | BD18: 1 | BE18: 1 | BF18: 1 | BG18: 1 | BJ18: 9 | BK18: =SUM(BA18:BI18) -> 7 | BL18: =+BK18/BJ18 -> 0.77777778 | BR18: PPEDIDOS-260727498 Se espera que PT este listo 30 Sept | BS18: 46376 | BT18: Eduardo (Compras) | CJ18: 46188
A19: 3 | B19: TBC | C19: Diciembre | D19: En tiempo | E19: 7502327990871 | F19: VLT-03 | G19: Base de Maquillaje Velvet "Smooth Foundation - CC3" | H19: #VALUE! | I19: 50 mL | J19: Velvet | K19: Mix de canales | L19: 1 | M19: MUC | N19: https://www.maccosmetics.com.mx/product/13847/119586/productos/maquillaje/rostro/bases-de-maquillaje/studio-radiance-serum-poweredtm-foundation?shade=NW30 | O19: MAKEUP | P19: 6.95 | Q19: RMB | R19: 10000 | S19: =+P19*$T$29 -> #VALUE! | T19: =+S19*0.25 -> #VALUE! | U19: =(S19+T19)*0.044 -> #VALUE! | V19: =S19+T19+U19 -> #VALUE! | W19: 249 | X19: =W19/1.16 -> 214.65517 | Y19: =X19*0.6 -> 128.7931 | Z19: =V19/Y19 -> #VALUE! | AA19: =1-(V19/Y19) -> #VALUE! | AB19: =1-(Y19/(W19/1.16)) -> 0.4 | AC19: China | AE19: 6 | AF19: 48 | AG19: En revisión de dummy para autorización final | AH19: 46341 | AL19: 161.85 | AM19: =+AL19/1.16 -> 139.52586 | AN19: =+V20/AM19 -> #VALUE! | AO19: =1-V20/AM19 -> #VALUE! | AP19: =1-(AM19/(AL19/1.16)) -> 0 | BA19: 1 | BB19: 1 | BC19: 1 | BD19: 1 | BE19: 1 | BF19: 1 | BG19: 1 | BJ19: 9 | BK19: =SUM(BA19:BI19) -> 7 | BL19: =+BK19/BJ19 -> 0.77777778 | BR19: PPEDIDOS-260727498 Se espera que PT este listo 30 Sept | BS19: 46376 | BT19: Eduardo (Compras) | CJ19: 46188
A20: 4 | B20: TBC | C20: Diciembre | D20: En tiempo | E20: 7502327990888 | F20: VLT-04 | G20: Base de Maquillaje Velvet "Smooth Foundation - MN4" | H20: #VALUE! | I20: 50 mL | J20: Velvet | K20: Mix de canales | L20: 1 | M20: MUC | N20: https://www.maccosmetics.com.mx/product/13847/119586/productos/maquillaje/rostro/bases-de-maquillaje/studio-radiance-serum-poweredtm-foundation?shade=NW35 | O20: MAKEUP | P20: 6.95 | Q20: RMB | R20: 10000 | S20: =+P20*$T$29 -> #VALUE! | T20: =+S20*0.25 -> #VALUE! | U20: =(S20+T20)*0.044 -> #VALUE! | V20: =S20+T20+U20 -> #VALUE! | W20: 249 | X20: =W20/1.16 -> 214.65517 | Y20: =X20*0.6 -> 128.7931 | Z20: =V20/Y20 -> #VALUE! | AA20: =1-(V20/Y20) -> #VALUE! | AB20: =1-(Y20/(W20/1.16)) -> 0.4 | AC20: China | AE20: 6 | AF20: 48 | AG20: En revisión de dummy para autorización final | AH20: 46341 | AL20: 161.85 | AM20: =+AL20/1.16 -> 139.52586 | AN20: =+V21/AM20 -> #VALUE! | AO20: =1-V21/AM20 -> #VALUE! | AP20: =1-(AM20/(AL20/1.16)) -> 0 | BA20: 1 | BB20: 1 | BC20: 1 | BD20: 1 | BE20: 1 | BF20: 1 | BG20: 1 | BJ20: 9 | BK20: =SUM(BA20:BI20) -> 7 | BL20: =+BK20/BJ20 -> 0.77777778 | BR20: PPEDIDOS-260727498 Se espera que PT este listo 30 Sept | BS20: 46376 | BT20: Eduardo (Compras) | CJ20: 46188
A21: 5 | B21: TBC | C21: Diciembre | D21: En tiempo | E21: 7502327990895 | F21: VLT-05 | G21: Base de Maquillaje Velvet "Smooth Foundation - MC5" | H21: #VALUE! | I21: 50 mL | J21: Velvet | K21: Mix de canales | L21: 1 | M21: MUC | N21: https://www.maccosmetics.com.mx/product/13847/119586/productos/maquillaje/rostro/bases-de-maquillaje/studio-radiance-serum-poweredtm-foundation?shade=NC42 | O21: MAKEUP | P21: 6.95 | Q21: RMB | R21: 10000 | S21: =+P21*$T$29 -> #VALUE! | T21: =+S21*0.25 -> #VALUE! | U21: =(S21+T21)*0.044 -> #VALUE! | V21: =S21+T21+U21 -> #VALUE! | W21: 249 | X21: =W21/1.16 -> 214.65517 | Y21: =X21*0.6 -> 128.7931 | Z21: =V21/Y21 -> #VALUE! | AA21: =1-(V21/Y21) -> #VALUE! | AB21: =1-(Y21/(W21/1.16)) -> 0.4 | AC21: China | AE21: 6 | AF21: 48 | AG21: En revisión de dummy para autorización final | AH21: 46341 | AL21: 161.85 | AM21: =+AL21/1.16 -> 139.52586 | AN21: =+V22/AM21 -> #VALUE! | AO21: =1-V22/AM21 -> #VALUE! | AP21: =1-(AM21/(AL21/1.16)) -> 0 | BA21: 1 | BB21: 1 | BC21: 1 | BD21: 1 | BE21: 1 | BF21: 1 | BG21: 1 | BJ21: 9 | BK21: =SUM(BA21:BI21) -> 7 | BL21: =+BK21/BJ21 -> 0.77777778 | BR21: PPEDIDOS-260727498 Se espera que PT este listo 30 Sept | BS21: 46376 | BT21: Eduardo (Compras) | CJ21: 46188
A22: 6 | B22: TBC | C22: Diciembre | D22: En tiempo | E22: 7502327990901 | F22: VLT-06 | G22: Base de Maquillaje Velvet "Smooth Foundation - MN6" | H22: #VALUE! | I22: 50 mL | J22: Velvet | K22: Mix de canales | L22: 1 | M22: MUC | N22: https://www.elpalaciodehierro.com/mac-base-de-maquillaje-studio-fix-fluid-spf-15-nc45-5.3-ml-39786604.html?srsltid=AfmBOood9B2Y0XbWpVOtAuHS2Ge3jaGY5lfhHCdFSZcATb5qKcvOXpk_ | O22: MAKEUP | P22: 6.95 | Q22: RMB | R22: 10000 | S22: =+P22*$T$29 -> #VALUE! | T22: =+S22*0.25 -> #VALUE! | U22: =(S22+T22)*0.044 -> #VALUE! | V22: =S22+T22+U22 -> #VALUE! | W22: 249 | X22: =W22/1.16 -> 214.65517 | Y22: =X22*0.6 -> 128.7931 | Z22: =V22/Y22 -> #VALUE! | AA22: =1-(V22/Y22) -> #VALUE! | AB22: =1-(Y22/(W22/1.16)) -> 0.4 | AC22: China | AE22: 6 | AF22: 48 | AG22: En revisión de dummy para autorización final | AH22: 46341 | AL22: 161.85 | AM22: =+AL22/1.16 -> 139.52586 | AN22: =+V27/AM22 -> #VALUE! | AO22: =1-V27/AM22 -> #VALUE! | AP22: =1-(AM22/(AL22/1.16)) -> 0 | BA22: 1 | BB22: 1 | BC22: 1 | BD22: 1 | BE22: 1 | BF22: 1 | BG22: 1 | BJ22: 9 | BK22: =SUM(BA22:BI22) -> 7 | BL22: =+BK22/BJ22 -> 0.77777778 | BR22: PPEDIDOS-260727498 Se espera que PT este listo 30 Sept | BS22: 46376 | BT22: Eduardo (Compras) | CJ22: 46188
A23: 7 | B23: TBC | C23: Diciembre | D23: En tiempo | E23: 7502327990918 | F23: VLT-07 | G23: Corrector Líquido Velvet "Smooth Concealer - CN1" | I23: 7.5 mL | J23: Velvet | K23: Mix de canales | L23: 1 | M23: USHAS | N23: https://www.maccosmetics.com.mx/product/13844/60430/productos/maquillaje/rostro/correctores/corrector-liquido-studio-fix-24-hour-smooth-wear-concealer?shade=NC15 | O23: MAKEUP | P23: 3 | Q23: RMB | R23: 10000 | S23: =+P23*$T$25 -> 0 | T23: =+S23*0.25 -> 0 | U23: =(S23+T23)*0.0267 -> 0 | V23: =S23+T23+U23 -> 0 | W23: 179 | X23: =W23/1.16 -> 154.31034 | Y23: =X23*0.6 -> 92.586207 | Z23: =V23/Y23 -> 0 | AA23: =1-(V23/Y23) -> 1 | AB23: =1-(Y23/(W23/1.16)) -> 0.4 | AC23: China | AG23: En revisión de dummy para autorización final | AH23: 46366 | BA23: 1 | BB23: 1 | BC23: 1 | BD23: 1 | BE23: 1 | BF23: 1 | BG23: 1 | BJ23: 9 | BK23: =SUM(BA23:BI23) -> 7 | BL23: =+BK23/BJ23 -> 0.77777778 | BR23: PPEDIDOS-260827594 Se espera que PT este listo 09 Nov | BS23: 46038 | BT23: Eduardo (Compras)
A24: 8 | B24: TBC | C24: Diciembre | D24: En tiempo | E24: 7502327990925 | F24: VLT-08 | G24: Corrector Líquido Velvet "Smooth Concealer - CC2" | I24: 7.5 mL | J24: Velvet | K24: Mix de canales | L24: 1 | M24: USHAS | N24: https://www.maccosmetics.com.mx/product/13844/60430/productos/maquillaje/rostro/correctores/corrector-liquido-studio-fix-24-hour-smooth-wear-concealer?shade=NC15 | O24: MAKEUP | P24: 3 | Q24: RMB | R24: 10000 | S24: =+P24*$T$25 -> 0 | T24: =+S24*0.25 -> 0 | U24: =(S24+T24)*0.0267 -> 0 | V24: =S24+T24+U24 -> 0 | W24: 179 | X24: =W24/1.16 -> 154.31034 | Y24: =X24*0.6 -> 92.586207 | Z24: =V24/Y24 -> 0 | AA24: =1-(V24/Y24) -> 1 | AB24: =1-(Y24/(W24/1.16)) -> 0.4 | AC24: China | AG24: En revisión de dummy para autorización final | AH24: 46366 | BA24: 1 | BB24: 1 | BC24: 1 | BD24: 1 | BE24: 1 | BF24: 1 | BG24: 1 | BJ24: 9 | BK24: =SUM(BA24:BI24) -> 7 | BL24: =+BK24/BJ24 -> 0.77777778 | BR24: PPEDIDOS-260827594 Se espera que PT este listo 09 Nov | BS24: 46038 | BT24: Eduardo (Compras)
A25: 9 | B25: TBC | C25: Diciembre | D25: En tiempo | E25: 7502327990932 | F25: VLT-09 | G25: Corrector Líquido Velvet "Smooth Concealer - CC3" | I25: 7.5 mL | J25: Velvet | K25: Mix de canales | L25: 1 | M25: USHAS | N25: https://www.maccosmetics.com.mx/product/13844/60430/productos/maquillaje/rostro/correctores/corrector-liquido-studio-fix-24-hour-smooth-wear-concealer?shade=NC15 | O25: MAKEUP | P25: 3 | Q25: RMB | R25: 10000 | S25: =+P25*$T$25 -> 0 | T25: =+S25*0.25 -> 0 | U25: =(S25+T25)*0.0267 -> 0 | V25: =S25+T25+U25 -> 0 | W25: 179 | X25: =W25/1.16 -> 154.31034 | Y25: =X25*0.6 -> 92.586207 | Z25: =V25/Y25 -> 0 | AA25: =1-(V25/Y25) -> 1 | AB25: =1-(Y25/(W25/1.16)) -> 0.4 | AC25: China | AG25: En revisión de dummy para autorización final | AH25: 46366 | BA25: 1 | BB25: 1 | BC25: 1 | BD25: 1 | BE25: 1 | BF25: 1 | BG25: 1 | BJ25: 9 | BK25: =SUM(BA25:BI25) -> 7 | BL25: =+BK25/BJ25 -> 0.77777778 | BR25: PPEDIDOS-260827594 Se espera que PT este listo 09 Nov | BS25: 46038 | BT25: Eduardo (Compras)
A26: 10 | B26: TBC | C26: Diciembre | D26: En tiempo | E26: 7502327990949 | F26: VLT-10 | G26: Corrector Líquido Velvet "Smooth Concealer - MC4" | I26: 7.5 mL | J26: Velvet | K26: Mix de canales | L26: 1 | M26: USHAS | N26: https://www.maccosmetics.com.mx/product/13844/60430/productos/maquillaje/rostro/correctores/corrector-liquido-studio-fix-24-hour-smooth-wear-concealer?shade=NC15 | O26: MAKEUP | P26: 3 | Q26: RMB | R26: 10000 | S26: =+P26*$T$25 -> 0 | T26: =+S26*0.25 -> 0 | U26: =(S26+T26)*0.0267 -> 0 | V26: =S26+T26+U26 -> 0 | W26: 179 | X26: =W26/1.16 -> 154.31034 | Y26: =X26*0.6 -> 92.586207 | Z26: =V26/Y26 -> 0 | AA26: =1-(V26/Y26) -> 1 | AB26: =1-(Y26/(W26/1.16)) -> 0.4 | AC26: China | AG26: En revisión de dummy para autorización final | AH26: 46366 | BA26: 1 | BB26: 1 | BC26: 1 | BD26: 1 | BE26: 1 | BF26: 1 | BG26: 1 | BJ26: 9 | BK26: =SUM(BA26:BI26) -> 7 | BL26: =+BK26/BJ26 -> 0.77777778 | BR26: PPEDIDOS-260827594 Se espera que PT este listo 09 Nov | BS26: 46038 | BT26: Eduardo (Compras)
A27: 11 | B27: TBC | C27: Diciembre | D27: En tiempo | E27: 7502327990956 | F27: VLT-11 | G27: Rubor en crema Velvet "Blush Mauve" | H27: #VALUE! | I27: 5.8 g | J27: Velvet | K27: Mix de canales | L27: 1 | M27: MUC | N27: https://www.rhodeskin.com/products/pocket-blush-tan-line?_pos=1&_psq=blush&_ss=e&_v=1.0 | O27: MAKEUP | P27: 4.75 | Q27: RMB | R27: 10000 | S27: =+P27*$T$29 -> #VALUE! | T27: =+S27*0.25 -> #VALUE! | U27: =(S27+T27)*0.0257 -> #VALUE! | V27: =S27+T27+U27 -> #VALUE! | W27: 169 | X27: =W27/1.16 -> 145.68966 | Y27: =X27*0.6 -> 87.413793 | Z27: =V27/Y27 -> #VALUE! | AA27: =1-(V27/Y27) -> #VALUE! | AB27: =1-(Y27/(W27/1.16)) -> 0.4 | AC27: China | AE27: 6 | AF27: 144 | AG27: En revisión de dummy para autorización final | AH27: 46341 | AL27: 109.85 | AM27: =+AL27/1.16 -> 94.698276 | AN27: =+V28/AM27 -> #VALUE! | AO27: =1-V28/AM27 -> #VALUE! | AP27: =1-(AM27/(AL27/1.16)) -> 0 | BA27: 1 | BB27: 1 | BC27: 1 | BD27: 1 | BE27: 1 | BF27: 1 | BG27: 1 | BJ27: 9 | BK27: =SUM(BA27:BI27) -> 7 | BL27: =+BK27/BJ27 -> 0.77777778 | BR27: PPEDIDOS-260727520 Se espera que PT este listo 14 Octubre | BS27: 46379 | BT27: Eduardo (Compras) | CJ27: 46188
A28: 12 | B28: TBC | C28: Diciembre | D28: En tiempo | E28: 7502327990963 | F28: VLT-12 | G28: Rubor en crema Velvet "Blush Peony" | H28: #VALUE! | I28: 5.8 g | J28: Velvet | K28: Mix de canales | L28: 1 | M28: MUC | N28: https://www.rhodeskin.com/products/pocket-blush-tan-line?_pos=1&_psq=blush&_ss=e&_v=1.1 | O28: MAKEUP | P28: 4.75 | Q28: RMB | R28: 10000 | S28: =+P28*$T$29 -> #VALUE! | T28: =+S28*0.25 -> #VALUE! | U28: =(S28+T28)*0.0257 -> #VALUE! | V28: =S28+T28+U28 -> #VALUE! | W28: 169 | X28: =W28/1.16 -> 145.68966 | Y28: =X28*0.6 -> 87.413793 | Z28: =V28/Y28 -> #VALUE! | AA28: =1-(V28/Y28) -> #VALUE! | AB28: =1-(Y28/(W28/1.16)) -> 0.4 | AC28: China | AE28: 6 | AF28: 144 | AG28: En revisión de dummy para autorización final | AH28: 46341 | AL28: 109.85 | AM28: =+AL28/1.16 -> 94.698276 | AN28: =+V29/AM28 -> #VALUE! | AO28: =1-V29/AM28 -> #VALUE! | AP28: =1-(AM28/(AL28/1.16)) -> 0 | BA28: 1 | BB28: 1 | BC28: 1 | BD28: 1 | BE28: 1 | BF28: 1 | BG28: 1 | BJ28: 9 | BK28: =SUM(BA28:BI28) -> 7 | BL28: =+BK28/BJ28 -> 0.77777778 | BR28: PPEDIDOS-260727520 Se espera que PT este listo 14 Octubre | BS28: 46379 | BT28: Eduardo (Compras) | CJ28: 46188
A29: 13 | B29: TBC | C29: Diciembre | D29: En tiempo | E29: 7502327990970 | F29: VLT-13 | G29: Rubor en crema Velvet "Blush Peach" | H29: #VALUE! | I29: 5.8 g | J29: Velvet | K29: Mix de canales | L29: 1 | M29: MUC | N29: https://www.rhodeskin.com/products/pocket-blush-tan-line?_pos=1&_psq=blush&_ss=e&_v=1.1 | O29: MAKEUP | P29: 4.75 | Q29: RMB | R29: 10000 | S29: =+P29*$T$29 -> #VALUE! | T29: =+S29*0.25 -> #VALUE! | U29: =(S29+T29)*0.0257 -> #VALUE! | V29: =S29+T29+U29 -> #VALUE! | W29: 169 | X29: =W29/1.16 -> 145.68966 | Y29: =X29*0.6 -> 87.413793 | Z29: =V29/Y29 -> #VALUE! | AA29: =1-(V29/Y29) -> #VALUE! | AB29: =1-(Y29/(W29/1.16)) -> 0.4 | AC29: China | AE29: 6 | AF29: 144 | AG29: En revisión de dummy para autorización final | AH29: 46341 | AL29: 109.85 | AM29: =+AL29/1.16 -> 94.698276 | AN29: =+V30/AM29 -> #VALUE! | AO29: =1-V30/AM29 -> #VALUE! | AP29: =1-(AM29/(AL29/1.16)) -> 0 | BA29: 1 | BB29: 1 | BC29: 1 | BD29: 1 | BE29: 1 | BF29: 1 | BG29: 1 | BJ29: 9 | BK29: =SUM(BA29:BI29) -> 7 | BL29: =+BK29/BJ29 -> 0.77777778 | BR29: PPEDIDOS-260727520 Se espera que PT este listo 14 Octubre | BS29: 46379 | BT29: Eduardo (Compras) | CJ29: 46188
A30: 14 | B30: TBC | C30: Diciembre | D30: En tiempo | E30: 7502327990987 | F30: VLT-14 | G30: Rubor en crema Velvet "Blush Hibiscus" | H30: #VALUE! | I30: 5.8 g | J30: Velvet | K30: Mix de canales | L30: 1 | M30: MUC | N30: https://www.rhodeskin.com/products/pocket-blush-tan-line?_pos=1&_psq=blush&_ss=e&_v=1.1 | O30: MAKEUP | P30: 4.75 | Q30: RMB | R30: 10000 | S30: =+P30*$T$29 -> #VALUE! | T30: =+S30*0.25 -> #VALUE! | U30: =(S30+T30)*0.0257 -> #VALUE! | V30: =S30+T30+U30 -> #VALUE! | W30: 169 | X30: =W30/1.16 -> 145.68966 | Y30: =X30*0.6 -> 87.413793 | Z30: =V30/Y30 -> #VALUE! | AA30: =1-(V30/Y30) -> #VALUE! | AB30: =1-(Y30/(W30/1.16)) -> 0.4 | AC30: China | AE30: 6 | AF30: 144 | AG30: En revisión de dummy para autorización final | AH30: 46341 | AL30: 109.85 | AM30: =+AL30/1.16 -> 94.698276 | AN30: =+V31/AM30 -> #VALUE! | AO30: =1-V31/AM30 -> #VALUE! | AP30: =1-(AM30/(AL30/1.16)) -> 0 | BA30: 1 | BB30: 1 | BC30: 1 | BD30: 1 | BE30: 1 | BF30: 1 | BG30: 1 | BJ30: 9 | BK30: =SUM(BA30:BI30) -> 7 | BL30: =+BK30/BJ30 -> 0.77777778 | BR30: PPEDIDOS-260727520 Se espera que PT este listo 14 Octubre | BS30: 46379 | BT30: Eduardo (Compras) | CJ30: 46188
A31: 15 | B31: TBC | C31: Diciembre | D31: En tiempo | E31: 7502327990994 | F31: VLT-15 | G31: Rubor en crema Velvet "Blush Scarlet" | H31: #VALUE! | I31: 5.8 g | J31: Velvet | K31: Mix de canales | L31: 1 | M31: MUC | N31: https://www.rhodeskin.com/products/pocket-blush-tan-line?_pos=1&_psq=blush&_ss=e&_v=1.1 | O31: MAKEUP | P31: 4.75 | Q31: RMB | R31: 10000 | S31: =+P31*$T$29 -> #VALUE! | T31: =+S31*0.25 -> #VALUE! | U31: =(S31+T31)*0.0257 -> #VALUE! | V31: =S31+T31+U31 -> #VALUE! | W31: 169 | X31: =W31/1.16 -> 145.68966 | Y31: =X31*0.6 -> 87.413793 | Z31: =V31/Y31 -> #VALUE! | AA31: =1-(V31/Y31) -> #VALUE! | AB31: =1-(Y31/(W31/1.16)) -> 0.4 | AC31: China | AE31: 6 | AF31: 144 | AG31: En revisión de dummy para autorización final | AH31: 46341 | AL31: 109.85 | AM31: =+AL31/1.16 -> 94.698276 | AN31: =+V32/AM31 -> #VALUE! | AO31: =1-V32/AM31 -> #VALUE! | AP31: =1-(AM31/(AL31/1.16)) -> 0 | BA31: 1 | BB31: 1 | BC31: 1 | BD31: 1 | BE31: 1 | BF31: 1 | BG31: 1 | BJ31: 9 | BK31: =SUM(BA31:BI31) -> 7 | BL31: =+BK31/BJ31 -> 0.77777778 | BR31: PPEDIDOS-260727520 Se espera que PT este listo 14 Octubre | BS31: 46379 | BT31: Eduardo (Compras) | CJ31: 46188
A32: 16 | B32: TBC | C32: Diciembre | D32: En tiempo | E32: 7502327991007 | F32: VLT-16 | G32: Contour en crema Velvet "Sculpt Contour Almond" | H32: #VALUE! | I32: 5.8 g | J32: Velvet | K32: Mix de canales | L32: 1 | M32: MUC | N32: https://beautycreationscosmetics.com.mx/products/flawless-stay-contour-sticks?variant=41691245838426&country=MX&currency=MXN&utm_medium=product_sync&utm_source=google&utm_content=sag_organic&utm_campaign=sag_organic&srsltid=AfmBOoqqqZtG6vzrYn-vwluDoZ2GABwqAo8Eng13wWofCpwCn5mhKehd2TY | O32: MAKEUP | P32: 5.1 | Q32: RMB | R32: 10000 | S32: =+P32*$T$29 -> #VALUE! | T32: =+S32*0.25 -> #VALUE! | U32: =(S32+T32)*0.0257 -> #VALUE! | V32: =S32+T32+U32 -> #VALUE! | W32: 169 | X32: =W32/1.16 -> 145.68966 | Y32: =X32*0.6 -> 87.413793 | Z32: =V32/Y32 -> #VALUE! | AA32: =1-(V32/Y32) -> #VALUE! | AB32: =1-(Y32/(W32/1.16)) -> 0.4 | AC32: China | AE32: 6 | AF32: 144 | AG32: Falta arte final de la caja por parte de Incitrus | AH32: 46341 | AL32: 109.85 | AM32: =+AL32/1.16 -> 94.698276 | AN32: =+V33/AM32 -> #VALUE! | AO32: =1-V33/AM32 -> #VALUE! | AP32: =1-(AM32/(AL32/1.16)) -> 0 | BA32: 1 | BB32: 1 | BC32: 1 | BD32: 1 | BE32: 1 | BF32: 1 | BG32: 1 | BJ32: 9 | BK32: =SUM(BA32:BI32) -> 7 | BL32: =+BK32/BJ32 -> 0.77777778 | BR32: PPEDIDOS-260727498 Se espera que PT este listo 19 Sept | BS32: 46379 | BT32: Eduardo (Compras) | CJ32: 46195
A33: 17 | B33: TBC | C33: Diciembre | D33: En tiempo | E33: 7502327991014 | F33: VLT-17 | G33: Contour en crema Velvet "Sculpt Contour Mocha" | H33: #VALUE! | I33: 5.8 g | J33: Velvet | K33: Mix de canales | L33: 1 | M33: MUC | N33: https://beautycreationscosmetics.com.mx/products/flawless-stay-contour-sticks?variant=41691245838426&country=MX&currency=MXN&utm_medium=product_sync&utm_source=google&utm_content=sag_organic&utm_campaign=sag_organic&srsltid=AfmBOoqqqZtG6vzrYn-vwluDoZ2GABwqAo8Eng13wWofCpwCn5mhKehd2TY | O33: MAKEUP | P33: 5.1 | Q33: RMB | R33: 10000 | S33: =+P33*$T$29 -> #VALUE! | T33: =+S33*0.25 -> #VALUE! | U33: =(S33+T33)*0.0257 -> #VALUE! | V33: =S33+T33+U33 -> #VALUE! | W33: 169 | X33: =W33/1.16 -> 145.68966 | Y33: =X33*0.6 -> 87.413793 | Z33: =V33/Y33 -> #VALUE! | AA33: =1-(V33/Y33) -> #VALUE! | AB33: =1-(Y33/(W33/1.16)) -> 0.4 | AC33: China | AE33: 6 | AF33: 144 | AG33: Falta arte final de la caja por parte de Incitrus | AH33: 46341 | AL33: 109.85 | AM33: =+AL33/1.16 -> 94.698276 | AN33: =+V34/AM33 -> #VALUE! | AO33: =1-V34/AM33 -> #VALUE! | AP33: =1-(AM33/(AL33/1.16)) -> 0 | BA33: 1 | BB33: 1 | BC33: 1 | BD33: 1 | BE33: 1 | BF33: 1 | BG33: 1 | BJ33: 9 | BK33: =SUM(BA33:BI33) -> 7 | BL33: =+BK33/BJ33 -> 0.77777778 | BR33: PPEDIDOS-260727498 Se espera que PT este listo 19 Sept | BS33: 46379 | BT33: Eduardo (Compras) | CJ33: 46195
A34: 18 | B34: TBC | C34: Diciembre | D34: En tiempo | E34: 7502327991021 | F34: VLT-18 | G34: Contour en crema Velvet "Sculpt Contour Latte" | H34: #VALUE! | I34: 5.8 g | J34: Velvet | K34: Mix de canales | L34: 1 | M34: MUC | N34: https://beautycreationscosmetics.com.mx/products/flawless-stay-contour-sticks?variant=41691245838426&country=MX&currency=MXN&utm_medium=product_sync&utm_source=google&utm_content=sag_organic&utm_campaign=sag_organic&srsltid=AfmBOoqqqZtG6vzrYn-vwluDoZ2GABwqAo8Eng13wWofCpwCn5mhKehd2TY | O34: MAKEUP | P34: 5.1 | Q34: RMB | R34: 10000 | S34: =+P34*$T$29 -> #VALUE! | T34: =+S34*0.25 -> #VALUE! | U34: =(S34+T34)*0.0257 -> #VALUE! | V34: =S34+T34+U34 -> #VALUE! | W34: 169 | X34: =W34/1.16 -> 145.68966 | Y34: =X34*0.6 -> 87.413793 | Z34: =V34/Y34 -> #VALUE! | AA34: =1-(V34/Y34) -> #VALUE! | AB34: =1-(Y34/(W34/1.16)) -> 0.4 | AC34: China | AE34: 6 | AF34: 144 | AG34: Falta arte final de la caja por parte de Incitrus | AH34: 46341 | AL34: 109.85 | AM34: =+AL34/1.16 -> 94.698276 | AN34: =+V35/AM34 -> #VALUE! | AO34: =1-V35/AM34 -> #VALUE! | AP34: =1-(AM34/(AL34/1.16)) -> 0 | BA34: 1 | BB34: 1 | BC34: 1 | BD34: 1 | BE34: 1 | BF34: 1 | BG34: 1 | BJ34: 9 | BK34: =SUM(BA34:BI34) -> 7 | BL34: =+BK34/BJ34 -> 0.77777778 | BR34: PPEDIDOS-260727498 Se espera que PT este listo 19 Sept | BS34: 46379 | BT34: Eduardo (Compras) | CJ34: 46195
A35: 19 | B35: TBC | C35: Diciembre | D35: En tiempo | E35: 7502327991038 | F35: VLT-19 | G35: Iluminador en barra Velvet -"Barely Lit Champagne" | H35: #VALUE! | I35: 5.8 g | J35: Velvet | K35: Mix de canales | L35: 1 | M35: MUC | N35: https://www.amazon.com/-/es/LOreal-Highlighter-reflectante-transl%C3%BAcido-iluminador/dp/B0DHLM914R/ref=zg_bs_g_21190478011_d_sccl_8/132-2883545-9921149?th=1 | O35: MAKEUP | P35: 4.45 | Q35: RMB | R35: 10000 | S35: =+P35*$T$29 -> #VALUE! | T35: =+S35*0.25 -> #VALUE! | U35: =(S35+T35)*0.0257 -> #VALUE! | V35: =S35+T35+U35 -> #VALUE! | W35: 169 | X35: =W35/1.16 -> 145.68966 | Y35: =X35*0.6 -> 87.413793 | Z35: =V35/Y35 -> #VALUE! | AA35: =1-(V35/Y35) -> #VALUE! | AB35: =1-(Y35/(W35/1.16)) -> 0.4 | AC35: China | AE35: 6 | AF35: 144 | AG35: Falta arte final de la caja. En espera suaje por parte de Daniel | AH35: 46341 | AL35: 109.85 | AM35: =+AL35/1.16 -> 94.698276 | AN35: =+V36/AM35 -> #VALUE! | AO35: =1-V36/AM35 -> #VALUE! | AP35: =1-(AM35/(AL35/1.16)) -> 0 | BA35: 1 | BB35: 1 | BC35: 1 | BD35: 1 | BE35: 1 | BF35: 1 | BG35: 1 | BJ35: 9 | BK35: =SUM(BA35:BI35) -> 7 | BL35: =+BK35/BJ35 -> 0.77777778 | BR35: PPEDIDOS-260827551 Se espera que PT este listo 24 Oct | BS35: 46376 | BT35: Eduardo (Compras) | CJ35: 46202
A36: 20 | B36: TBC | C36: Diciembre | D36: En tiempo | E36: 7502327991045 | F36: VLT-20 | G36: Iluminador en barra Velvet -"Barely Lit Champagne - Tono Rose Wine" | H36: #VALUE! | I36: 5.8 g | J36: Velvet | K36: Mix de canales | L36: 1 | M36: MUC | N36: https://www.amazon.com/-/es/LOreal-Highlighter-reflectante-transl%C3%BAcido-iluminador/dp/B0DHLP46Y1/ref=zg_bs_g_21190478011_d_sccl_8/132-2883545-9921149?th=1 | P36: 4.45 | Q36: RMB | R36: 10000 | S36: =+P36*$T$29 -> #VALUE! | T36: =+S36*0.25 -> #VALUE! | U36: =(S36+T36)*0.0257 -> #VALUE! | V36: =S36+T36+U36 -> #VALUE! | W36: 169 | X36: =W36/1.16 -> 145.68966 | Y36: =X36*0.6 -> 87.413793 | Z36: =V36/Y36 -> #VALUE! | AA36: =1-(V36/Y36) -> #VALUE! | AB36: =1-(Y36/(W36/1.16)) -> 0.4 | AC36: China | AE36: 6 | AF36: 144 | AG36: Falta arte final de la caja. En espera suaje por parte de Daniel | AH36: CANCELADO | AL36: 109.85 | AM36: =+AL36/1.16 -> 94.698276 | AN36: =+V37/AM36 -> #VALUE! | AO36: =1-V37/AM36 -> #VALUE! | AP36: =1-(AM36/(AL36/1.16)) -> 0 | BA36: 1 | BB36: 1 | BC36: 1 | BD36: 1 | BE36: 1 | BF36: 1 | BG36: 1 | BJ36: 9 | BK36: =SUM(BA36:BI36) -> 7 | BL36: =+BK36/BJ36 -> 0.77777778 | BR36: CANCELADO | BS36: =AH36 -> CANCELADO | BT36: Eduardo (Compras) | CJ36: 46202
A37: 21 | B37: TBC | C37: Diciembre | D37: En tiempo | E37: 7502327991052 | F37: VLT-21 | G37: Iluminador en barra Velvet "Barely Lit Spritz" | H37: #VALUE! | I37: 5.8 g | J37: Velvet | K37: Mix de canales | L37: 1 | M37: MUC | N37: https://www.amazon.com/-/es/LOreal-Highlighter-reflectante-transl%C3%BAcido-iluminador/dp/B0DHLP46Y1/ref=zg_bs_g_21190478011_d_sccl_8/132-2883545-9921149?th=1 | O37: MAKEUP | P37: 4.45 | Q37: RMB | R37: 10000 | S37: =+P37*$T$29 -> #VALUE! | T37: =+S37*0.25 -> #VALUE! | U37: =(S37+T37)*0.0257 -> #VALUE! | V37: =S37+T37+U37 -> #VALUE! | W37: 169 | X37: =W37/1.16 -> 145.68966 | Y37: =X37*0.6 -> 87.413793 | Z37: =V37/Y37 -> #VALUE! | AA37: =1-(V37/Y37) -> #VALUE! | AB37: =1-(Y37/(W37/1.16)) -> 0.4 | AC37: China | AE37: 6 | AF37: 144 | AG37: Falta arte final de la caja. En espera suaje por parte de Daniel | AH37: 46341 | AL37: 109.85 | AM37: =+AL37/1.16 -> 94.698276 | AN37: =+V38/AM37 -> #VALUE! | AO37: =1-V38/AM37 -> #VALUE! | AP37: =1-(AM37/(AL37/1.16)) -> 0 | BA37: 1 | BB37: 1 | BC37: 1 | BD37: 1 | BE37: 1 | BF37: 1 | BG37: 1 | BJ37: 9 | BK37: =SUM(BA37:BI37) -> 7 | BL37: =+BK37/BJ37 -> 0.77777778 | BR37: PPEDIDOS-260827551 Se espera que PT este listo 24 Oct | BS37: 46376 | BT37: Eduardo (Compras) | CJ37: 46202
A38: 22 | B38: TBC | C38: Diciembre | D38: En tiempo | E38: 7502327991069 | F38: VLT-22 | G38: Primer Facial Iluminador Velvet "Primer Dewy" | H38: #VALUE! | I38: 65 g | J38: Velvet | K38: Mix de canales | L38: 1 | M38: MUC | N38: https://www.mercadolibre.com.mx/rhode-glazing-milk-leche-hidratante/up/MLMU3068912205?pdp_filters=item_id:MLM2260105059 | O38: MAKEUP | P38: 5.65 | Q38: RMB | R38: 10000 | S38: =+P38*$T$29 -> #VALUE! | T38: =+S38*0.25 -> #VALUE! | U38: =(S38+T38)*0.0745 -> #VALUE! | V38: =S38+T38+U38 -> #VALUE! | W38: 219 | X38: =W38/1.16 -> 188.7931 | Y38: =X38*0.6 -> 113.27586 | Z38: =V38/Y38 -> #VALUE! | AA38: =1-(V38/Y38) -> #VALUE! | AB38: =1-(Y38/(W38/1.16)) -> 0.4 | AC38: China | AE38: 6 | AF38: 72 | AG38: En revisión de dummy para autorización final | AH38: 46341 | AL38: 142.35 | AM38: =+AL38/1.16 -> 122.71552 | AN38: =+V39/AM38 -> #VALUE! | AO38: =1-V39/AM38 -> #VALUE! | AP38: =1-(AM38/(AL38/1.16)) -> 0 | BA38: 1 | BB38: 1 | BC38: 1 | BD38: 1 | BE38: 1 | BF38: 1 | BG38: 1 | BJ38: 9 | BK38: =SUM(BA38:BI38) -> 7 | BL38: =+BK38/BJ38 -> 0.77777778 | BR38: PPEDIDOS-260727520 Se espera que PT este listo 14 Octubre | BS38: 46373 | BT38: Eduardo (Compras) | CJ38: 46188
A39: 23 | B39: TBC | C39: Diciembre | D39: En tiempo | E39: 7502327991076 | F39: VLT-23 | G39: Polvo Traslúcido Velvet "Veil Cushion Powder" | H39: #VALUE! | I39: 6 g | J39: Velvet | K39: Mix de canales | L39: 1 | M39: MUC | N39: https://www.amazon.com/-/es/MAYBELLINE-Fit-Me-maquillaje-transl%C3%BAcido/dp/B00PFCSNWA/ref=zg_bs_g_11058971_d_sccl_1/132-2883545-9921149?psc=1 | O39: MAKEUP | P39: 9.15 | Q39: RMB | R39: 10000 | S39: =+P39*$T$29 -> #VALUE! | T39: =+S39*0.25 -> #VALUE! | U39: =(S39+T39)*0.0769 -> #VALUE! | V39: =S39+T39+U39 -> #VALUE! | W39: 259 | X39: =W39/1.16 -> 223.27586 | Y39: =X39*0.6 -> 133.96552 | Z39: =V39/Y39 -> #VALUE! | AA39: =1-(V39/Y39) -> #VALUE! | AB39: =1-(Y39/(W39/1.16)) -> 0.4 | AC39: China | AE39: 6 | AF39: 72 | AG39: En revisión de dummy para autorización final | AH39: 46341 | AL39: 168.35 | AM39: =+AL39/1.16 -> 145.12931 | AN39: =+V40/AM39 -> #VALUE! | AO39: =1-V40/AM39 -> #VALUE! | AP39: =1-(AM39/(AL39/1.16)) -> 0 | BA39: 1 | BB39: 1 | BC39: 1 | BD39: 1 | BE39: 1 | BF39: 1 | BG39: 1 | BJ39: 9 | BK39: =SUM(BA39:BI39) -> 7 | BL39: =+BK39/BJ39 -> 0.77777778 | BR39: PPEDIDOS-260727520 Se espera que PT este listo 19 Sept | BS39: 46376 | BT39: Eduardo (Compras) | CJ39: 46188
A40: 24 | B40: TBC | C40: Diciembre | D40: En tiempo | E40: 7502327991083 | F40: VLT-24 | G40: Sombra líquida para ojos Velvet "Glaze Liquid Eyeshadow Sunlit" | H40: #VALUE! | I40: 4 g | J40: Velvet | K40: Mix de canales | L40: 1 | M40: MUC | N40: https://www.amazon.com/-/es/l%C3%ADquida-met%C3%A1lica-multidimensional-cobertura-l%C3%ADquidas/dp/B0947DWWTN/ref=zg_bs_g_11058361_d_sccl_6/132-2883545-9921149?th=1 | O40: MAKEUP | P40: 3.85 | Q40: RMB | R40: 10000 | S40: =+P40*$T$29 -> #VALUE! | T40: =+S40*0.25 -> #VALUE! | U40: =(S40+T40)*0.0369 -> #VALUE! | V40: =S40+T40+U40 -> #VALUE! | W40: 149 | X40: =W40/1.16 -> 128.44828 | Y40: =X40*0.6 -> 77.068966 | Z40: =V40/Y40 -> #VALUE! | AA40: =1-(V40/Y40) -> #VALUE! | AB40: =1-(Y40/(W40/1.16)) -> 0.4 | AC40: China | AE40: 6 | AF40: 72 | AG40: En revisión de dummy para autorización final | AH40: 46341 | AL40: 96.85 | AM40: =+AL40/1.16 -> 83.491379 | AN40: =+V41/AM40 -> #VALUE! | AO40: =1-V41/AM40 -> #VALUE! | AP40: =1-(AM40/(AL40/1.16)) -> 0 | BA40: 1 | BB40: 1 | BC40: 1 | BD40: 1 | BE40: 1 | BF40: 1 | BG40: 1 | BJ40: 9 | BK40: =SUM(BA40:BI40) -> 7 | BL40: =+BK40/BJ40 -> 0.77777778 | BR40: PPEDIDOS-260727498 Se espera que PT este listo 25 Sept | BS40: 46378 | BT40: Eduardo (Compras)
A41: 25 | B41: TBC | C41: Diciembre | D41: En tiempo | E41: 7502327991090 | F41: VLT-25 | G41: Sombra líquida para ojos Velvet "Glaze Liquid Eyeshadow Dawnfire" | H41: #VALUE! | I41: 4 g | J41: Velvet | K41: Mix de canales | L41: 1 | M41: MUC | N41: https://www.amazon.com/-/es/l%C3%ADquida-met%C3%A1lica-multidimensional-cobertura-l%C3%ADquidas/dp/B0947BWDG7/ref=zg_bs_g_11058361_d_sccl_6/132-2883545-9921149?th=1 | O41: MAKEUP | P41: 3.85 | Q41: RMB | R41: 10000 | S41: =+P41*$T$29 -> #VALUE! | T41: =+S41*0.25 -> #VALUE! | U41: =(S41+T41)*0.0369 -> #VALUE! | V41: =S41+T41+U41 -> #VALUE! | W41: 149 | X41: =W41/1.16 -> 128.44828 | Y41: =X41*0.6 -> 77.068966 | Z41: =V41/Y41 -> #VALUE! | AA41: =1-(V41/Y41) -> #VALUE! | AB41: =1-(Y41/(W41/1.16)) -> 0.4 | AC41: China | AE41: 6 | AF41: 72 | AG41: En revisión de dummy para autorización final | AH41: 46341 | AL41: 96.85 | AM41: =+AL41/1.16 -> 83.491379 | AN41: =+V42/AM41 -> #VALUE! | AO41: =1-V42/AM41 -> #VALUE! | AP41: =1-(AM41/(AL41/1.16)) -> 0 | BA41: 1 | BB41: 1 | BC41: 1 | BD41: 1 | BE41: 1 | BF41: 1 | BG41: 1 | BJ41: 9 | BK41: =SUM(BA41:BI41) -> 7 | BL41: =+BK41/BJ41 -> 0.77777778 | BR41: PPEDIDOS-260727498 Se espera que PT este listo 25 Sept | BS41: 46378 | BT41: Eduardo (Compras)
A42: 26 | B42: TBC | C42: Diciembre | D42: En tiempo | E42: 7502327991106 | F42: VLT-26 | G42: Sombra líquida para ojos Velvet "Soft Mate Eyeshadow Stardrift" | H42: #VALUE! | I42: 4 g | J42: Velvet | K42: Mix de canales | L42: 1 | M42: MUC | N42: https://www.amazon.com/-/es/l%C3%ADquida-met%C3%A1lica-multidimensional-cobertura-l%C3%ADquidas/dp/B0947F4Y44/ref=zg_bs_g_11058361_d_sccl_6/132-2883545-9921149?th=1 | O42: MAKEUP | P42: 3.85 | Q42: RMB | R42: 10000 | S42: =+P42*$T$29 -> #VALUE! | T42: =+S42*0.25 -> #VALUE! | U42: =(S42+T42)*0.0369 -> #VALUE! | V42: =S42+T42+U42 -> #VALUE! | W42: 149 | X42: =W42/1.16 -> 128.44828 | Y42: =X42*0.6 -> 77.068966 | Z42: =V42/Y42 -> #VALUE! | AA42: =1-(V42/Y42) -> #VALUE! | AB42: =1-(Y42/(W42/1.16)) -> 0.4 | AC42: China | AE42: 6 | AF42: 72 | AG42: En revisión de dummy para autorización final | AH42: 46341 | AL42: 96.85 | AM42: =+AL42/1.16 -> 83.491379 | AN42: =+V43/AM42 -> #VALUE! | AO42: =1-V43/AM42 -> #VALUE! | AP42: =1-(AM42/(AL42/1.16)) -> 0 | BA42: 1 | BB42: 1 | BC42: 1 | BD42: 1 | BE42: 1 | BF42: 1 | BG42: 1 | BJ42: 9 | BK42: =SUM(BA42:BI42) -> 7 | BL42: =+BK42/BJ42 -> 0.77777778 | BR42: PPEDIDOS-260727498 Se espera que PT este listo 25 Sept | BS42: 46378 | BT42: Eduardo (Compras)
A43: 27 | B43: TBC | C43: Diciembre | D43: En tiempo | E43: 7502327991113 | F43: VLT-27 | G43: Sombra líquida para ojos Velvet "Glaze Liquid Eyeshadow Lovelight" | H43: #VALUE! | I43: 4 g | J43: Velvet | K43: Mix de canales | L43: 1 | M43: MUC | N43: https://www.amazon.com/-/es/l%C3%ADquida-met%C3%A1lica-multidimensional-cobertura-l%C3%ADquidas/dp/B0947BWZQ1/ref=zg_bs_g_11058361_d_sccl_6/132-2883545-9921149?th=1 | O43: MAKEUP | P43: 3.85 | Q43: RMB | R43: 10000 | S43: =+P43*$T$29 -> #VALUE! | T43: =+S43*0.25 -> #VALUE! | U43: =(S43+T43)*0.0369 -> #VALUE! | V43: =S43+T43+U43 -> #VALUE! | W43: 149 | X43: =W43/1.16 -> 128.44828 | Y43: =X43*0.6 -> 77.068966 | Z43: =V43/Y43 -> #VALUE! | AA43: =1-(V43/Y43) -> #VALUE! | AB43: =1-(Y43/(W43/1.16)) -> 0.4 | AC43: China | AE43: 6 | AF43: 72 | AG43: En revisión de dummy para autorización final | AH43: CANCELADO | AL43: 96.85 | AM43: =+AL43/1.16 -> 83.491379 | AN43: =+V44/AM43 -> #VALUE! | AO43: =1-V44/AM43 -> #VALUE! | AP43: =1-(AM43/(AL43/1.16)) -> 0 | BA43: 1 | BB43: 1 | BC43: 1 | BD43: 1 | BE43: 1 | BF43: 1 | BG43: 1 | BJ43: 9 | BK43: =SUM(BA43:BI43) -> 7 | BL43: =+BK43/BJ43 -> 0.77777778 | BR43: CANCELADO | BS43: 46378 | BT43: Eduardo (Compras)
A44: 28 | B44: TBC | C44: Diciembre | D44: En tiempo | E44: 7502327991120 | F44: VLT-28 | G44: Sombra líquida para ojos Velvet "Glaze Liquid Eyeshadow Bronze Dust" | H44: #VALUE! | I44: 4 g | J44: Velvet | K44: Mix de canales | L44: 1 | M44: MUC | N44: https://www.amazon.com/-/es/l%C3%ADquida-met%C3%A1lica-multidimensional-cobertura-l%C3%ADquidas/dp/B09487B9DF/ref=zg_bs_g_11058361_d_sccl_6/132-2883545-9921149?th=1 | O44: MAKEUP | P44: 3.85 | Q44: RMB | R44: 10000 | S44: =+P44*$T$29 -> #VALUE! | T44: =+S44*0.25 -> #VALUE! | U44: =(S44+T44)*0.0369 -> #VALUE! | V44: =S44+T44+U44 -> #VALUE! | W44: 149 | X44: =W44/1.16 -> 128.44828 | Y44: =X44*0.6 -> 77.068966 | Z44: =V44/Y44 -> #VALUE! | AA44: =1-(V44/Y44) -> #VALUE! | AB44: =1-(Y44/(W44/1.16)) -> 0.4 | AC44: China | AE44: 6 | AF44: 72 | AG44: En revisión de dummy para autorización final | AH44: CANCELADO | AL44: 96.85 | AM44: =+AL44/1.16 -> 83.491379 | AN44: =+V45/AM44 -> #VALUE! | AO44: =1-V45/AM44 -> #VALUE! | AP44: =1-(AM44/(AL44/1.16)) -> 0 | BA44: 1 | BB44: 1 | BC44: 1 | BD44: 1 | BE44: 1 | BF44: 1 | BG44: 1 | BJ44: 9 | BK44: =SUM(BA44:BI44) -> 7 | BL44: =+BK44/BJ44 -> 0.77777778 | BR44: CANCELADO | BS44: =AH44 -> CANCELADO | BT44: Eduardo (Compras)
A45: 29 | B45: TBC | C45: Diciembre | D45: En tiempo | E45: 7502327991137 | F45: VLT-29 | G45: Sombra líquida para ojos Velvet "Glaze Liquid Eyeshadow Peachveil" | H45: #VALUE! | I45: 4 g | J45: Velvet | K45: Mix de canales | L45: 1 | M45: MUC | N45: https://www.amazon.com/-/es/l%C3%ADquida-met%C3%A1lica-multidimensional-cobertura-l%C3%ADquidas/dp/B0984X94WK/ref=zg_bs_g_11058361_d_sccl_6/132-2883545-9921149?th=1 | O45: MAKEUP | P45: 3.85 | Q45: RMB | R45: 10000 | S45: =+P45*$T$29 -> #VALUE! | T45: =+S45*0.25 -> #VALUE! | U45: =(S45+T45)*0.0369 -> #VALUE! | V45: =S45+T45+U45 -> #VALUE! | W45: 149 | X45: =W45/1.16 -> 128.44828 | Y45: =X45*0.6 -> 77.068966 | Z45: =V45/Y45 -> #VALUE! | AA45: =1-(V45/Y45) -> #VALUE! | AB45: =1-(Y45/(W45/1.16)) -> 0.4 | AC45: China | AE45: 6 | AF45: 72 | AG45: En revisión de dummy para autorización final | AH45: 46341 | AL45: 96.85 | AM45: =+AL45/1.16 -> 83.491379 | AN45: =+V46/AM45 -> #VALUE! | AO45: =1-V46/AM45 -> #VALUE! | AP45: =1-(AM45/(AL45/1.16)) -> 0 | BA45: 1 | BB45: 1 | BC45: 1 | BD45: 1 | BE45: 1 | BF45: 1 | BG45: 1 | BJ45: 9 | BK45: =SUM(BA45:BI45) -> 7 | BL45: =+BK45/BJ45 -> 0.77777778 | BR45: PPEDIDOS-260727498 Se espera que PT este listo 25 Sept | BS45: 46378 | BT45: Eduardo (Compras)
A46: 30 | B46: TBC | C46: Diciembre | D46: En tiempo | E46: 7502327991144 | F46: VLT-30 | G46: Delineador en plumón para ojos Velvet "Graphite Satin Ink" | H46: #VALUE! | I46: 0.5 g | J46: Velvet | K46: Mix de canales | L46: 1 | M46: MUC | N46: https://www.amazon.com.mx/maybelline-new-york-Delineador-resistente/dp/B07W8JJ61X/ref=sr_1_13?__mk_es_MX=%C3%85M%C3%85%C5%BD%C3%95%C3%91&crid=2GP1LPU8DCJGT&dib=eyJ2IjoiMSJ9.X5H9JN8c1SZ6yXE1iOfZ7q5kG8Da2b5F3IR7lPShDB26RxcoEEN0uiJ1_VG1VZMrDpgULmB3zqFpBwMbWA_vbEjrYbKPjdKTLfXhD9q-vDvt5Fr0r8X__pOYrmvcjb7TLU5_wFp3XUnj1JBCRiOxfEaSJvj8KPShghpHZcUtjbfj-cc5XvPU4JYXngTP6VCCw45HBbeLkbuOlygZtZLrJEbfIJX5cNxiUdgPiFrjAxSl-7YY5DZ_-svi55f4IEQ9CxSFCyJd-30rqRznNHn4KO_fff-sdRoPE8nR-W5Hxrs.wld7TdhxK5SosWRIOszo2oady6wVIPMUmFWpxD_2nSQ&dib_tag=se&keywords=delineador%2Bsatinado&qid=1755106894&sprefix=delienador%2Bsatinado%2Caps%2C167&sr=8-13&ufe=app_do%3Aamzn1.fos.de93fa6a-174c-4df7-be7c-5bc8e9c5a71b&th=1 | O46: MAKEUP | P46: 3.85 | Q46: RMB | R46: 10000 | S46: =+P46*$T$29 -> #VALUE! | T46: =+S46*0.25 -> #VALUE! | U46: =(S46+T46)*0.0123 -> #VALUE! | V46: =S46+T46+U46 -> #VALUE! | W46: 159 | X46: =W46/1.16 -> 137.06897 | Y46: =X46*0.6 -> 82.241379 | Z46: =V46/Y46 -> #VALUE! | AA46: =1-(V46/Y46) -> #VALUE! | AB46: =1-(Y46/(W46/1.16)) -> 0.4 | AC46: China | AE46: 6 | AF46: 144 | AG46: En revisión de dummy para autorización final | AH46: 46341 | AL46: 103.35 | AM46: =+AL46/1.16 -> 89.094828 | AN46: =+V47/AM46 -> #VALUE! | AO46: =1-V47/AM46 -> #VALUE! | AP46: =1-(AM46/(AL46/1.16)) -> 0 | BA46: 1 | BB46: 1 | BC46: 1 | BD46: 1 | BE46: 1 | BF46: 1 | BG46: 1 | BJ46: 9 | BK46: =SUM(BA46:BI46) -> 7 | BL46: =+BK46/BJ46 -> 0.77777778 | BR46: PPEDIDOS-260827551 Se espera que PT este listo 24 Oct | BS46: 46374 | BT46: Eduardo (Compras)
A47: 31 | B47: TBC | C47: Diciembre | D47: En tiempo | E47: 7502327991151 | F47: VLT-31 | G47: Delineador en plumón para ojos Velvet "Graphite Matte Ink" | H47: #VALUE! | I47: 0.5 g | J47: Velvet | K47: Mix de canales | L47: 1 | M47: MUC | N47: https://www.amazon.com.mx/Maybelline-delineador-superpreciso-transfiere-pigmentos/dp/B0BZ7SMYSF/ref=zg_bs_g_10178482011_d_sccl_2/139-5127535-4936938?th=1 | O47: MAKEUP | P47: 4.3 | Q47: RMB | R47: 10000 | S47: =+P47*$T$29 -> #VALUE! | T47: =+S47*0.25 -> #VALUE! | U47: =(S47+T47)*0.0123 -> #VALUE! | V47: =S47+T47+U47 -> #VALUE! | W47: 159 | X47: =W47/1.16 -> 137.06897 | Y47: =X47*0.6 -> 82.241379 | Z47: =V47/Y47 -> #VALUE! | AA47: =1-(V47/Y47) -> #VALUE! | AB47: =1-(Y47/(W47/1.16)) -> 0.4 | AC47: China | AE47: 6 | AF47: 144 | AG47: En revisión de dummy para autorización final | AH47: 46341 | AL47: 103.35 | AM47: =+AL47/1.16 -> 89.094828 | AN47: =+V48/AM47 -> #VALUE! | AO47: =1-V48/AM47 -> #VALUE! | AP47: =1-(AM47/(AL47/1.16)) -> 0 | BA47: 1 | BB47: 1 | BC47: 1 | BD47: 1 | BE47: 1 | BF47: 1 | BG47: 1 | BJ47: 9 | BK47: =SUM(BA47:BI47) -> 7 | BL47: =+BK47/BJ47 -> 0.77777778 | BR47: PPEDIDOS-260827551 Se espera que PT este listo 24 Oct | BS47: 46374 | BT47: Eduardo (Compras)
A48: 32 | B48: TBC | C48: Diciembre | D48: En tiempo | E48: 7502327991168 | F48: VLT-32 | G48: Gel Fijador para Cejas Velvet "Brow-Define Cocoa" | H48: #VALUE! | I48: 5 mL | J48: Velvet | K48: Mix de canales | L48: 1 | M48: USHAS | N48: https://www.amazon.com.mx/Maybelline-New-York-Tattoo-estilizador/dp/B0B35622GD/ref=zg_bs_g_10178480011_d_sccl_9/139-5127535-4936938?th=1 | O48: MAKEUP | P48: 3.2 | Q48: RMB | R48: 10000 | S48: =+P48*$T$29 -> #VALUE! | T48: =+S48*0.25 -> #VALUE! | U48: =(S48+T48)*0.0691 -> #VALUE! | V48: =S48+T48+U48 -> #VALUE! | W48: 169 | X48: =W48/1.16 -> 145.68966 | Y48: =X48*0.6 -> 87.413793 | Z48: =V48/Y48 -> #VALUE! | AA48: =1-(V48/Y48) -> #VALUE! | AB48: =1-(Y48/(W48/1.16)) -> 0.4 | AC48: China | AE48: 6 | AF48: 144 | AG48: En revisión de dummy para autorización final | AH48: 46366 | AL48: 109.85 | AM48: =+AL48/1.16 -> 94.698276 | AN48: =+V49/AM48 -> #VALUE! | AO48: =1-V49/AM48 -> #VALUE! | AP48: =1-(AM48/(AL48/1.16)) -> 0 | BA48: 1 | BB48: 1 | BC48: 1 | BD48: 1 | BE48: 1 | BF48: 1 | BG48: 1 | BJ48: 9 | BK48: =SUM(BA48:BI48) -> 7 | BL48: =+BK48/BJ48 -> 0.77777778 | BR48: PPEDIDOS-260827594 Se espera que PT este listo 09 Nov | BS48: 46038 | BT48: Eduardo (Compras)
A49: 33 | B49: TBC | C49: Diciembre | D49: En tiempo | E49: 7502327991175 | F49: VLT-33 | G49: Gel Fijador para Cejas Velvet "Brow-Define Espresso" | H49: #VALUE! | I49: 5 mL | J49: Velvet | K49: Mix de canales | L49: 1 | M49: USHAS | N49: https://www.amazon.com.mx/Maybelline-New-York-Tattoo-estilizador/dp/B0B3553Q1N/ref=zg_bs_g_10178480011_d_sccl_9/139-5127535-4936938?th=1 | O49: MAKEUP | P49: 3.2 | Q49: RMB | R49: 10000 | S49: =+P49*$T$29 -> #VALUE! | T49: =+S49*0.25 -> #VALUE! | U49: =(S49+T49)*0.0691 -> #VALUE! | V49: =S49+T49+U49 -> #VALUE! | W49: 169 | X49: =W49/1.16 -> 145.68966 | Y49: =X49*0.6 -> 87.413793 | Z49: =V49/Y49 -> #VALUE! | AA49: =1-(V49/Y49) -> #VALUE! | AB49: =1-(Y49/(W49/1.16)) -> 0.4 | AC49: China | AE49: 6 | AF49: 144 | AG49: En revisión de dummy para autorización final | AH49: 46366 | AL49: 109.85 | AM49: =+AL49/1.16 -> 94.698276 | AN49: =+V50/AM49 -> #VALUE! | AO49: =1-V50/AM49 -> #VALUE! | AP49: =1-(AM49/(AL49/1.16)) -> 0 | BA49: 1 | BB49: 1 | BC49: 1 | BD49: 1 | BE49: 1 | BF49: 1 | BG49: 1 | BJ49: 9 | BK49: =SUM(BA49:BI49) -> 7 | BL49: =+BK49/BJ49 -> 0.77777778 | BR49: PPEDIDOS-260827594 Se espera que PT este listo 09 Nov | BS49: 46038 | BT49: Eduardo (Compras)
A50: 34 | B50: TBC | C50: Diciembre | D50: En tiempo | E50: 7502327991182 | F50: VLT-34 | G50: Gel Fijador para Cejas Velvet "Brow-Define Clear" | H50: #VALUE! | I50: 5 mL | J50: Velvet | K50: Mix de canales | L50: 1 | M50: USHAS | N50: https://www.amazon.com.mx/Yuya-Republic-Cosmetics-Fijador-Cejas/dp/B09BK45HG6/ref=sr_1_7?adgrpid=139157503839&dib=eyJ2IjoiMSJ9.5DqSaVcsUTfgLgN-QWSll5jbbOGZ7z-DNIt7LyxZCQLaC3qJN51vdMbRIgHIl9dHdf3IVjXz8zOrwBkAFjTHdeJG62-068rlcsbW0-UUs-zNQMGDWJnVmY_KStQZZGLXWQZFKkA6fMH6aax3s4nLTat3c9aMv_8mB4Xi_4ewkEab7Gg4ALHDi-jj9txzJoHYelnEvfLOn8qGvuwxkt8gRN2jLr3HAljmy77u07vYFhpemX_xW730T5bLenIccOSqVJoiS2NwJka1nUdGofw4r5YyGiA-lttrexTerPE7T70.nAduoSvs08ullPUDva-YI4qmumL7lcsGO7b8EJwcXSA&dib_tag=se&hvadid=678098102325&hvdev=c&hvlocphy=9047088&hvnetw=g&hvqmt=b&hvrand=16028351888192121247&hvtargid=kwd-546089015882&hydadcr=4092_13211314&keywords=by+yuya&mcid=f8f8e7cbac583eec92a8fec9ec3b5ee9&qid=1755717129&sr=8-7 | O50: MAKEUP | P50: 2.9 | Q50: RMB | R50: 10000 | S50: =+P50*$T$29 -> #VALUE! | T50: =+S50*0.25 -> #VALUE! | U50: =(S50+T50)*0.0762 -> #VALUE! | V50: =S50+T50+U50 -> #VALUE! | W50: 169 | X50: =W50/1.16 -> 145.68966 | Y50: =X50*0.6 -> 87.413793 | Z50: =V50/Y50 -> #VALUE! | AA50: =1-(V50/Y50) -> #VALUE! | AB50: =1-(Y50/(W50/1.16)) -> 0.4 | AC50: China | AE50: 6 | AF50: 144 | AG50: En revisión de dummy para autorización final | AH50: 46366 | AL50: 109.85 | AM50: =+AL50/1.16 -> 94.698276 | AN50: =+V51/AM50 -> 0.2323168 | AO50: =1-V51/AM50 -> 0.7676832 | AP50: =1-(AM50/(AL50/1.16)) -> 0 | BA50: 1 | BB50: 1 | BC50: 1 | BD50: 1 | BE50: 1 | BF50: 1 | BG50: 1 | BJ50: 9 | BK50: =SUM(BA50:BI50) -> 7 | BL50: =+BK50/BJ50 -> 0.77777778 | BR50: PPEDIDOS-260827594 Se espera que PT este listo 09 Nov | BS50: 46038 | BT50: Eduardo (Compras)
A51: 35 | B51: TBC | C51: Diciembre | D51: En tiempo | E51: 7502327991199 | F51: VLT-35 | G51: Máscara para pestañas Velvet "Lash Bold" | H51: #VALUE! | I51: 20 g | J51: Velvet | K51: Mix de canales | L51: 1 | M51: RC | N51: https://www.sephora.com.mx/products/benefit-cosmetics-badgal-bang-12847.html?srsltid=AfmBOoofbaVebzZAwnPukJ7Cu5bt2jy0-mIyY2JRAmBtQJUAk_v9mUgA | O51: MAKEUP | Q51: MX | R51: 10000 | S51: 22 | V51: =S51+T51+U51 -> 22 | W51: 199 | X51: =W51/1.16 -> 171.55172 | Y51: =X51*0.6 -> 102.93103 | Z51: =V51/Y51 -> 0.21373534 | AA51: =1-(V51/Y51) -> 0.78626466 | AB51: =1-(Y51/(W51/1.16)) -> 0.4 | AC51: China | AE51: 6 | AF51: 144 | AG51: En revisión de dummy para autorización final | AH51: 46361 | AL51: 129.35 | AM51: =+AL51/1.16 -> 111.50862 | AN51: =+V52/AM51 -> 0.07516703 | AO51: =1-V52/AM51 -> 0.92483297 | AP51: =1-(AM51/(AL51/1.16)) -> 0 | BA51: 1 | BB51: 1 | BC51: 1 | BD51: 1 | BE51: 1 | BF51: 1 | BJ51: 9 | BK51: =SUM(BA51:BI51) -> 6 | BL51: =+BK51/BJ51 -> 0.66666667 | BS51: =AH51 -> 46361 | BT51: Eduardo (Compras)
A52: 36 | B52: TBC | C52: Diciembre | D52: En tiempo | E52: 7502327991205 | F52: VLT-36 | G52: Lápiz para cejas "Brow Pencil Cocoa" | H52: #VALUE! | I52: 0.09 g | J52: Velvet | K52: Mix de canales | L52: 1 | M52: Herbeauty | N52: https://www.amazon.com.mx/Maybelline-delineador-estilizarla-rellenarla-transfiere/dp/B0B2NHP7YV/ref=zg_bs_g_10178480011_d_sccl_4/139-5127535-4936938?th=1 | O52: MAKEUP | P52: 0.355 | Q52: USD | R52: 10000 | S52: =+P52*18.5 -> 6.5675 | T52: =+S52*0.25 -> 1.641875 | U52: =(S52+T52)*0.021 -> 0.17239688 | V52: =S52+T52+U52 -> 8.3817719 | W52: 149 | X52: =W52/1.16 -> 128.44828 | Y52: =X52*0.6 -> 77.068966 | Z52: =V52/Y52 -> 0.10875677 | AA52: =1-(V52/Y52) -> 0.89124323 | AB52: =1-(Y52/(W52/1.16)) -> 0.4 | AC52: China | AE52: 6 | AF52: 144 | AG52: En revisión de dummy para autorización final | AH52: 46341 | AL52: 96.85 | AM52: =+AL52/1.16 -> 83.491379 | AN52: =+V53/AM52 -> 0.10039087 | AO52: =1-V53/AM52 -> 0.89960913 | AP52: =1-(AM52/(AL52/1.16)) -> 0 | BA52: 1 | BB52: 1 | BC52: 1 | BD52: 1 | BE52: 1 | BF52: 1 | BG52: 1 | BJ52: 9 | BK52: =SUM(BA52:BI52) -> 7 | BL52: =+BK52/BJ52 -> 0.77777778 | BR52: PPEDIDOS-260727509 Se espera tener PT listo 22 Sept | BS52: 46355 | BT52: Eduardo (Compras)
A53: 37 | B53: TBC | C53: Diciembre | D53: En tiempo | E53: 7502327991212 | F53: VLT-37 | G53: Lápiz para cejas "Brow Pencil Espresso" | H53: #VALUE! | I53: 0.09 g | J53: Velvet | K53: Mix de canales | L53: 1 | M53: Herbeauty | N53: https://www.amazon.com.mx/Maybelline-delineador-estilizarla-rellenarla-transfiere/dp/B0B2NHMR5P/ref=zg_bs_g_10178480011_d_sccl_4/139-5127535-4936938?th=1 | O53: MAKEUP | P53: 0.355 | Q53: USD | R53: 10000 | S53: =+P53*18.5 -> 6.5675 | T53: =+S53*0.25 -> 1.641875 | U53: =(S53+T53)*0.021 -> 0.17239688 | V53: =S53+T53+U53 -> 8.3817719 | W53: 149 | X53: =W53/1.16 -> 128.44828 | Y53: =X53*0.6 -> 77.068966 | Z53: =V53/Y53 -> 0.10875677 | AA53: =1-(V53/Y53) -> 0.89124323 | AB53: =1-(Y53/(W53/1.16)) -> 0.4 | AC53: China | AE53: 6 | AF53: 144 | AG53: En revisión de dummy para autorización final | AH53: 46341 | AL53: 96.85 | AM53: =+AL53/1.16 -> 83.491379 | AN53: =+V54/AM53 -> #VALUE! | AO53: =1-V54/AM53 -> #VALUE! | AP53: =1-(AM53/(AL53/1.16)) -> 0 | BA53: 1 | BB53: 1 | BC53: 1 | BD53: 1 | BE53: 1 | BF53: 1 | BG53: 1 | BJ53: 9 | BK53: =SUM(BA53:BI53) -> 7 | BL53: =+BK53/BJ53 -> 0.77777778 | BR53: PPEDIDOS-260727509 Se espera tener PT listo 22 Sept | BS53: 46355 | BT53: Eduardo (Compras)
A54: 38 | B54: TBC | C54: Diciembre | D54: En tiempo | E54: 7502327991229 | F54: VLT-38 | G54: Labial Gloss con colgante Velvet "Lip Glaze True" | H54: #VALUE! | I54: 12.5 g | J54: Velvet | K54: Mix de canales | L54: 1 | M54: USHAS | N54: https://www.amazon.com.mx/gp/aw/d/B0F2TS79HS/?_encoding=UTF8&pd_rd_plhdr=t&aaxitk=b9cc468649bc8da8a4b40dab37c68acc&hsa_cr_id=0&qid=1755107150&sr=1-1-9e67e56a-6f64-441f-a281-df67fc737124&ref_=sbx_be_s_sparkle_lsi4d_asin_0_title&pd_rd_w=Jz3uq&content-id=amzn1.sym.cc2c6205-3abd-4de8-9a5e-9263ccb1e66a%3Aamzn1.sym.cc2c6205-3abd-4de8-9a5e-9263ccb1e66a&pf_rd_p=cc2c6205-3abd-4de8-9a5e-9263ccb1e66a&pf_rd_r=YK4AKDSA4HDJ27GXNPGJ&pd_rd_wg=vzXnI&pd_rd_r=4b81acff-6719-4d1f-8ca8-d6df26ac1343&th=1 | O54: MAKEUP | P54: 6.8 | Q54: RMB | R54: 10000 | S54: =+P54*$T$29 -> #VALUE! | T54: =+S54*0.36 -> #VALUE! | U54: =(S54+T54)*0.0586 -> #VALUE! | V54: =S54+T54+U54 -> #VALUE! | W54: 179 | X54: =W54/1.16 -> 154.31034 | Y54: =X54*0.6 -> 92.586207 | Z54: =V54/Y54 -> #VALUE! | AA54: =1-(V54/Y54) -> #VALUE! | AB54: =1-(Y54/(W54/1.16)) -> 0.4 | AC54: China | AE54: 6 | AF54: 144 | AG54: En revisión de dummy para autorización final | AH54: 46366 | AL54: 116.35 | AM54: =+AL54/1.16 -> 100.30172 | AN54: =+V55/AM54 -> #VALUE! | AO54: =1-V55/AM54 -> #VALUE! | AP54: =1-(AM54/(AL54/1.16)) -> 0 | BA54: 1 | BB54: 1 | BC54: 1 | BD54: 1 | BE54: 1 | BF54: 1 | BJ54: 9 | BK54: =SUM(BA54:BI54) -> 6 | BL54: =+BK54/BJ54 -> 0.66666667 | BR54: En revisión por costos | BS54: =AH54 -> 46366 | BT54: Eduardo (Compras)
A55: 39 | B55: TBC | C55: Diciembre | D55: En tiempo | E55: 7502327991236 | F55: VLT-39 | G55: Labial Gloss con colgante Velvet "Lip Glaze Essence" | H55: #VALUE! | I55: 12.5 g | J55: Velvet | K55: Mix de canales | L55: 1 | M55: USHAS | N55: https://www.amazon.com.mx/gp/aw/d/B0F1P544FK/?_encoding=UTF8&pd_rd_plhdr=t&aaxitk=b9cc468649bc8da8a4b40dab37c68acc&hsa_cr_id=0&qid=1755107150&sr=1-1-9e67e56a-6f64-441f-a281-df67fc737124&ref_=sbx_be_s_sparkle_lsi4d_asin_0_title&pd_rd_w=Jz3uq&content-id=amzn1.sym.cc2c6205-3abd-4de8-9a5e-9263ccb1e66a%3Aamzn1.sym.cc2c6205-3abd-4de8-9a5e-9263ccb1e66a&pf_rd_p=cc2c6205-3abd-4de8-9a5e-9263ccb1e66a&pf_rd_r=YK4AKDSA4HDJ27GXNPGJ&pd_rd_wg=vzXnI&pd_rd_r=4b81acff-6719-4d1f-8ca8-d6df26ac1343&th=1 | O55: MAKEUP | P55: 6.8 | Q55: RMB | R55: 10000 | S55: =+P55*$T$29 -> #VALUE! | T55: =+S55*0.36 -> #VALUE! | U55: =(S55+T55)*0.0586 -> #VALUE! | V55: =S55+T55+U55 -> #VALUE! | W55: 179 | X55: =W55/1.16 -> 154.31034 | Y55: =X55*0.6 -> 92.586207 | Z55: =V55/Y55 -> #VALUE! | AA55: =1-(V55/Y55) -> #VALUE! | AB55: =1-(Y55/(W55/1.16)) -> 0.4 | AC55: China | AE55: 6 | AF55: 144 | AG55: En revisión de dummy para autorización final | AH55: 46366 | AL55: 116.35 | AM55: =+AL55/1.16 -> 100.30172 | AN55: =+V56/AM55 -> #VALUE! | AO55: =1-V56/AM55 -> #VALUE! | AP55: =1-(AM55/(AL55/1.16)) -> 0 | BA55: 1 | BB55: 1 | BC55: 1 | BD55: 1 | BE55: 1 | BF55: 1 | BJ55: 9 | BK55: =SUM(BA55:BI55) -> 6 | BL55: =+BK55/BJ55 -> 0.66666667 | BR55: En revisión por costos | BS55: =AH55 -> 46366 | BT55: Eduardo (Compras)
A56: 40 | B56: TBC | C56: Diciembre | D56: En tiempo | E56: 7502327991243 | F56: VLT-40 | G56: Labial Gloss con colgante Velvet "Lip Glaze Grace" | H56: #VALUE! | I56: 12.5 g | J56: Velvet | K56: Mix de canales | L56: 1 | M56: USHAS | N56: https://www.amazon.com.mx/gp/aw/d/B0F1P4P9WZ/?_encoding=UTF8&pd_rd_plhdr=t&aaxitk=b9cc468649bc8da8a4b40dab37c68acc&hsa_cr_id=0&qid=1755107150&sr=1-1-9e67e56a-6f64-441f-a281-df67fc737124&ref_=sbx_be_s_sparkle_lsi4d_asin_0_title&pd_rd_w=Jz3uq&content-id=amzn1.sym.cc2c6205-3abd-4de8-9a5e-9263ccb1e66a%3Aamzn1.sym.cc2c6205-3abd-4de8-9a5e-9263ccb1e66a&pf_rd_p=cc2c6205-3abd-4de8-9a5e-9263ccb1e66a&pf_rd_r=YK4AKDSA4HDJ27GXNPGJ&pd_rd_wg=vzXnI&pd_rd_r=4b81acff-6719-4d1f-8ca8-d6df26ac1343&th=1 | O56: MAKEUP | P56: 6.8 | Q56: RMB | R56: 10000 | S56: =+P56*$T$29 -> #VALUE! | T56: =+S56*0.36 -> #VALUE! | U56: =(S56+T56)*0.0586 -> #VALUE! | V56: =S56+T56+U56 -> #VALUE! | W56: 179 | X56: =W56/1.16 -> 154.31034 | Y56: =X56*0.6 -> 92.586207 | Z56: =V56/Y56 -> #VALUE! | AA56: =1-(V56/Y56) -> #VALUE! | AB56: =1-(Y56/(W56/1.16)) -> 0.4 | AC56: China | AE56: 6 | AF56: 144 | AG56: En revisión de dummy para autorización final | AH56: 46366 | AL56: 116.35 | AM56: =+AL56/1.16 -> 100.30172 | AN56: =+V57/AM56 -> #VALUE! | AO56: =1-V57/AM56 -> #VALUE! | AP56: =1-(AM56/(AL56/1.16)) -> 0 | BA56: 1 | BB56: 1 | BC56: 1 | BD56: 1 | BE56: 1 | BF56: 1 | BJ56: 9 | BK56: =SUM(BA56:BI56) -> 6 | BL56: =+BK56/BJ56 -> 0.66666667 | BR56: En revisión por costos | BS56: =AH56 -> 46366 | BT56: Eduardo (Compras)
A57: 41 | B57: TBC | C57: Diciembre | D57: En tiempo | E57: 7502327991250 | F57: VLT-41 | G57: Aceite para labios Velvet "Lip Nectar Raspberry" | H57: #VALUE! | I57: 3.5 g | J57: Velvet | K57: Mix de canales | L57: 1 | M57: MUC | N57: https://www.amazon.com.mx/Brillo-labial-NYX-Professional-Makeup/dp/B0D6871LGP/ref=sr_1_5?__mk_es_MX=%C3%85M%C3%85%C5%BD%C3%95%C3%91&crid=1F2MXEYL4UXTN&dib=eyJ2IjoiMSJ9.AW9m6Onz6H_t42c4UIiBOwwX16eJOANPELS00G79-sWNKHtsZBbjrSGHT3pFo8gjIenHMpSoE6ZX2MdL4YKVHm5ydZeYRMEd5oQCfstWzGwWmTDMXEtpdn0M-96tYxcoLHETpvMSfVaVFm3dJiLD-8PsUrcA5LFfQxRsp9toF6ZNbZRHSyRzo25c7IVAqSOxgjXV2BLG8IkClKqF_wqluRt2LV2y1s04aFrY3QSJ4Q7oi_7GBoEH4JLqzsllIYamsCGI4BExP7fhuy5nOp69Mv-qJX9TsltF8fBBBVz0mNg.SXQV92bAHeZ7xvttpfYUd1CsrWS2ULnSSIw3sehUadg&dib_tag=se&keywords=lio%2Boil&qid=1755107688&sprefix=lio%2Boil%2Caps%2C149&sr=8-5&ufe=app_do%3Aamzn1.fos.de93fa6a-174c-4df7-be7c-5bc8e9c5a71b&th=1 | O57: MAKEUP | P57: 4.45 | Q57: RMB | R57: 10000 | S57: =+P57*$T$29 -> #VALUE! | T57: =+S57*0.36 -> #VALUE! | U57: =(S57+T57)*0.0248 -> #VALUE! | V57: =S57+T57+U57 -> #VALUE! | W57: 159 | X57: =W57/1.16 -> 137.06897 | Y57: =X57*0.6 -> 82.241379 | Z57: =V57/Y57 -> #VALUE! | AA57: =1-(V57/Y57) -> #VALUE! | AB57: =1-(Y57/(W57/1.16)) -> 0.4 | AC57: China | AE57: 6 | AF57: 144 | AG57: En revisión de dummy para autorización final | AH57: 46341 | AL57: 103.35 | AM57: =+AL57/1.16 -> 89.094828 | AN57: =+V58/AM57 -> #VALUE! | AO57: =1-V58/AM57 -> #VALUE! | AP57: =1-(AM57/(AL57/1.16)) -> 0 | BA57: 1 | BB57: 1 | BC57: 1 | BD57: 1 | BE57: 1 | BF57: 1 | BG57: 1 | BJ57: 9 | BK57: =SUM(BA57:BI57) -> 7 | BL57: =+BK57/BJ57 -> 0.77777778 | BR57: PPEDIDOS-260727498 Se espera que PT este listo 25 Sept | BS57: 46373 | BT57: Eduardo (Compras)
A58: 42 | B58: TBC | C58: Diciembre | D58: En tiempo | E58: 7502327991267 | F58: VLT-42 | G58: Aceite para labios Velvet "Lip Nectar Papaya" | H58: #VALUE! | I58: 3.5 g | J58: Velvet | K58: Mix de canales | L58: 1 | M58: MUC | N58: https://www.amazon.com.mx/Brillo-labial-NYX-Professional-Makeup/dp/B0D6871LGP/ref=sr_1_5?__mk_es_MX=%C3%85M%C3%85%C5%BD%C3%95%C3%91&crid=1F2MXEYL4UXTN&dib=eyJ2IjoiMSJ9.AW9m6Onz6H_t42c4UIiBOwwX16eJOANPELS00G79-sWNKHtsZBbjrSGHT3pFo8gjIenHMpSoE6ZX2MdL4YKVHm5ydZeYRMEd5oQCfstWzGwWmTDMXEtpdn0M-96tYxcoLHETpvMSfVaVFm3dJiLD-8PsUrcA5LFfQxRsp9toF6ZNbZRHSyRzo25c7IVAqSOxgjXV2BLG8IkClKqF_wqluRt2LV2y1s04aFrY3QSJ4Q7oi_7GBoEH4JLqzsllIYamsCGI4BExP7fhuy5nOp69Mv-qJX9TsltF8fBBBVz0mNg.SXQV92bAHeZ7xvttpfYUd1CsrWS2ULnSSIw3sehUadg&dib_tag=se&keywords=lio%2Boil&qid=1755107688&sprefix=lio%2Boil%2Caps%2C149&sr=8-5&ufe=app_do%3Aamzn1.fos.de93fa6a-174c-4df7-be7c-5bc8e9c5a71b&th=1 | O58: MAKEUP | P58: 4.45 | Q58: RMB | R58: 10000 | S58: =+P58*$T$29 -> #VALUE! | T58: =+S58*0.36 -> #VALUE! | U58: =(S58+T58)*0.0248 -> #VALUE! | V58: =S58+T58+U58 -> #VALUE! | W58: 159 | X58: =W58/1.16 -> 137.06897 | Y58: =X58*0.6 -> 82.241379 | Z58: =V58/Y58 -> #VALUE! | AA58: =1-(V58/Y58) -> #VALUE! | AB58: =1-(Y58/(W58/1.16)) -> 0.4 | AC58: China | AE58: 6 | AF58: 144 | AG58: En revisión de dummy para autorización final | AH58: 46341 | AL58: 103.35 | AM58: =+AL58/1.16 -> 89.094828 | AN58: =+V59/AM58 -> #VALUE! | AO58: =1-V59/AM58 -> #VALUE! | AP58: =1-(AM58/(AL58/1.16)) -> 0 | BA58: 1 | BB58: 1 | BC58: 1 | BD58: 1 | BE58: 1 | BF58: 1 | BG58: 1 | BJ58: 9 | BK58: =SUM(BA58:BI58) -> 7 | BL58: =+BK58/BJ58 -> 0.77777778 | BR58: PPEDIDOS-260727498 Se espera que PT este listo 25 Sept | BS58: 46373 | BT58: Eduardo (Compras)
A59: 43 | B59: TBC | C59: Diciembre | D59: En tiempo | E59: 7502327991274 | F59: VLT-43 | G59: Aceite para labios Velvet "Lip Nectar Dragonfruit" | H59: #VALUE! | I59: 3.5 g | J59: Velvet | K59: Mix de canales | L59: 1 | M59: MUC | N59: https://www.amazon.com.mx/Brillo-labial-NYX-Professional-Makeup/dp/B0D68GVTZN/ref=sr_1_5?__mk_es_MX=%C3%85M%C3%85%C5%BD%C3%95%C3%91&crid=1F2MXEYL4UXTN&dib=eyJ2IjoiMSJ9.AW9m6Onz6H_t42c4UIiBOwwX16eJOANPELS00G79-sWNKHtsZBbjrSGHT3pFo8gjIenHMpSoE6ZX2MdL4YKVHm5ydZeYRMEd5oQCfstWzGwWmTDMXEtpdn0M-96tYxcoLHETpvMSfVaVFm3dJiLD-8PsUrcA5LFfQxRsp9toF6ZNbZRHSyRzo25c7IVAqSOxgjXV2BLG8IkClKqF_wqluRt2LV2y1s04aFrY3QSJ4Q7oi_7GBoEH4JLqzsllIYamsCGI4BExP7fhuy5nOp69Mv-qJX9TsltF8fBBBVz0mNg.SXQV92bAHeZ7xvttpfYUd1CsrWS2ULnSSIw3sehUadg&dib_tag=se&keywords=lio%2Boil&qid=1755107688&sprefix=lio%2Boil%2Caps%2C149&sr=8-5&ufe=app_do%3Aamzn1.fos.de93fa6a-174c-4df7-be7c-5bc8e9c5a71b&th=1 | O59: MAKEUP | P59: 4.45 | Q59: RMB | R59: 10000 | S59: =+P59*$T$29 -> #VALUE! | T59: =+S59*0.36 -> #VALUE! | U59: =(S59+T59)*0.0248 -> #VALUE! | V59: =S59+T59+U59 -> #VALUE! | W59: 159 | X59: =W59/1.16 -> 137.06897 | Y59: =X59*0.6 -> 82.241379 | Z59: =V59/Y59 -> #VALUE! | AA59: =1-(V59/Y59) -> #VALUE! | AB59: =1-(Y59/(W59/1.16)) -> 0.4 | AC59: China | AE59: 6 | AF59: 144 | AG59: En revisión de dummy para autorización final | AH59: 46341 | AL59: 103.35 | AM59: =+AL59/1.16 -> 89.094828 | AN59: =+#REF!/AM59 -> #REF! | AO59: =1-#REF!/AM59 -> #REF! | AP59: =1-(AM59/(AL59/1.16)) -> 0 | BA59: 1 | BB59: 1 | BC59: 1 | BD59: 1 | BE59: 1 | BF59: 1 | BG59: 1 | BJ59: 9 | BK59: =SUM(BA59:BI59) -> 7 | BL59: =+BK59/BJ59 -> 0.77777778 | BR59: PPEDIDOS-260727498 Se espera que PT este listo 25 Sept | BS59: 46373 | BT59: Eduardo (Compras)
A60: 44 | B60: TBC | C60: Diciembre | D60: En tiempo | E60: 7502327991311 | F60: VLT-47 | G60: Delineador cremoso para labios Velvet "Define lip liner Juliet" | H60: #VALUE! | I60: 1.4 g | J60: Velvet | K60: Mix de canales | L60: 1 | M60: MUC | N60: https://www.amazon.com.mx/Maybelline-Delineador-Labios-Lifter-Liner/dp/B0CZBLMMQZ/ref=zg_bs_g_10178501011_d_sccl_1/139-5127535-4936938?th=1 | O60: MAKEUP | P60: 4.65 | Q60: USD | R60: 10000 | S60: =+P60*18.5 -> 86.025 | T60: =+S60*0.36 -> 30.969 | U60: =(S60+T60)*0.117 -> 13.688298 | V60: =S60+T60+U60 -> 130.6823 | W60: 139 | X60: =W60/1.16 -> 119.82759 | Y60: =X60*0.6 -> 71.896552 | Z60: =V60/Y60 -> 1.8176435 | AA60: =1-(V60/Y60) -> -0.81764347 | AB60: =1-(Y60/(W60/1.16)) -> 0.4 | AC60: China | AE60: 6 | AF60: 144 | AG60: Falta arte final de la caja por parte de Incitrus | AH60: 46341 | AL60: $77 | AM60: =+AL60/1.16 -> 66.37931 | AN60: =+V61/AM60 -> 1.9687203 | AO60: =1-V61/AM60 -> -0.96872033 | AP60: =1-(AM60/(AL60/1.16)) -> 0 | BA60: 1 | BB60: 1 | BC60: 1 | BD60: 1 | BE60: 1 | BF60: 1 | BG60: 1 | BJ60: 9 | BK60: =SUM(BA60:BI60) -> 7 | BL60: =+BK60/BJ60 -> 0.77777778 | BR60: PPEDIDOS-260727498 Se espera que PT este listo 30 Sept | BS60: 46380 | BT60: Eduardo (Compras)
A61: 45 | B61: TBC | C61: Diciembre | D61: En tiempo | E61: 7502327991328 | F61: VLT-48 | G61: Delineador cremoso para labios Velvet "Define lip liner Ophelia" | H61: #VALUE! | I61: 1.4 g | J61: Velvet | K61: Mix de canales | L61: 1 | M61: MUC | N61: https://www.amazon.com.mx/Maybelline-Delineador-Labios-Lifter-Liner/dp/B0CZBPLRHZ/ref=zg_bs_g_10178501011_d_sccl_1/139-5127535-4936938?th=1 | O61: MAKEUP | P61: 4.65 | Q61: USD | R61: 10000 | S61: =+P61*18.5 -> 86.025 | T61: =+S61*0.36 -> 30.969 | U61: =(S61+T61)*0.117 -> 13.688298 | V61: =S61+T61+U61 -> 130.6823 | W61: 139 | X61: =W61/1.16 -> 119.82759 | Y61: =X61*0.6 -> 71.896552 | Z61: =V61/Y61 -> 1.8176435 | AA61: =1-(V61/Y61) -> -0.81764347 | AB61: =1-(Y61/(W61/1.16)) -> 0.4 | AC61: China | AE61: 6 | AF61: 144 | AG61: Falta arte final de la caja por parte de Incitrus | AH61: 46341 | AL61: $77 | AM61: =+AL61/1.16 -> 66.37931 | AN61: =+V62/AM61 -> 1.9687203 | AO61: =1-V62/AM61 -> -0.96872033 | AP61: =1-(AM61/(AL61/1.16)) -> 0 | BA61: 1 | BB61: 1 | BC61: 1 | BD61: 1 | BE61: 1 | BF61: 1 | BG61: 1 | BJ61: 9 | BK61: =SUM(BA61:BI61) -> 7 | BL61: =+BK61/BJ61 -> 0.77777778 | BR61: PPEDIDOS-260727498 Se espera que PT este listo 30 Sept | BS61: 46380 | BT61: Eduardo (Compras)
A62: 46 | B62: TBC | C62: Diciembre | D62: En tiempo | E62: 7502327991335 | F62: VLT-49 | G62: Delineador cremoso para labios Velvet "Define lip liner Sophia" | H62: #VALUE! | I62: 1.4 g | J62: Velvet | K62: Mix de canales | L62: 1 | M62: MUC | N62: https://www.amazon.com.mx/Maybelline-Delineador-Labios-Lifter-Liner/dp/B0CZBJ1Y4Y/ref=zg_bs_g_10178501011_d_sccl_1/139-5127535-4936938?th=1 | O62: MAKEUP | P62: 4.65 | Q62: USD | R62: 10000 | S62: =+P62*18.5 -> 86.025 | T62: =+S62*0.36 -> 30.969 | U62: =(S62+T62)*0.117 -> 13.688298 | V62: =S62+T62+U62 -> 130.6823 | W62: 139 | X62: =W62/1.16 -> 119.82759 | Y62: =X62*0.6 -> 71.896552 | Z62: =V62/Y62 -> 1.8176435 | AA62: =1-(V62/Y62) -> -0.81764347 | AB62: =1-(Y62/(W62/1.16)) -> 0.4 | AC62: China | AE62: 6 | AF62: 144 | AG62: Falta arte final de la caja por parte de Incitrus | AH62: CANCELADO | AL62: $77 | AM62: =+AL62/1.16 -> 66.37931 | AN62: =+V63/AM62 -> 1.9687203 | AO62: =1-V63/AM62 -> -0.96872033 | AP62: =1-(AM62/(AL62/1.16)) -> 0 | BA62: 1 | BB62: 1 | BC62: 1 | BD62: 1 | BE62: 1 | BF62: 1 | BG62: 1 | BJ62: 9 | BK62: =SUM(BA62:BI62) -> 7 | BL62: =+BK62/BJ62 -> 0.77777778 | BR62: =+AG62 -> Falta arte final de la caja por parte de Incitrus | BS62: =AH62 -> CANCELADO | BT62: Eduardo (Compras)
A63: 47 | B63: TBC | C63: Diciembre | D63: En tiempo | E63: 7502327991342 | F63: VLT-50 | G63: Delineador cremoso para labios Velvet "Define lip liner Elizabeth" | H63: #VALUE! | I63: 1.4 g | J63: Velvet | K63: Mix de canales | L63: 1 | M63: MUC | N63: https://www.amazon.com.mx/Maybelline-Delineador-Labios-Lifter-Liner/dp/B0CZBGWBMS/ref=zg_bs_g_10178501011_d_sccl_1/139-5127535-4936938?th=1 | O63: MAKEUP | P63: 4.65 | Q63: USD | R63: 10000 | S63: =+P63*18.5 -> 86.025 | T63: =+S63*0.36 -> 30.969 | U63: =(S63+T63)*0.117 -> 13.688298 | V63: =S63+T63+U63 -> 130.6823 | W63: 139 | X63: =W63/1.16 -> 119.82759 | Y63: =X63*0.6 -> 71.896552 | Z63: =V63/Y63 -> 1.8176435 | AA63: =1-(V63/Y63) -> -0.81764347 | AB63: =1-(Y63/(W63/1.16)) -> 0.4 | AC63: China | AE63: 6 | AF63: 144 | AG63: Falta arte final de la caja por parte de Incitrus | AH63: 46341 | AL63: $77 | AM63: =+AL63/1.16 -> 66.37931 | AN63: =+V64/AM63 -> 1.9687203 | AO63: =1-V64/AM63 -> -0.96872033 | AP63: =1-(AM63/(AL63/1.16)) -> 0 | BA63: 1 | BB63: 1 | BC63: 1 | BD63: 1 | BE63: 1 | BF63: 1 | BG63: 1 | BJ63: 9 | BK63: =SUM(BA63:BI63) -> 7 | BL63: =+BK63/BJ63 -> 0.77777778 | BR63: PPEDIDOS-260727498 Se espera que PT este listo 30 Sept | BS63: 46380 | BT63: Eduardo (Compras)
A64: 48 | B64: TBC | C64: Diciembre | D64: En tiempo | E64: 7502327991359 | F64: VLT-51 | G64: Delineador cremoso para labios Velvet "Define lip liner Vivian" | I64: 1.4 g | J64: Velvet | K64: Mix de canales | L64: 1 | M64: MUC | N64: https://www.amazon.com.mx/Maybelline-Delineador-Labios-Lifter-Liner/dp/B0CZBBZ8DQ/ref=zg_bs_g_10178501011_d_sccl_1/139-5127535-4936938?th=1 | O64: MAKEUP | P64: 4.65 | Q64: USD | R64: 10000 | S64: =+P64*18.5 -> 86.025 | T64: =+S64*0.36 -> 30.969 | U64: =(S64+T64)*0.117 -> 13.688298 | V64: =S64+T64+U64 -> 130.6823 | W64: 139 | X64: =W64/1.16 -> 119.82759 | Y64: =X64*0.6 -> 71.896552 | Z64: =V64/Y64 -> 1.8176435 | AA64: =1-(V64/Y64) -> -0.81764347 | AB64: =1-(Y64/(W64/1.16)) -> 0.4 | AC64: China | AE64: 6 | AF64: 144 | AG64: Falta arte final de la caja por parte de Incitrus | AH64: 46341 | AL64: $77 | AM64: =+AL64/1.16 -> 66.37931 | AN64: =+V65/AM64 -> #VALUE! | AO64: =1-V65/AM64 -> #VALUE! | AP64: =1-(AM64/(AL64/1.16)) -> 0 | BA64: 1 | BB64: 1 | BC64: 1 | BD64: 1 | BE64: 1 | BF64: 1 | BG64: 1 | BJ64: 9 | BK64: =SUM(BA64:BI64) -> 7 | BL64: =+BK64/BJ64 -> 0.77777778 | BR64: PPEDIDOS-260727498 Se espera que PT este listo 30 Sept | BS64: 46380 | BT64: Eduardo (Compras)
A65: 49 | B65: TBC | C65: Diciembre | D65: En tiempo | E65: 7502327991366 | F65: VLT-52 | G65: Labial en Barra Velvet "Cream Luxe Lipstick Dahlia" | H65: #VALUE! | I65: 4 g | J65: Velvet | K65: Mix de canales | L65: 1 | M65: MUC | N65: https://www.amazon.com.mx/Revlon-7264274003-ColorStay-Suede-Lipstick/dp/B0BHJP6FS9/ref=zg_bs_g_10178504011_d_sccl_6/139-5127535-4936938?th=1 | O65: MAKEUP | P65: 4.65 | Q65: RMB | R65: 10000 | S65: =+P65*$T$29 -> #VALUE! | T65: =+S65*0.36 -> #VALUE! | U65: =(S65+T65)*0.0323 -> #VALUE! | V65: =S65+T65+U65 -> #VALUE! | W65: 149 | X65: =W65/1.16 -> 128.44828 | Y65: =X65*0.6 -> 77.068966 | Z65: =V65/Y65 -> #VALUE! | AA65: =1-(V65/Y65) -> #VALUE! | AB65: =1-(Y65/(W65/1.16)) -> 0.4 | AC65: China | AE65: 6 | AF65: 144 | AG65: Falta arte final de la caja. En espera suaje por parte de Daniel | AH65: 46341 | AL65: 96.85 | AM65: =+AL65/1.16 -> 83.491379 | AN65: =+V66/AM65 -> #VALUE! | AO65: =1-V66/AM65 -> #VALUE! | AP65: =1-(AM65/(AL65/1.16)) -> 0 | BA65: 1 | BB65: 1 | BC65: 1 | BD65: 1 | BE65: 1 | BF65: 1 | BG65: 1 | BJ65: 9 | BK65: =SUM(BA65:BI65) -> 7 | BL65: =+BK65/BJ65 -> 0.77777778 | BR65: PPEDIDOS-260727520 Se espera que PT este listo 14 Octubre | BS65: 46381 | BT65: Eduardo (Compras)
A66: 50 | B66: TBC | C66: Diciembre | D66: En tiempo | E66: 7502327991373 | F66: VLT-53 | G66: Labial en Barra Velvet "Cream Luxe Lipstick Tulip" | H66: #VALUE! | I66: 4 g | J66: Velvet | K66: Mix de canales | L66: 1 | M66: MUC | N66: https://www.amazon.com.mx/Revlon-7264274003-ColorStay-Suede-Lipstick/dp/B0BHJJ4KTT/ref=zg_bs_g_10178504011_d_sccl_6/139-5127535-4936938?th=1 | O66: MAKEUP | P66: 4.65 | Q66: RMB | R66: 10000 | S66: =+P66*$T$29 -> #VALUE! | T66: =+S66*0.36 -> #VALUE! | U66: =(S66+T66)*0.0323 -> #VALUE! | V66: =S66+T66+U66 -> #VALUE! | W66: 149 | X66: =W66/1.16 -> 128.44828 | Y66: =X66*0.6 -> 77.068966 | Z66: =V66/Y66 -> #VALUE! | AA66: =1-(V66/Y66) -> #VALUE! | AB66: =1-(Y66/(W66/1.16)) -> 0.4 | AC66: China | AE66: 6 | AF66: 144 | AG66: Falta arte final de la caja. En espera suaje por parte de Daniel | AH66: 46341 | AL66: 96.85 | AM66: =+AL66/1.16 -> 83.491379 | AN66: =+V67/AM66 -> #VALUE! | AO66: =1-V67/AM66 -> #VALUE! | AP66: =1-(AM66/(AL66/1.16)) -> 0 | BA66: 1 | BB66: 1 | BC66: 1 | BD66: 1 | BE66: 1 | BF66: 1 | BG66: 1 | BJ66: 9 | BK66: =SUM(BA66:BI66) -> 7 | BL66: =+BK66/BJ66 -> 0.77777778 | BR66: PPEDIDOS-260727520 Se espera que PT este listo 14 Octubre | BS66: 46381 | BT66: Eduardo (Compras)
A67: 51 | B67: TBC | C67: Diciembre | D67: En tiempo | E67: 7502327991380 | F67: VLT-54 | G67: Labial en Barra Velvet "Cream Luxe Lipstick Rose" | H67: #VALUE! | I67: 4 g | J67: Velvet | K67: Mix de canales | L67: 1 | M67: MUC | N67: https://www.amazon.com.mx/Revlon-7264274003-ColorStay-Suede-Lipstick/dp/B0BHJL1K6T/ref=zg_bs_g_10178504011_d_sccl_6/139-5127535-4936938?th=1 | O67: MAKEUP | P67: 4.65 | Q67: RMB | R67: 10000 | S67: =+P67*$T$29 -> #VALUE! | T67: =+S67*0.36 -> #VALUE! | U67: =(S67+T67)*0.0323 -> #VALUE! | V67: =S67+T67+U67 -> #VALUE! | W67: 149 | X67: =W67/1.16 -> 128.44828 | Y67: =X67*0.6 -> 77.068966 | Z67: =V67/Y67 -> #VALUE! | AA67: =1-(V67/Y67) -> #VALUE! | AB67: =1-(Y67/(W67/1.16)) -> 0.4 | AC67: China | AE67: 6 | AF67: 144 | AG67: Falta arte final de la caja. En espera suaje por parte de Daniel | AH67: 46341 | AL67: 96.85 | AM67: =+AL67/1.16 -> 83.491379 | AN67: =+V68/AM67 -> #VALUE! | AO67: =1-V68/AM67 -> #VALUE! | AP67: =1-(AM67/(AL67/1.16)) -> 0 | BA67: 1 | BB67: 1 | BC67: 1 | BD67: 1 | BE67: 1 | BF67: 1 | BG67: 1 | BJ67: 9 | BK67: =SUM(BA67:BI67) -> 7 | BL67: =+BK67/BJ67 -> 0.77777778 | BR67: PPEDIDOS-260727520 Se espera que PT este listo 14 Octubre | BS67: 46381 | BT67: Eduardo (Compras)
A68: 52 | B68: TBC | C68: Diciembre | D68: En tiempo | E68: 7502327991397 | F68: VLT-55 | G68: Labial en Barra Velvet "Cream Luxe Lipstick Orchid" | H68: #VALUE! | I68: 4 g | J68: Velvet | K68: Mix de canales | L68: 1 | M68: MUC | N68: https://www.amazon.com.mx/Revlon-7264274003-ColorStay-Suede-Lipstick/dp/B0BHJKC5FR/ref=zg_bs_g_10178504011_d_sccl_6/139-5127535-4936938?th=1 | O68: MAKEUP | P68: 4.65 | Q68: RMB | R68: 10000 | S68: =+P68*$T$29 -> #VALUE! | T68: =+S68*0.36 -> #VALUE! | U68: =(S68+T68)*0.0323 -> #VALUE! | V68: =S68+T68+U68 -> #VALUE! | W68: 149 | X68: =W68/1.16 -> 128.44828 | Y68: =X68*0.6 -> 77.068966 | Z68: =V68/Y68 -> #VALUE! | AA68: =1-(V68/Y68) -> #VALUE! | AB68: =1-(Y68/(W68/1.16)) -> 0.4 | AC68: China | AE68: 6 | AF68: 144 | AG68: Falta arte final de la caja. En espera suaje por parte de Daniel | AH68: 46341 | AL68: 96.85 | AM68: =+AL68/1.16 -> 83.491379 | AN68: =+V69/AM68 -> #VALUE! | AO68: =1-V69/AM68 -> #VALUE! | AP68: =1-(AM68/(AL68/1.16)) -> 0 | BA68: 1 | BB68: 1 | BC68: 1 | BD68: 1 | BE68: 1 | BF68: 1 | BG68: 1 | BJ68: 9 | BK68: =SUM(BA68:BI68) -> 7 | BL68: =+BK68/BJ68 -> 0.77777778 | BR68: PPEDIDOS-260727520 Se espera que PT este listo 14 Octubre | BS68: 46381 | BT68: Eduardo (Compras)
A69: 53 | B69: TBC | C69: Diciembre | D69: En tiempo | E69: 7502327991403 | F69: VLT-56 | G69: Tinta para labios y mejillas Velvet "Tint Old Romance" | H69: #VALUE! | I69: 5 g | J69: Velvet | K69: Mix de canales | L69: 1 | M69: USHAS | N69: https://www.amazon.com.mx/Sundae-Momiji-K-Tint-pigmentaci%C3%B3n-acabado/dp/B08XLM9T8F?th=1 | O69: MAKEUP | P69: 3 | Q69: RMB | R69: 10000 | S69: =+P69*$T$29 -> #VALUE! | T69: =+S69*0.36 -> #VALUE! | U69: =(S69+T69)*0.0382 -> #VALUE! | V69: =S69+T69+U69 -> #VALUE! | W69: 219 | X69: =W69/1.16 -> 188.7931 | Y69: =X69*0.6 -> 113.27586 | Z69: =V69/Y69 -> #VALUE! | AA69: =1-(V69/Y69) -> #VALUE! | AB69: =1-(Y69/(W69/1.16)) -> 0.4 | AC69: China | AE69: 6 | AF69: 144 | AG69: En revisión de dummy para autorización final | AH69: 46366 | AL69: 142.35 | AM69: =+AL69/1.16 -> 122.71552 | AN69: =+V70/AM69 -> #VALUE! | AO69: =1-V70/AM69 -> #VALUE! | AP69: =1-(AM69/(AL69/1.16)) -> 0 | BA69: 1 | BB69: 1 | BC69: 1 | BD69: 1 | BE69: 1 | BF69: 1 | BG69: 1 | BJ69: 9 | BK69: =SUM(BA69:BI69) -> 7 | BL69: =+BK69/BJ69 -> 0.77777778 | BR69: PPEDIDOS-260827594 Se espera que PT este listo 09 Nov | BS69: 46038 | BT69: Eduardo (Compras)
A70: 54 | B70: TBC | C70: Diciembre | D70: En tiempo | E70: 7502327991410 | F70: VLT-57 | G70: Tinta para labios y mejillas Velvet "Tint Love Letter" | H70: #VALUE! | I70: 5 g | J70: Velvet | K70: Mix de canales | L70: 1 | M70: USHAS | N70: https://www.amazon.com.mx/Sundae-Momiji-K-Tint-pigmentaci%C3%B3n-acabado/dp/B08XLM9T8F?th=1 | O70: MAKEUP | P70: 3 | Q70: RMB | R70: 10000 | S70: =+P70*$T$29 -> #VALUE! | T70: =+S70*0.36 -> #VALUE! | U70: =(S70+T70)*0.0382 -> #VALUE! | V70: =S70+T70+U70 -> #VALUE! | W70: 219 | X70: =W70/1.16 -> 188.7931 | Y70: =X70*0.6 -> 113.27586 | Z70: =V70/Y70 -> #VALUE! | AA70: =1-(V70/Y70) -> #VALUE! | AB70: =1-(Y70/(W70/1.16)) -> 0.4 | AC70: China | AE70: 6 | AF70: 144 | AG70: En revisión de dummy para autorización final | AH70: 46366 | AL70: 142.35 | AM70: =+AL70/1.16 -> 122.71552 | AN70: =+V71/AM70 -> #VALUE! | AO70: =1-V71/AM70 -> #VALUE! | AP70: =1-(AM70/(AL70/1.16)) -> 0 | BA70: 1 | BB70: 1 | BC70: 1 | BD70: 1 | BE70: 1 | BF70: 1 | BG70: 1 | BJ70: 9 | BK70: =SUM(BA70:BI70) -> 7 | BL70: =+BK70/BJ70 -> 0.77777778 | BR70: PPEDIDOS-260827594 Se espera que PT este listo 09 Nov | BS70: 46038 | BT70: Eduardo (Compras)
A71: 55 | B71: TBC | C71: Diciembre | D71: En tiempo | E71: 7502327991427 | F71: VLT-58 | G71: Tinta para labios y mejillas Velvet "Tint Devotion" | H71: #VALUE! | I71: 5 g | J71: Velvet | K71: Mix de canales | L71: 1 | M71: USHAS | N71: https://www.amazon.com.mx/Sundae-Momiji-K-Tint-pigmentaci%C3%B3n-acabado/dp/B08XLM9T8F?th=1 | O71: MAKEUP | P71: 3 | Q71: RMB | R71: 10000 | S71: =+P71*$T$29 -> #VALUE! | T71: =+S71*0.36 -> #VALUE! | U71: =(S71+T71)*0.0382 -> #VALUE! | V71: =S71+T71+U71 -> #VALUE! | W71: 219 | X71: =W71/1.16 -> 188.7931 | Y71: =X71*0.6 -> 113.27586 | Z71: =V71/Y71 -> #VALUE! | AA71: =1-(V71/Y71) -> #VALUE! | AB71: =1-(Y71/(W71/1.16)) -> 0.4 | AC71: China | AE71: 6 | AF71: 144 | AG71: En revisión de dummy para autorización final | AH71: CANCELADO | AL71: 142.35 | AM71: =+AL71/1.16 -> 122.71552 | AN71: =+V72/AM71 -> #VALUE! | AO71: =1-V72/AM71 -> #VALUE! | AP71: =1-(AM71/(AL71/1.16)) -> 0 | BA71: 1 | BB71: 1 | BC71: 1 | BD71: 1 | BE71: 1 | BF71: 1 | BG71: 1 | BJ71: 9 | BK71: =SUM(BA71:BI71) -> 7 | BL71: =+BK71/BJ71 -> 0.77777778 | BR71: =+AG71 -> En revisión de dummy para autorización final | BS71: =AH71 -> CANCELADO | BT71: Eduardo (Compras)
A72: 56 | B72: TBC | C72: Diciembre | D72: En tiempo | E72: 7502327991434 | F72: VLT-59 | G72: Tinta para labios y mejillas Velvet "Tint Poetry Rose" | H72: #VALUE! | I72: 5 g | J72: Velvet | K72: Mix de canales | L72: 1 | M72: USHAS | N72: https://www.amazon.com.mx/Sundae-Momiji-K-Tint-pigmentaci%C3%B3n-acabado/dp/B08XLM9T8F?th=1 | O72: MAKEUP | P72: 3 | Q72: RMB | R72: 10000 | S72: =+P72*$T$29 -> #VALUE! | T72: =+S72*0.36 -> #VALUE! | U72: =(S72+T72)*0.0382 -> #VALUE! | V72: =S72+T72+U72 -> #VALUE! | W72: 219 | X72: =W72/1.16 -> 188.7931 | Y72: =X72*0.6 -> 113.27586 | Z72: =V72/Y72 -> #VALUE! | AA72: =1-(V72/Y72) -> #VALUE! | AB72: =1-(Y72/(W72/1.16)) -> 0.4 | AC72: China | AE72: 6 | AF72: 144 | AG72: En revisión de dummy para autorización final | AH72: 46366 | AL72: 142.35 | AM72: =+AL72/1.16 -> 122.71552 | AN72: =+V73/AM72 -> #VALUE! | AO72: =1-V73/AM72 -> #VALUE! | AP72: =1-(AM72/(AL72/1.16)) -> 0 | BA72: 1 | BB72: 1 | BC72: 1 | BD72: 1 | BE72: 1 | BF72: 1 | BG72: 1 | BJ72: 9 | BK72: =SUM(BA72:BI72) -> 7 | BL72: =+BK72/BJ72 -> 0.77777778 | BR72: PPEDIDOS-260827594 Se espera que PT este listo 09 Nov | BS72: 46038 | BT72: Eduardo (Compras)
A73: 57 | B73: TBC | C73: Diciembre | D73: En tiempo | E73: 7502327991441 | F73: VLT-60 | G73: Labial líquido Velvet "Still on my lips Juliet" | H73: #VALUE! | I73: 4 mL | J73: Velvet | K73: Mix de canales | L73: 1 | M73: MUC | N73: https://www.maccosmetics.com.mx/product/31840/75919/productos/maquillaje/labios/liquid-lip-colours/powder-kiss-liquid-lipcolour?shade=Resort_Season_ | O73: MAKEUP | P73: 4.15 | Q73: RMB | R73: 10000 | S73: =+P73*$T$29 -> #VALUE! | T73: =+S73*0.36 -> #VALUE! | U73: =(S73+T73)*0.0462 -> #VALUE! | V73: =S73+T73+U73 -> #VALUE! | W73: 149 | X73: =W73/1.16 -> 128.44828 | Y73: =X73*0.6 -> 77.068966 | Z73: =V73/Y73 -> #VALUE! | AA73: =1-(V73/Y73) -> #VALUE! | AB73: =1-(Y73/(W73/1.16)) -> 0.4 | AC73: China | AE73: 6 | AF73: 144 | AG73: Falta arte final de la caja. En espera suaje por parte de Daniel | AH73: 46341 | AL73: 96.85 | AM73: =+AL73/1.16 -> 83.491379 | AN73: =+V74/AM73 -> #VALUE! | AO73: =1-V74/AM73 -> #VALUE! | AP73: =1-(AM73/(AL73/1.16)) -> 0 | BA73: 1 | BB73: 1 | BC73: 1 | BD73: 1 | BE73: 1 | BF73: 1 | BG73: 1 | BJ73: 9 | BK73: =SUM(BA73:BI73) -> 7 | BL73: =+BK73/BJ73 -> 0.77777778 | BR73: PPEDIDOS-260827551 Se espera que PT este listo 24 Oct | BS73: 46378 | BT73: Eduardo (Compras)
A74: 58 | B74: TBC | C74: Diciembre | D74: En tiempo | E74: 7502327991458 | F74: VLT-61 | G74: Labial líquido Velvet "Still on my lips Ophelia" | H74: #VALUE! | I74: 4 mL | J74: Velvet | K74: Mix de canales | L74: 1 | M74: MUC | N74: https://www.maccosmetics.com.mx/product/31840/75919/productos/maquillaje/labios/liquid-lip-colours/powder-kiss-liquid-lipcolour?shade=Resort_Season_ | O74: SKINCARE | P74: 4.15 | Q74: RMB | R74: 10000 | S74: =+P74*$T$29 -> #VALUE! | T74: =+S74*0.36 -> #VALUE! | U74: =(S74+T74)*0.0462 -> #VALUE! | V74: =S74+T74+U74 -> #VALUE! | W74: 149 | X74: =W74/1.16 -> 128.44828 | Y74: =X74*0.6 -> 77.068966 | Z74: =V74/Y74 -> #VALUE! | AA74: =1-(V74/Y74) -> #VALUE! | AB74: =1-(Y74/(W74/1.16)) -> 0.4 | AC74: China | AE74: 6 | AF74: 144 | AG74: Falta arte final de la caja. En espera suaje por parte de Daniel | AH74: 46341 | AL74: 96.85 | AM74: =+AL74/1.16 -> 83.491379 | AN74: =+V75/AM74 -> #VALUE! | AO74: =1-V75/AM74 -> #VALUE! | AP74: =1-(AM74/(AL74/1.16)) -> 0 | BA74: 1 | BB74: 1 | BC74: 1 | BD74: 1 | BE74: 1 | BF74: 1 | BG74: 1 | BJ74: 9 | BK74: =SUM(BA74:BI74) -> 7 | BL74: =+BK74/BJ74 -> 0.77777778 | BR74: PPEDIDOS-260827551 Se espera que PT este listo 24 Oct | BS74: 46378 | BT74: Eduardo (Compras)
A75: 59 | B75: TBC | C75: Diciembre | D75: En tiempo | E75: 7502327991465 | F75: VLT-62 | G75: Labial líquido Velvet "Still on my lips Sophia" | H75: #VALUE! | I75: 4 mL | J75: Velvet | K75: Mix de canales | L75: 1 | M75: MUC | N75: https://www.maccosmetics.com.mx/product/31840/75919/productos/maquillaje/labios/liquid-lip-colours/powder-kiss-liquid-lipcolour?shade=Resort_Season_ | O75: SKINCARE | P75: 4.15 | Q75: RMB | R75: 10000 | S75: =+P75*$T$29 -> #VALUE! | T75: =+S75*0.36 -> #VALUE! | U75: =(S75+T75)*0.0462 -> #VALUE! | V75: =S75+T75+U75 -> #VALUE! | W75: 149 | X75: =W75/1.16 -> 128.44828 | Y75: =X75*0.6 -> 77.068966 | Z75: =V75/Y75 -> #VALUE! | AA75: =1-(V75/Y75) -> #VALUE! | AB75: =1-(Y75/(W75/1.16)) -> 0.4 | AC75: China | AE75: 6 | AF75: 144 | AG75: Falta arte final de la caja. En espera suaje por parte de Daniel | AH75: 46341 | AL75: 96.85 | AM75: =+AL75/1.16 -> 83.491379 | AN75: =+V76/AM75 -> #VALUE! | AO75: =1-V76/AM75 -> #VALUE! | AP75: =1-(AM75/(AL75/1.16)) -> 0 | BA75: 1 | BB75: 1 | BC75: 1 | BD75: 1 | BE75: 1 | BF75: 1 | BG75: 1 | BJ75: 9 | BK75: =SUM(BA75:BI75) -> 7 | BL75: =+BK75/BJ75 -> 0.77777778 | BR75: PPEDIDOS-260827551 Se espera que PT este listo 24 Oct | BS75: 46378 | BT75: Eduardo (Compras)
A76: 60 | B76: TBC | C76: Diciembre | D76: En tiempo | E76: 7502327991472 | F76: VLT-63 | G76: Labial líquido Velvet "Still on my lips Elizabeth" | H76: #VALUE! | I76: 4 mL | J76: Velvet | K76: Mix de canales | L76: 1 | M76: MUC | N76: https://www.maccosmetics.com.mx/product/31840/75919/productos/maquillaje/labios/liquid-lip-colours/powder-kiss-liquid-lipcolour?shade=Resort_Season_ | O76: SKINCARE | P76: 4.15 | Q76: RMB | R76: 10000 | S76: =+P76*$T$29 -> #VALUE! | T76: =+S76*0.36 -> #VALUE! | U76: =(S76+T76)*0.0462 -> #VALUE! | V76: =S76+T76+U76 -> #VALUE! | W76: 149 | X76: =W76/1.16 -> 128.44828 | Y76: =X76*0.6 -> 77.068966 | Z76: =V76/Y76 -> #VALUE! | AA76: =1-(V76/Y76) -> #VALUE! | AB76: =1-(Y76/(W76/1.16)) -> 0.4 | AC76: China | AE76: 6 | AF76: 144 | AG76: Falta arte final de la caja. En espera suaje por parte de Daniel | AH76: 46341 | AL76: 96.85 | AM76: =+AL76/1.16 -> 83.491379 | AN76: =+V77/AM76 -> #VALUE! | AO76: =1-V77/AM76 -> #VALUE! | AP76: =1-(AM76/(AL76/1.16)) -> 0 | BA76: 1 | BB76: 1 | BC76: 1 | BD76: 1 | BE76: 1 | BF76: 1 | BG76: 1 | BJ76: 9 | BK76: =SUM(BA76:BI76) -> 7 | BL76: =+BK76/BJ76 -> 0.77777778 | BR76: PPEDIDOS-260827551 Se espera que PT este listo 24 Oct | BS76: 46378 | BT76: Eduardo (Compras)
A77: 61 | B77: TBC | C77: Diciembre | D77: En tiempo | E77: 7502327991489 | F77: VLT-64 | G77: Labial líquido Velvet "Still on my lips Vivian" | H77: #VALUE! | I77: 4 mL | J77: Velvet | K77: Mix de canales | L77: 1 | M77: MUC | N77: https://www.maccosmetics.com.mx/product/31840/75919/productos/maquillaje/labios/liquid-lip-colours/powder-kiss-liquid-lipcolour?shade=Resort_Season_ | O77: SKINCARE | P77: 4.15 | Q77: RMB | R77: 10000 | S77: =+P77*$T$29 -> #VALUE! | T77: =+S77*0.36 -> #VALUE! | U77: =(S77+T77)*0.0462 -> #VALUE! | V77: =S77+T77+U77 -> #VALUE! | W77: 149 | X77: =W77/1.16 -> 128.44828 | Y77: =X77*0.6 -> 77.068966 | Z77: =V77/Y77 -> #VALUE! | AA77: =1-(V77/Y77) -> #VALUE! | AB77: =1-(Y77/(W77/1.16)) -> 0.4 | AC77: China | AE77: 6 | AF77: 144 | AG77: Falta arte final de la caja. En espera suaje por parte de Daniel | AH77: 46341 | AL77: 96.85 | AM77: =+AL77/1.16 -> 83.491379 | AN77: =+V78/AM77 -> #VALUE! | AO77: =1-V78/AM77 -> #VALUE! | AP77: =1-(AM77/(AL77/1.16)) -> 0 | BA77: 1 | BB77: 1 | BC77: 1 | BD77: 1 | BE77: 1 | BF77: 1 | BG77: 1 | BJ77: 9 | BK77: =SUM(BA77:BI77) -> 7 | BL77: =+BK77/BJ77 -> 0.77777778 | BR77: PPEDIDOS-260827551 Se espera que PT este listo 24 Oct | BS77: 46378 | BT77: Eduardo (Compras)
A78: 62 | B78: TBC | C78: Diciembre | D78: En tiempo | E78: 7502327991496 | F78: VLT-65 | G78: Spray Fijador Velvet "Perfect Veil Fixing Spray" | H78: #VALUE! | I78: 50 mL | J78: Velvet | K78: Mix de canales | L78: 1 | M78: MUC | N78: https://pinkup.mx/product/fx-fixer?srsltid=AfmBOop0OvWJrHfhS6DGeB3Ps4UtHfUMPRJ2tlc448t7KTViU9lg-9BA | O78: SKINCARE | P78: 7 | Q78: RMB | R78: 10000 | S78: =+P78*$T$29 -> #VALUE! | T78: =+S78*0.25 -> #VALUE! | U78: =(S78+T78)*0.0696 -> #VALUE! | V78: =S78+T78+U78 -> #VALUE! | W78: 199 | X78: =W78/1.16 -> 171.55172 | Y78: =X78*0.6 -> 102.93103 | Z78: =V78/Y78 -> #VALUE! | AA78: =1-(V78/Y78) -> #VALUE! | AB78: =1-(Y78/(W78/1.16)) -> 0.4 | AC78: China | AE78: 4 | AF78: 48 | AG78: En revisión de dummy para autorización final | AH78: 46341 | AL78: 129.35 | AM78: =+AL78/1.16 -> 111.50862 | AN78: =+V79/AM78 -> #VALUE! | AO78: =1-V79/AM78 -> #VALUE! | AP78: =1-(AM78/(AL78/1.16)) -> 0 | BA78: 1 | BB78: 1 | BC78: 1 | BD78: 1 | BE78: 1 | BF78: 1 | BG78: 1 | BJ78: 9 | BK78: =SUM(BA78:BI78) -> 7 | BL78: =+BK78/BJ78 -> 0.77777778 | BR78: PPEDIDOS-260727498 Se espera que PT este listo 20 Sept | BS78: 46373 | BT78: Eduardo (Compras)
A79: 63 | B79: TBC | C79: Diciembre | D79: En tiempo | E79: 7502327991502 | F79: VLT-66 | G79: Protector Solar en Polvo Velvet "Sun Veil Powder" SPF30 | H79: #VALUE! | I79: 12.22g | J79: Velvet | K79: Mix de canales | L79: 1 | M79: MUC | N79: https://www.fahorro.com/fotoprotector-isdin-uv-mineral-brush-spf-50-2-g.html?srsltid=AfmBOoo2njWhr6gdFEay4W2c-2EDJlJBQ13dRmU0LGzC5BHgwKuaj5msZ9o | O79: SKINCARE | P79: 11.15 | Q79: RMB | R79: 10000 | S79: =+P79*$T$29 -> #VALUE! | T79: =+S79*0.25 -> #VALUE! | U79: =(S79+T79)*0.0179 -> #VALUE! | V79: =S79+T79+U79 -> #VALUE! | W79: 299 | X79: =W79/1.16 -> 257.75862 | Y79: =X79*0.6 -> 154.65517 | Z79: =V79/Y79 -> #VALUE! | AA79: =1-(V79/Y79) -> #VALUE! | AB79: =1-(Y79/(W79/1.16)) -> 0.4 | AC79: China | AE79: 6 | AF79: 72 | AG79: En revisión de dummy para autorización final | AH79: 46341 | AL79: 194.35 | AM79: =+AL79/1.16 -> 167.5431 | AN79: =+V80/AM79 -> 0.1215717 | AO79: =1-V80/AM79 -> 0.8784283 | AP79: =1-(AM79/(AL79/1.16)) -> 0 | BA79: 1 | BB79: 1 | BC79: 1 | BD79: 1 | BE79: 1 | BF79: 1 | BG79: 1 | BJ79: 9 | BK79: =SUM(BA79:BI79) -> 7 | BL79: =+BK79/BJ79 -> 0.77777778 | BR79: PPEDIDOS-260727498 Se espera que PT este listo 20 Sept | BS79: 46373 | BT79: Eduardo (Compras)
A80: 64 | B80: TBC | C80: Diciembre | D80: En tiempo | E80: 7502327991519 | F80: VLT-67 | G80: Suero Facial con Ácido Hialurónico Velvet "Serum Hydradaily" | H80: #VALUE! | I80: 30 mL | J80: Velvet | K80: Mix de canales | L80: 1 | M80: BIYING | N80: https://www.mercadolibre.com.mx/glazing-fluid-rhode-by-hailey-biebier-serum-hidratante-momento-de-aplicacion-dianoche-tipo-de-piel-todo-tipo-de-piel/p/MLM24114851#polycard_client=search-nordic&searchVariation=MLM24114851&wid=MLM3164142352&position=1&search_layout=grid&type=product&tracking_id=09469454-d69b-4913-9b38-211e4cc2183c&sid=search | O80: SKINCARE | P80: 0.8 | Q80: USD | R80: 10000 | S80: =+P80*18.5 -> 14.8 | T80: =+S80*0.25 -> 3.7 | U80: =(S80+T80)*0.101 -> 1.8685 | V80: =S80+T80+U80 -> 20.3685 | W80: 179 | X80: =W80/1.16 -> 154.31034 | Y80: =X80*0.6 -> 92.586207 | Z80: =V80/Y80 -> 0.21999497 | AA80: =1-(V80/Y80) -> 0.78000503 | AB80: =1-(Y80/(W80/1.16)) -> 0.4 | AC80: China | AE80: 4 | AF80: 48 | AG80: En proceso de realizacion de dummy para autorizacion final | AH80: 46341 | AL80: 116.35 | AM80: =+AL80/1.16 -> 100.30172 | AN80: =+#REF!/AM80 -> #REF! | AO80: =1-#REF!/AM80 -> #REF! | AP80: =1-(AM80/(AL80/1.16)) -> 0 | BA80: 1 | BB80: 1 | BC80: 1 | BD80: 1 | BE80: 1 | BF80: 1 | BG80: 1 | BJ80: 9 | BK80: =SUM(BA80:BI80) -> 7 | BL80: =+BK80/BJ80 -> 0.77777778 | BR80: PPEDIDOS-260727505 Se espera PT listo 24 Sept | BS80: 46373 | BT80: Eduardo (Compras)
A81: 66 | B81: TBC | C81: Diciembre | D81: En tiempo | E81: 7502327991533 | F81: VLT-69 | G81: Bruma humectante Velvet "Hydra Mist" | H81: #VALUE! | I81: 80 mL | J81: Velvet | K81: Mix de canales | L81: 1 | M81: MUC | O81: SKINCARE | P81: 9.15 | Q81: RMB | R81: 10000 | S81: =+P81*$T$29 -> #VALUE! | T81: =+S81*0.12 -> #VALUE! | U81: =(S81+T81)*0.0696 -> #VALUE! | V81: =S81+T81+U81 -> #VALUE! | W81: 219 | X81: =W81/1.16 -> 188.7931 | Y81: =X81*0.6 -> 113.27586 | Z81: =V81/Y81 -> #VALUE! | AA81: =1-(V81/Y81) -> #VALUE! | AB81: =1-(Y81/(W81/1.16)) -> 0.4 | AC81: China | AE81: 6 | AF81: 36 | AG81: En revisión de dummy para autorización final | AH81: 46341 | AL81: 142.35 | AM81: =+AL81/1.16 -> 122.71552 | AN81: =+V82/AM81 -> #VALUE! | AO81: =1-V82/AM81 -> #VALUE! | AP81: =1-(AM81/(AL81/1.16)) -> 0 | BA81: 1 | BB81: 1 | BC81: 1 | BD81: 1 | BE81: 1 | BF81: 1 | BG81: 1 | BJ81: 9 | BK81: =SUM(BA81:BI81) -> 7 | BL81: =+BK81/BJ81 -> 0.77777778 | BR81: PPEDIDOS-260727498 Se espera que PT este listo 20 Sept | BS81: 46375 | BT81: Eduardo (Compras)
A82: 67 | B82: TBC | C82: Diciembre | D82: En tiempo | E82: 7502327991540 | F82: VLT-70 | G82: Bruma refrescante Velvet "Fresh Mist" | H82: #VALUE! | I82: 300 gr | J82: Velvet | K82: Mix de canales | L82: 1 | M82: USHAS | O82: SKINCARE | P82: 9.15 | Q82: RMB | R82: 10000 | S82: =+P82*$T$29 -> #VALUE! | T82: =+S82*0.25 -> #VALUE! | U82: =(S82+T82)*0.1546 -> #VALUE! | V82: =S82+T82+U82 -> #VALUE! | W82: 299 | X82: =W82/1.16 -> 257.75862 | Y82: =X82*0.6 -> 154.65517 | Z82: =V82/Y82 -> #VALUE! | AA82: =1-(V82/Y82) -> #VALUE! | AB82: =1-(Y82/(W82/1.16)) -> 0.4 | AC82: China | AE82: 4 | AF82: 24 | AG82: En proceso de render para solicitar autorizacion final | AH82: 46366 | AL82: 194.35 | AM82: =+AL82/1.16 -> 167.5431 | AN82: =+V83/AM82 -> 2.1686636 | AO82: =1-V83/AM82 -> -1.1686636 | AP82: =1-(AM82/(AL82/1.16)) -> 0 | BA82: 1 | BB82: 1 | BC82: 1 | BD82: 1 | BE82: 1 | BF82: 1 | BG82: 1 | BJ82: 9 | BK82: =SUM(BA82:BI82) -> 7 | BL82: =+BK82/BJ82 -> 0.77777778 | BR82: PPEDIDOS-260727498 Se espera que PT este listo 20 Sept | BS82: 46375 | BT82: Eduardo (Compras)
A83: 68 | B83: TBC | C83: Diciembre | D83: En tiempo | E83: 7502327991557 | F83: VLT-71 | G83: Limpiador Facial Velvet "Cappuccino Cloud Cleanser" | H83: #VALUE! | I83: 1 pz | J83: Velvet | K83: Mix de canales | L83: 1 | M83: BIYING | O83: SKINCARE | P83: 14 | Q83: USD | R83: 30000 | S83: =+P83*18.5 -> 259 | T83: =+S83*0.25 -> 64.75 | U83: =(S83+T83)*0.1223 -> 39.594625 | V83: =S83+T83+U83 -> 363.34463 | W83: 29 | X83: =W83/1.16 -> 25 | Y83: =X83*0.6 -> 15 | Z83: =V83/Y83 -> 24.222975 | AA83: =1-(V83/Y83) -> -23.222975 | AB83: =1-(Y83/(W83/1.16)) -> 0.4 | AC83: China | AE83: 12 | AF83: 480 | AG83: En proceso de render para solicitar autorizacion final | AH83: 46341 | AL83: 18.85 | AM83: =+AL83/1.16 -> 16.25 | AN83: =+V84/AM83 -> 1.5971192 | AO83: =1-V84/AM83 -> -0.59711923 | AP83: =1-(AM83/(AL83/1.16)) -> 0 | BA83: 1 | BB83: 1 | BC83: 1 | BD83: 1 | BE83: 1 | BF83: 1 | BG83: 1 | BJ83: 9 | BK83: =SUM(BA83:BI83) -> 7 | BL83: =+BK83/BJ83 -> 0.77777778 | BR83: PPEDIDOS-260727505 Se espera PT listo 28 Ago | BS83: 46332 | BT83: Eduardo (Compras)
A84: 69 | B84: TBC | C84: Diciembre | D84: En tiempo | E84: 7502327991564 | F84: VLT-72 | G84: Mascarilla facial con extracto de Granada Velvet "Pomegranate Sheet Mask" | H84: #VALUE! | I84: 1 pz | J84: Velvet | K84: Mix de canales | L84: 1 | M84: BIYING | O84: PERSONAL CARE | P84: 1 | Q84: USD | R84: 30000 | S84: =+P84*18.5 -> 18.5 | T84: =+S84*0.25 -> 4.625 | U84: =(S84+T84)*0.1223 -> 2.8281875 | V84: =S84+T84+U84 -> 25.953187 | W84: 29 | X84: =W84/1.16 -> 25 | Y84: =X84*0.6 -> 15 | Z84: =V84/Y84 -> 1.7302125 | AA84: =1-(V84/Y84) -> -0.7302125 | AB84: =1-(Y84/(W84/1.16)) -> 0.4 | AC84: China | AE84: 12 | AF84: 480 | AG84: En proceso de render para solicitar autorizacion final | AH84: 46341 | AL84: 18.85 | AM84: =+AL84/1.16 -> 16.25 | AN84: =+V85/AM84 -> 1.5971192 | AO84: =1-V85/AM84 -> -0.59711923 | AP84: =1-(AM84/(AL84/1.16)) -> 0 | BA84: 1 | BB84: 1 | BC84: 1 | BD84: 1 | BE84: 1 | BF84: 1 | BG84: 1 | BJ84: 9 | BK84: =SUM(BA84:BI84) -> 7 | BL84: =+BK84/BJ84 -> 0.77777778 | BR84: PPEDIDOS-260727505 Se espera PT listo 28 Ago | BS84: 46332 | BT84: Eduardo (Compras)
A85: 70 | B85: TBC | C85: Diciembre | D85: En tiempo | E85: 7502327991571 | F85: VLT-73 | G85: Mascarilla facial con cafeina Velvet "Coffee Mask" | H85: #VALUE! | I85: 1 pz | J85: Velvet | K85: Mix de canales | L85: 1 | M85: BIYING | O85: PERSONAL CARE | P85: 1 | Q85: USD | R85: 30000 | S85: =+P85*18.5 -> 18.5 | T85: =+S85*0.25 -> 4.625 | U85: =(S85+T85)*0.1223 -> 2.8281875 | V85: =S85+T85+U85 -> 25.953187 | W85: 29 | X85: =W85/1.16 -> 25 | Y85: =X85*0.6 -> 15 | Z85: =V85/Y85 -> 1.7302125 | AA85: =1-(V85/Y85) -> -0.7302125 | AB85: =1-(Y85/(W85/1.16)) -> 0.4 | AC85: China | AE85: 12 | AF85: 480 | AG85: En proceso de render para solicitar autorizacion final | AH85: 46341 | AL85: 18.85 | AM85: =+AL85/1.16 -> 16.25 | AN85: =+V86/AM85 -> 1.5971192 | AO85: =1-V86/AM85 -> -0.59711923 | AP85: =1-(AM85/(AL85/1.16)) -> 0 | BA85: 1 | BB85: 1 | BC85: 1 | BD85: 1 | BE85: 1 | BF85: 1 | BG85: 1 | BJ85: 9 | BK85: =SUM(BA85:BI85) -> 7 | BL85: =+BK85/BJ85 -> 0.77777778 | BR85: PPEDIDOS-260727505 Se espera PT listo 28 Ago | BS85: 46332 | BT85: Eduardo (Compras)
A86: 71 | B86: TBC | C86: Diciembre | D86: En tiempo | E86: 7502327991588 | F86: VLT-74 | G86: Mascarilla Facial con Retinol Velvet "Retinol Sheet Mask" | H86: #VALUE! | I86: 1 pz | J86: Velvet | K86: Mix de canales | L86: 1 | M86: BIYING | O86: BEAUTY & ACCESORIES | P86: 1 | Q86: USD | R86: 30000 | S86: =+P86*18.5 -> 18.5 | T86: =+S86*0.25 -> 4.625 | U86: =(S86+T86)*0.1223 -> 2.8281875 | V86: =S86+T86+U86 -> 25.953187 | W86: 29 | X86: =W86/1.16 -> 25 | Y86: =X86*0.6 -> 15 | Z86: =V86/Y86 -> 1.7302125 | AA86: =1-(V86/Y86) -> -0.7302125 | AB86: =1-(Y86/(W86/1.16)) -> 0.4 | AC86: China | AE86: 12 | AF86: 480 | AG86: En proceso de render para solicitar autorizacion final | AH86: 46341 | AL86: 18.85 | AM86: =+AL86/1.16 -> 16.25 | AN86: =+V87/AM86 -> 1.5971192 | AO86: =1-V87/AM86 -> -0.59711923 | AP86: =1-(AM86/(AL86/1.16)) -> 0 | BA86: 1 | BB86: 1 | BC86: 1 | BD86: 1 | BE86: 1 | BF86: 1 | BG86: 1 | BJ86: 9 | BK86: =SUM(BA86:BI86) -> 7 | BL86: =+BK86/BJ86 -> 0.77777778 | BR86: PPEDIDOS-260727505 Se espera PT listo 28 Ago | BS86: 46332 | BT86: Eduardo (Compras)
A87: 72 | B87: TBC | C87: Diciembre | D87: En tiempo | E87: 7502327991595 | F87: VLT-75 | G87: Mascarilla Facial con péptidos Velvet "Peptides Sheet Mask" | H87: #VALUE! | I87: 1 pz | J87: Velvet | K87: Mix de canales | L87: 1 | M87: BIYING | O87: BEAUTY & ACCESORIES | P87: 1 | Q87: USD | R87: 30000 | S87: =+P87*18.5 -> 18.5 | T87: =+S87*0.25 -> 4.625 | U87: =(S87+T87)*0.1223 -> 2.8281875 | V87: =S87+T87+U87 -> 25.953187 | W87: 29 | X87: =W87/1.16 -> 25 | Y87: =X87*0.6 -> 15 | Z87: =V87/Y87 -> 1.7302125 | AA87: =1-(V87/Y87) -> -0.7302125 | AB87: =1-(Y87/(W87/1.16)) -> 0.4 | AC87: China | AE87: 12 | AF87: 480 | AG87: En proceso de render para solicitar autorizacion final | AH87: 46341 | AL87: 18.85 | AM87: =+AL87/1.16 -> 16.25 | AN87: =+V88/AM87 -> 0.63788 | AO87: =1-V88/AM87 -> 0.36212 | AP87: =1-(AM87/(AL87/1.16)) -> 0 | BA87: 1 | BB87: 1 | BC87: 1 | BD87: 1 | BE87: 1 | BF87: 1 | BG87: 1 | BJ87: 9 | BK87: =SUM(BA87:BI87) -> 7 | BL87: =+BK87/BJ87 -> 0.77777778 | BR87: PPEDIDOS-260727505 Se espera PT listo 28 Ago | BS87: 46332 | BT87: Eduardo (Compras)
A88: 73 | B88: TBC | C88: Diciembre | D88: En tiempo | E88: 7502327991601 | F88: VLT-76 | G88: Mascarilla Facial con Niacinamida Velvet "Niacinamide Sheet Mask" | H88: #VALUE! | I88: 1 pz | J88: Velvet | K88: Mix de canales | L88: 1 | M88: BIYING | O88: MAKEUP | P88: 0.4 | Q88: USD | R88: 30000 | S88: =+P88*18.5 -> 7.4 | T88: =+S88*0.25 -> 1.85 | U88: =(S88+T88)*0.1206 -> 1.11555 | V88: =S88+T88+U88 -> 10.36555 | W88: 129 | X88: =W88/1.16 -> 111.2069 | Y88: =X88*0.6 -> 66.724138 | Z88: =V88/Y88 -> 0.15534933 | AA88: =1-(V88/Y88) -> 0.84465067 | AB88: =1-(Y88/(W88/1.16)) -> 0.4 | AC88: China | AE88: 6 | AF88: 72 | AG88: En proceso de render para solicitar autorizacion final | AH88: 46341 | AL88: 83.85 | AM88: =+AL88/1.16 -> 72.284483 | AN88: =+V89/AM88 -> #VALUE! | AO88: =1-V89/AM88 -> #VALUE! | AP88: =1-(AM88/(AL88/1.16)) -> 0 | BA88: 1 | BB88: 1 | BC88: 1 | BD88: 1 | BE88: 1 | BF88: 1 | BG88: 1 | BJ88: 9 | BK88: =SUM(BA88:BI88) -> 7 | BL88: =+BK88/BJ88 -> 0.77777778 | BR88: PPEDIDOS-260727505 Se espera PT listo 28 Ago | BS88: 46332 | BT88: Eduardo (Compras)
A89: 74 | B89: TBC | C89: Diciembre | D89: En tiempo | E89: 7502327991618 | F89: VLT-77 | G89: Pack de 5 mascarillas faciales variadas Velvet "Essential Collection" | H89: #VALUE! | I89: 250 mL | J89: Velvet | K89: Mix de canales | L89: 1 | M89: MUC | N89: https://www.fragrantica.es/perfume/Victoria-s-Secret/Berry-Elixir-No-16-83974.html | O89: MAKEUP | P89: 8.65 | Q89: RMB | R89: 10000 | S89: =+P89*$T$29 -> #VALUE! | T89: =+S89*0.25 -> #VALUE! | U89: =(S89+T89)*0.1726 -> #VALUE! | V89: =S89+T89+U89 -> #VALUE! | W89: 195 | X89: =W89/1.16 -> 168.10345 | Y89: =X89*0.6 -> 100.86207 | Z89: =V89/Y89 -> #VALUE! | AA89: =1-(V89/Y89) -> #VALUE! | AB89: =1-(Y89/(W89/1.16)) -> 0.4 | AC89: China | AE89: 4 | AF89: 48 | AG89: En proceso de render para solicitar autorizacion final | AH89: 46341 | AL89: 126.75 | AM89: =+AL89/1.16 -> 109.26724 | AN89: =+V90/AM89 -> #VALUE! | AO89: =1-V90/AM89 -> #VALUE! | AP89: =1-(AM89/(AL89/1.16)) -> 0 | BA89: 1 | BB89: 1 | BC89: 1 | BD89: 1 | BE89: 1 | BF89: 1 | BG89: 1 | BJ89: 9 | BK89: =SUM(BA89:BI89) -> 7 | BL89: =+BK89/BJ89 -> 0.77777778 | BR89: PPEDIDOS-260727505 Se espera PT listo 28 Ago | BS89: 46332 | BT89: Eduardo (Compras)
A90: 75 | B90: TBC | C90: Diciembre | D90: En tiempo | E90: 7502327991625 | F90: VLT-78 | G90: Mist Velvet "Wild Berries" | H90: #VALUE! | I90: 250 mL | J90: Velvet | K90: Mix de canales | L90: 1 | M90: MUC | N90: Winter Cranberry Victoria&#039;s Secret fragancia - una fragancia para Mujeres 2015 | O90: MAKEUP | P90: 8.65 | Q90: RMB | R90: 10000 | S90: =+P90*$T$29 -> #VALUE! | T90: =+S90*0.25 -> #VALUE! | U90: =(S90+T90)*0.1726 -> #VALUE! | V90: =S90+T90+U90 -> #VALUE! | W90: 195 | X90: =W90/1.16 -> 168.10345 | Y90: =X90*0.6 -> 100.86207 | Z90: =V90/Y90 -> #VALUE! | AA90: =1-(V90/Y90) -> #VALUE! | AB90: =1-(Y90/(W90/1.16)) -> 0.4 | AC90: China | AE90: 4 | AF90: 48 | AG90: En proceso de render para solicitar autorizacion final | AH90: 46341 | AL90: 126.75 | AM90: =+AL90/1.16 -> 109.26724 | AN90: =+V91/AM90 -> 1.0208987 | AO90: =1-V91/AM90 -> -0.020898676 | AP90: =1-(AM90/(AL90/1.16)) -> 0 | BA90: 1 | BB90: 1 | BC90: 1 | BD90: 1 | BE90: 1 | BF90: 1 | BG90: 1 | BJ90: 9 | BK90: =SUM(BA90:BI90) -> 7 | BL90: =+BK90/BJ90 -> 0.77777778 | BR90: PPEDIDOS-260827551 Se espera que PT este listo 24 Oct | BS90: 46381 | BT90: Eduardo (Compras)
A91: 76 | B91: TBC | C91: Diciembre | D91: En tiempo | E91: 7502327991632 | F91: VLT-79 | G91: Mist Velvet "Midnight Muse" | H91: #VALUE! | I91: 1 | J91: Velvet | K91: Mix de canales | L91: 1 | M91: MUC | O91: MAKEUP | P91: 4.2 | Q91: USD | R91: 10000 | S91: =+P91*18.5 -> 77.7 | T91: =+S91*0.15 -> 11.655 | U91: =(S91+T91)*0.2484 -> 22.195782 | V91: =S91+T91+U91 -> 111.55078 | W91: 149 | X91: =W91/1.16 -> 128.44828 | Y91: =X91*0.6 -> 77.068966 | Z91: =V91/Y91 -> 1.4474151 | AA91: =1-(V91/Y91) -> -0.44741507 | AB91: =1-(Y91/(W91/1.16)) -> 0.4 | AC91: China | AE91: 6 | AF91: 144 | AG91: En proceso de realizacion de dummy para autorizacion final | AH91: 46341 | AL91: 96.85 | AM91: =+AL91/1.16 -> 83.491379 | AN91: =+#REF!/AM91 -> #REF! | AO91: =1-#REF!/AM91 -> #REF! | AP91: =1-(AM91/(AL91/1.16)) -> 0 | BA91: 1 | BB91: 1 | BC91: 1 | BD91: 1 | BE91: 1 | BF91: 1 | BG91: 1 | BJ91: 9 | BK91: =SUM(BA91:BI91) -> 7 | BL91: =+BK91/BJ91 -> 0.77777778 | BR91: PPEDIDOS-260827551 Se espera que PT este listo 24 Oct | BS91: 46381 | BT91: Eduardo (Compras)
B92: TBC | C92: Diciembre | E92: 7502327991670 | F92: VLT-83 | G92: Enchinador para Pestañas Velvet "The quiet lift" | AG92: En proceso de realizacion de dummy para autorizacion final | AH92: 46341 | BA92: 1 | BB92: 1 | BC92: 1 | BD92: 1 | BE92: 1 | BF92: 1 | BG92: 1 | BJ92: 9 | BK92: =SUM(BA92:BI92) -> 7 | BL92: =+BK92/BJ92 -> 0.77777778 | BR92: PPEDIDOS-260727498 Se espera que PT este listo 30 Sept | BS92: 46380 | BT92: Eduardo (Compras)
A93: 77 | B93: TBC | C93: Diciembre | D93: En tiempo | E93: 7502327991700 | F93: VLT-86 | G93: Set de esponjas de maquillaje con 3 piezas Velvet "Blend sponge set" | H93: #VALUE! | I93: 3 PIEZAS | J93: Velvet | K93: Mix de canales | L93: 1 | M93: MUC / USHAS | N93: Beauty Creations - Trio De Esponjas Y Borla – Beauty Creations MX | O93: MAKEUP | P93: 4.15 | Q93: RMB | R93: 10000 | S93: =+P93*$T$29 -> #VALUE! | T93: =+S93*0.15 -> #VALUE! | U93: =(S93+T93)*0.5213 -> #VALUE! | V93: =S93+T93+U93 -> #VALUE! | W93: 99 | X93: =W93/1.16 -> 85.344828 | Y93: =X93*0.6 -> 51.206897 | Z93: =V93/Y93 -> #VALUE! | AA93: =1-(V93/Y93) -> #VALUE! | AB93: =1-(Y93/(W93/1.16)) -> 0.4 | AC93: China | AE93: 6 | AF93: 144 | AG93: En revisión de dummy para autorización final | AH93: 46341 | AL93: 64.35 | AM93: =+AL93/1.16 -> 55.474138 | AN93: =+V94/AM93 -> 1.0635914 | AO93: =1-V94/AM93 -> -0.063591449 | AP93: =1-(AM93/(AL93/1.16)) -> 0 | BA93: 1 | BB93: 1 | BC93: 1 | BD93: 1 | BE93: 1 | BF93: 1 | BJ93: 9 | BK93: =SUM(BA93:BI93) -> 6 | BL93: =+BK93/BJ93 -> 0.66666667 | BR93: En revisión por costos | BS93: =AH93 -> 46341 | BT93: Eduardo (Compras)
A94: 78 | B94: TBC | C94: Diciembre | D94: En tiempo | E94: 7502327991717 | F94: VLT-87 | G94: Paleta de sombras 12 tonos (Cafés) Velvet "Arabia" | H94: #VALUE! | I94: 18 g | J94: Velvet | K94: Mix de canales | L94: 1 | M94: BEAUTYDOM | N94: https://www.blush-bar.com.mx/paleta-de-sombras-bloom-eyeshadow-palette/p?idsku=3500&srsltid=AfmBOopxpXR3lZLe-yJZnOYad-nqSfjs7F4DLSXeQ1pPjvJb20OifH8azYI | O94: MAKEUP | P94: 2.45 | Q94: USD | R94: 15000 | S94: =+P94*18.5 -> 45.325 | T94: =+S94*0.25 -> 11.33125 | U94: =(S94+T94)*0.0414 -> 2.3455687 | V94: =S94+T94+U94 -> 59.001819 | W94: 389 | X94: =W94/1.16 -> 335.34483 | Y94: =X94*0.6 -> 201.2069 | Z94: =V94/Y94 -> 0.29323954 | AA94: =1-(V94/Y94) -> 0.70676046 | AB94: =1-(Y94/(W94/1.16)) -> 0.4 | AC94: China | AE94: 6 | AF94: 72 | AG94: En revisión de dummy para autorización final | AH94: 46341 | AL94: 252.85 | AM94: =+AL94/1.16 -> 217.97414 | AN94: =+V95/AM94 -> 0.27068266 | AO94: =1-V95/AM94 -> 0.72931734 | AP94: =1-(AM94/(AL94/1.16)) -> 0 | BA94: 1 | BB94: 1 | BC94: 1 | BD94: 1 | BE94: 1 | BF94: 1 | BG94: 1 | BJ94: 9 | BK94: =SUM(BA94:BI94) -> 7 | BL94: =+BK94/BJ94 -> 0.77777778 | BR94: PPEDIDOS-260727510 Se espera que PT este listo 25 Sept | BS94: 46358 | BT94: Eduardo (Compras)
A95: 79 | B95: TBC | C95: Diciembre | D95: En tiempo | E95: 7502327991724 | F95: VLT-88 | G95: Paleta de sombras 12 tonos (Terracota) Velvet "Italy" | H95: #VALUE! | I95: 18 g | J95: Velvet | K95: Mix de canales | L95: 1 | M95: BEAUTYDOM | N95: https://www.sephora.com.mx/products-9090668966.html | O95: MAKEUP | P95: 2.45 | Q95: USD | R95: 15000 | S95: =+P95*18.5 -> 45.325 | T95: =+S95*0.25 -> 11.33125 | U95: =(S95+T95)*0.0414 -> 2.3455687 | V95: =S95+T95+U95 -> 59.001819 | W95: 389 | X95: =W95/1.16 -> 335.34483 | Y95: =X95*0.6 -> 201.2069 | Z95: =V95/Y95 -> 0.29323954 | AA95: =1-(V95/Y95) -> 0.70676046 | AB95: =1-(Y95/(W95/1.16)) -> 0.4 | AC95: China | AE95: 6 | AF95: 72 | AG95: En revisión de dummy para autorización final | AH95: 46341 | AL95: 252.85 | AM95: =+AL95/1.16 -> 217.97414 | AN95: =+#REF!/AM95 -> #REF! | AO95: =1-#REF!/AM95 -> #REF! | AP95: =1-(AM95/(AL95/1.16)) -> 0 | BA95: 1 | BB95: 1 | BC95: 1 | BD95: 1 | BE95: 1 | BF95: 1 | BG95: 1 | BJ95: 9 | BK95: =SUM(BA95:BI95) -> 7 | BL95: =+BK95/BJ95 -> 0.77777778 | BR95: PPEDIDOS-260727510 Se espera que PT este listo 25 Sept | BS95: 46358 | BT95: Eduardo (Compras)
A96: 80 | B96: TBC | C96: Diciembre | D96: En tiempo | E96: 7502327991755 | F96: VLT-91 | G96: Labial gloss Velvet "Lip gloss In love" | H96: #VALUE! | I96: 3.3 g | J96: Velvet | K96: Mix de canales | L96: 1 | M96: USHAS | N96: https://www.mercadolibre.com.mx/blood-money-palette-x-jeffree-star-cosmetics-paleta-sombras/p/MLM22663715?matt_tool=28238160&utm_source=google_shopping&utm_medium=organic&pdp_filters=item_id%3AMLM3574100304&from=gshop | O96: MAKEUP | P96: 3.2 | Q96: RMB | R96: 10000 | S96: =+P96*$T$29 -> #VALUE! | T96: =+S96*0.36 -> #VALUE! | U96: =(S96+T96)*0.0586 -> #VALUE! | V96: =S96+T96+U96 -> #VALUE! | W96: 229 | X96: =W96/1.16 -> 197.41379 | Y96: =X96*0.6 -> 118.44828 | Z96: =V96/Y96 -> #VALUE! | AA96: =1-(V96/Y96) -> #VALUE! | AB96: =1-(Y96/(W96/1.16)) -> 0.4 | AC96: China | AE96: 6 | AF96: 144 | AG96: En revisión de dummy para autorización final | AH96: 46366 | AL96: 148.85 | AM96: =+AL96/1.16 -> 128.31897 | AN96: =+V97/AM96 -> #VALUE! | AO96: =1-V97/AM96 -> #VALUE! | AP96: =1-(AM96/(AL96/1.16)) -> 0 | BA96: 1 | BB96: 1 | BC96: 1 | BD96: 1 | BE96: 1 | BF96: 1 | BJ96: 9 | BK96: =SUM(BA96:BI96) -> 6 | BL96: =+BK96/BJ96 -> 0.66666667 | BR96: PPEDIDOS-260827594 Se espera que PT este listo 09 Nov | BS96: 46038 | BT96: Eduardo (Compras)
A97: 81 | B97: TBC | C97: Diciembre | D97: En tiempo | E97: 7502327991762 | F97: VLT-92 | G97: Labial gloss Velvet "Lip gloss My Crush" | H97: #VALUE! | I97: 3.3 gr | J97: Velvet | K97: Mix de canales | L97: 1 | M97: USHAS | N97: https://www.mercadolibre.com.mx/blood-money-palette-x-jeffree-star-cosmetics-paleta-sombras/p/MLM22663715?matt_tool=28238160&utm_source=google_shopping&utm_medium=organic&pdp_filters=item_id%3AMLM3574100304&from=gshop | O97: MAKEUP | P97: 3.2 | Q97: RMB | R97: 10000 | S97: =+P97*$T$29 -> #VALUE! | T97: =+S97*0.36 -> #VALUE! | U97: =(S97+T97)*0.0586 -> #VALUE! | V97: =S97+T97+U97 -> #VALUE! | W97: 229 | X97: =W97/1.16 -> 197.41379 | Y97: =X97*0.6 -> 118.44828 | Z97: =V97/Y97 -> #VALUE! | AA97: =1-(V97/Y97) -> #VALUE! | AB97: =1-(Y97/(W97/1.16)) -> 0.4 | AC97: China | AE97: 6 | AF97: 144 | AG97: En revisión de dummy para autorización final | AH97: 46366 | AL97: 148.85 | AM97: =+AL97/1.16 -> 128.31897 | AN97: =+V98/AM97 -> #VALUE! | AO97: =1-V98/AM97 -> #VALUE! | AP97: =1-(AM97/(AL97/1.16)) -> 0 | BA97: 1 | BB97: 1 | BC97: 1 | BD97: 1 | BE97: 1 | BF97: 1 | BJ97: 9 | BK97: =SUM(BA97:BI97) -> 6 | BL97: =+BK97/BJ97 -> 0.66666667 | BR97: PPEDIDOS-260827594 Se espera que PT este listo 09 Nov | BS97: 46038 | BT97: Eduardo (Compras)
A98: 82 | B98: TBC | C98: Diciembre | D98: En tiempo | E98: 7502327991779 | F98: VLT-93 | G98: Labial gloss Velvet "Lip gloss Dear Darling" | H98: #VALUE! | I98: 3.3 gr | J98: Velvet | K98: Mix de canales | L98: 1 | M98: USHAS | N98: https://www.mercadolibre.com.mx/blood-money-palette-x-jeffree-star-cosmetics-paleta-sombras/p/MLM22663715?matt_tool=28238160&utm_source=google_shopping&utm_medium=organic&pdp_filters=item_id%3AMLM3574100304&from=gshop | O98: MAKEUP | P98: 3.2 | Q98: RMB | R98: 10000 | S98: =+P98*$T$29 -> #VALUE! | T98: =+S98*0.36 -> #VALUE! | U98: =(S98+T98)*0.0586 -> #VALUE! | V98: =S98+T98+U98 -> #VALUE! | W98: 229 | X98: =W98/1.16 -> 197.41379 | Y98: =X98*0.6 -> 118.44828 | Z98: =V98/Y98 -> #VALUE! | AA98: =1-(V98/Y98) -> #VALUE! | AB98: =1-(Y98/(W98/1.16)) -> 0.4 | AC98: China | AE98: 6 | AF98: 144 | AG98: En revisión de dummy para autorización final | AH98: 46366 | AL98: 148.85 | AM98: =+AL98/1.16 -> 128.31897 | AN98: =+V99/AM98 -> #VALUE! | AO98: =1-V99/AM98 -> #VALUE! | AP98: =1-(AM98/(AL98/1.16)) -> 0 | BA98: 1 | BB98: 1 | BC98: 1 | BD98: 1 | BE98: 1 | BF98: 1 | BJ98: 9 | BK98: =SUM(BA98:BI98) -> 6 | BL98: =+BK98/BJ98 -> 0.66666667 | BR98: PPEDIDOS-260827594 Se espera que PT este listo 09 Nov | BS98: 46038 | BT98: Eduardo (Compras)
A99: 83 | B99: TBC | C99: Diciembre | D99: En tiempo | E99: 7502327991786 | F99: VLT-94 | G99: Labial líquido brillante de larga duración Velvet "Radiant Lip First Kiss" | H99: #VALUE! | I99: 10 g | J99: Velvet | K99: Mix de canales | L99: 1 | M99: USHAS | N99: https://www.mercadolibre.com.mx/blood-money-palette-x-jeffree-star-cosmetics-paleta-sombras/p/MLM22663715?matt_tool=28238160&utm_source=google_shopping&utm_medium=organic&pdp_filters=item_id%3AMLM3574100304&from=gshop | O99: MAKEUP | P99: 2.78 | Q99: RMB | R99: 10000 | S99: =+P99*$T$29 -> #VALUE! | T99: =+S99*0.36 -> #VALUE! | U99: =(S99+T99)*0.0814 -> #VALUE! | V99: =S99+T99+U99 -> #VALUE! | W99: 169 | X99: =W99/1.16 -> 145.68966 | Y99: =X99*0.6 -> 87.413793 | Z99: =V99/Y99 -> #VALUE! | AA99: =1-(V99/Y99) -> #VALUE! | AB99: =1-(Y99/(W99/1.16)) -> 0.4 | AC99: China | AE99: 6 | AF99: 144 | AG99: En revisión de dummy para autorización final | AH99: 46366 | AL99: 109.85 | AM99: =+AL99/1.16 -> 94.698276 | AN99: =+V100/AM99 -> #VALUE! | AO99: =1-V100/AM99 -> #VALUE! | AP99: =1-(AM99/(AL99/1.16)) -> 0 | BA99: 1 | BB99: 1 | BC99: 1 | BD99: 1 | BE99: 1 | BF99: 1 | BJ99: 9 | BK99: =SUM(BA99:BI99) -> 6 | BL99: =+BK99/BJ99 -> 0.66666667 | BR99: En revisión por costos | BS99: =AH99 -> 46366 | BT99: Eduardo (Compras)
A100: 84 | B100: TBC | C100: Diciembre | D100: En tiempo | E100: 7502327991793 | F100: VLT-95 | G100: Labial líquido brillante de larga duración Velvet "Radiant Lip True Romance" | H100: #VALUE! | I100: 10 g | J100: Velvet | K100: Mix de canales | L100: 1 | M100: USHAS | N100: https://www.mercadolibre.com.mx/blood-money-palette-x-jeffree-star-cosmetics-paleta-sombras/p/MLM22663715?matt_tool=28238160&utm_source=google_shopping&utm_medium=organic&pdp_filters=item_id%3AMLM3574100304&from=gshop | O100: MAKEUP | P100: 2.78 | Q100: RMB | R100: 10000 | S100: =+P100*$T$29 -> #VALUE! | T100: =+S100*0.36 -> #VALUE! | U100: =(S100+T100)*0.0814 -> #VALUE! | V100: =S100+T100+U100 -> #VALUE! | W100: 169 | X100: =W100/1.16 -> 145.68966 | Y100: =X100*0.6 -> 87.413793 | Z100: =V100/Y100 -> #VALUE! | AA100: =1-(V100/Y100) -> #VALUE! | AB100: =1-(Y100/(W100/1.16)) -> 0.4 | AC100: China | AE100: 6 | AF100: 144 | AG100: En revisión de dummy para autorización final | AH100: 46366 | AL100: 109.85 | AM100: =+AL100/1.16 -> 94.698276 | AN100: =+V101/AM100 -> #VALUE! | AO100: =1-V101/AM100 -> #VALUE! | AP100: =1-(AM100/(AL100/1.16)) -> 0 | BA100: 1 | BB100: 1 | BC100: 1 | BD100: 1 | BE100: 1 | BF100: 1 | BJ100: 9 | BK100: =SUM(BA100:BI100) -> 6 | BL100: =+BK100/BJ100 -> 0.66666667 | BR100: En revisión por costos | BS100: =AH100 -> 46366 | BT100: Eduardo (Compras)
A101: 85 | B101: TBC | C101: Diciembre | D101: En tiempo | E101: 7502327991809 | F101: VLT-96 | G101: Labial líquido brillante de larga duración Velvet "Radiant Lip Soft Devotion" | H101: #VALUE! | I101: 10 g | J101: Velvet | K101: Mix de canales | L101: 1 | M101: USHAS | N101: https://www.mercadolibre.com.mx/blood-money-palette-x-jeffree-star-cosmetics-paleta-sombras/p/MLM22663715?matt_tool=28238160&utm_source=google_shopping&utm_medium=organic&pdp_filters=item_id%3AMLM3574100304&from=gshop | O101: MAKEUP | P101: 2.78 | Q101: RMB | R101: 10000 | S101: =+P101*$T$29 -> #VALUE! | T101: =+S101*0.36 -> #VALUE! | U101: =(S101+T101)*0.0814 -> #VALUE! | V101: =S101+T101+U101 -> #VALUE! | W101: 169 | X101: =W101/1.16 -> 145.68966 | Y101: =X101*0.6 -> 87.413793 | Z101: =V101/Y101 -> #VALUE! | AA101: =1-(V101/Y101) -> #VALUE! | AB101: =1-(Y101/(W101/1.16)) -> 0.4 | AC101: China | AE101: 6 | AF101: 144 | AG101: En revisión de dummy para autorización final | AH101: 46366 | AL101: 109.85 | AM101: =+AL101/1.16 -> 94.698276 | AN101: =+V102/AM101 -> #VALUE! | AO101: =1-V102/AM101 -> #VALUE! | AP101: =1-(AM101/(AL101/1.16)) -> 0 | BA101: 1 | BB101: 1 | BC101: 1 | BD101: 1 | BE101: 1 | BF101: 1 | BJ101: 9 | BK101: =SUM(BA101:BI101) -> 6 | BL101: =+BK101/BJ101 -> 0.66666667 | BR101: En revisión por costos | BS101: =AH101 -> 46366 | BT101: Eduardo (Compras)
A102: 86 | B102: TBC | C102: Diciembre | D102: En tiempo | E102: 7502327992608 | F102: VLT-97 | G102: Labial gloss con colgante Velvet "Lip glaze Pure" | H102: #VALUE! | I102: 12.5 g | J102: Velvet | K102: Mix de canales | L102: 1 | M102: USHAS | N102: https://www.amazon.com.mx/gp/aw/d/B0F2TS79HS/?_encoding=UTF8&pd_rd_plhdr=t&aaxitk=b9cc468649bc8da8a4b40dab37c68acc&hsa_cr_id=0&qid=1755107150&sr=1-1-9e67e56a-6f64-441f-a281-df67fc737124&ref_=sbx_be_s_sparkle_lsi4d_asin_0_title&pd_rd_w=Jz3uq&content-id=amzn1.sym.cc2c6205-3abd-4de8-9a5e-9263ccb1e66a%3Aamzn1.sym.cc2c6205-3abd-4de8-9a5e-9263ccb1e66a&pf_rd_p=cc2c6205-3abd-4de8-9a5e-9263ccb1e66a&pf_rd_r=YK4AKDSA4HDJ27GXNPGJ&pd_rd_wg=vzXnI&pd_rd_r=4b81acff-6719-4d1f-8ca8-d6df26ac1343&th=1 | O102: MAKEUP | P102: 6.8 | Q102: RMB | R102: 10000 | S102: =+P102*$T$29 -> #VALUE! | T102: =+S102*0.36 -> #VALUE! | U102: =(S102+T102)*0.0586 -> #VALUE! | V102: =S102+T102+U102 -> #VALUE! | W102: 179 | X102: =W102/1.16 -> 154.31034 | Y102: =X102*0.6 -> 92.586207 | Z102: =V102/Y102 -> #VALUE! | AA102: =1-(V102/Y102) -> #VALUE! | AB102: =1-(Y102/(W102/1.16)) -> 0.4 | AC102: China | AE102: 6 | AF102: 144 | AG102: En proceso de realizacion de dummy para autorizacion final | AH102: 46366 | AL102: 116.35 | AM102: =+AL102/1.16 -> 100.30172 | AN102: =+V103/AM102 -> #VALUE! | AO102: =1-V103/AM102 -> #VALUE! | AP102: =1-(AM102/(AL102/1.16)) -> 0 | BA102: 1 | BB102: 1 | BC102: 1 | BD102: 1 | BE102: 1 | BF102: 1 | BJ102: 9 | BK102: =SUM(BA102:BI102) -> 6 | BL102: =+BK102/BJ102 -> 0.66666667 | BR102: En revisión por costos | BS102: =AH102 -> 46366 | BT102: Eduardo (Compras)
...

Sheet Velvet 2026 Fase 2
CJ14: SEGUIMIENTO DE FECHAS
CJ15: PPEDIDOS | CL15: PREPRODCCION | CN15: AUTORIZACIÓN MARCA | CP15: DISPONIBILIDAD | CR15: DOCUMENTOS PROVEEDOR | CT15: PICK UP DE MERCANCIA | CV15: SALIDA DE LIS | CX15: LLEGADA A ADUANA | CZ15: DISPONIBILIDAD EN ALMACEN
A16: # | B16: Fecha confirmada de Lanzamiento | C16: Mes de Lanzamiento (Esperado) | D16: Estatus | E16: EAN | F16: Código interno | G16: Nombre Comercial | H16: Imagen | I16: Contenido | J16: Marca | K16: Canales | L16: Fase | M16: Proveedor | N16: Benchmark tonos Amazon/MELI | O16: Categoría | P16: Costo real | Q16: Moneda | R16: Piezas cotizadas (MOQ) | S16: Costo Esperado en MXN | T16: IGI | U16: Incrementables | V16: Costo final en MXN (FOB en almacén PT) | W16: Precio publico C/IVA | X16: Precio Público S/IVA | Y16: Facturación por unidad | Z16: Factor costo | AA16: Margen de utilidad bruta | AB16: MU Cliente | AC16: Pais de Origen | AD16: DUN 14 (INNER) | AE16: Inner | AF16: Master | AG16: Comentarios | AI16: Precio publico C/IVA | AJ16: Facturación por unidad | AK16: Factor costo | AL16: Margen de utilidad bruta | AM16: Margen MO | BA16: Line Up | BB16: Costo Autorizado | BC16: PVP Autorizado | BD16: Formula autorizada | BE16: Vobo CEO + VPs | BF16: Arte Final | BG16: PO | BH16: Salida de LIS | BI16: Disponibilidad en almacén | BJ16: Total | BK16: Estatus | BL16: % de Avance | BR16: Comentarios | BS16: Disponibilidad en Almacén | BT16: Responsable Siguiente paso | CJ16: ESPERADA | CK16: REAL | CL16: ESPERADA | CM16: REAL | CN16: ESPERADA | CO16: REAL | CP16: ESPERADA | CQ16: REAL | CR16: ESPERADA | CS16: REAL | CT16: ESPERADA | CU16: REAL | CV16: ESPERADA | CW16: REAL | CX16: ESPERADA | CY16: REAL | CZ16: ESPERADA | DA16: REAL
A17: 68 | B17: 46248 | C17: Agosto | D17: En tiempo | E17: 7502327991526 | F17: VLT-68 | G17: Crema Facial VELVET | H17: #VALUE! | I17: 50 g | J17: Velvet | K17: Mix de canales | L17: 2 | M17: MUC | O17: Skin Care | P17: 9 | Q17: RMB | R17: 10000 | S17: =+P17*$T$21 -> 0 | T17: =+S17*0.25 -> 0 | U17: =(S17+T17)*0.0556 -> 0 | V17: =S17+T17+U17 -> 0 | W17: 249 | X17: =W17/1.16 -> 214.65517 | Y17: =X17*0.6 -> 128.7931 | Z17: =V17/Y17 -> 0 | AA17: =1-(V17/Y17) -> 1 | AB17: =1-(Y17/(W17/1.16)) -> 0.4 | AC17: China | AE17: 4 | AF17: 48 | AI17: 161.85 | AJ17: =+AI17/1.16 -> 139.52586 | AK17: =+V17/AJ17 -> 0 | AL17: =1-V17/AJ17 -> 1 | AM17: =1-(AJ17/(AI17/1.16)) -> 0 | BA17: 1 | BB17: 1 | BC17: 1 | BD17: 1 | BJ17: 9 | BK17: =SUM(BA17:BI17) -> 4 | BL17: =+BK17/BJ17 -> 0.44444444 | BR17: En proceso de realizacion de dummy para autorizacion final | BS17: CANCELADO | BT17: Daniel

Sheet Minion 2026
B1: Estatus | C1: En tiempo
A2: Minions
A3: Autorizacion | B3: 46101 | C3: 46119
A5: Diseño final | B5: =+B3+7 -> 46108 | C5: =+C3+7 -> 46126
A6: Autorizaciones | B6: =+B5+5 -> 46113 | C6: =+C5+5 -> 46131
A7: Orden de compra | B7: =+B6+2 -> 46115 | C7: 46119
A8: Produccion / envio | B8: =+B7+40 -> 46155 | C8: =+C7+50 -> 46169
A9: Fecha Estimada Pago balance | B9: =+B8+45 -> 46200 | C9: =+C8+45 -> 46214
A10: Llegada Almacén | B10: =+B8+65 -> 46220 | C10: =+C8+65 -> 46234 | AG10: 46188 | AH10: 46296 | AQ10: =+AH10+65 -> 46361 | AR10: cepillos
A11: Lanzamiento | B11: =+B10+14 -> 46234 | C11: =+C10+14 -> 46248 | AG11: 46197 | AH11: 46317 | AQ11: =+AH11+65 -> 46382 | AR11: 2 en 1
AG13: 46202 | AH13: 46326 | AQ13: =+AH13+65 -> 46391 | AR13: DARONG
AG14: 46223 | AH14: =+AG14+65 -> 46288 | AR14: Balsamos | CJ14: SEGUIMIENTO DE FECHAS
CJ15: PPEDIDOS | CL15: PREPRODCCION | CN15: AUTORIZACIÓN MARCA | CP15: DISPONIBILIDAD | CR15: DOCUMENTOS PROVEEDOR | CT15: PICK UP DE MERCANCIA | CV15: SALIDA DE LIS | CX15: LLEGADA A ADUANA | CZ15: DISPONIBILIDAD EN ALMACEN
A16: # | B16: Fecha confirmada de Lanzamiento | C16: Mes de Lanzamiento (Esperado) | D16: Estatus | E16: EAN | F16: Código Interno | G16: Nombre Comercial | H16: Imagen | I16: Contenido | J16: Marca | K16: Canales | L16: Fase | M16: Costo USD | N16: Moneda | O16: Piezas cotizadas | P16: Costo en MXN (FOB en almacén PT) | Q16: IGI | R16: Incrementables | S16: Regalía | T16: Costo final en MXN (FOB en almacén PT) | U16: Precio Benchmark | V16: Precio publico C/IVA | W16: Facturación por unidad | X16: Factor costo | Y16: Margen de utilidad bruta | Z16: Margen Cadena | AA16: Categoria | AB16: País de origen | AC16: Inner | AD16: Máster | AE16: Comentarios | AF16: Disponibilidad en Almacén | AI16: Precio publico C/IVA | AJ16: Facturación por unidad | AK16: Factor costo | AL16: Margen de utilidad bruta | AM16: Margen MO | BA16: Line Up | BB16: Costo Autorizado | BC16: PVP Autorizado | BD16: Formula autorizada | BE16: Vobo CEO + VPs | BF16: Arte Final | BG16: PO | BH16: Salida de LIS | BI16: Disponibilidad en almacén | BJ16: Total | BK16: Estatus | BL16: % de Avance | BR16: Comentarios | BS16: Disponibilidad en Almacén | BT16: Responsable Siguiente paso | CJ16: ESPERADA | CK16: REAL | CL16: ESPERADA | CM16: REAL | CN16: ESPERADA | CO16: REAL | CP16: ESPERADA | CQ16: REAL | CR16: ESPERADA | CS16: REAL | CT16: ESPERADA | CU16: REAL | CV16: ESPERADA | CW16: REAL | CX16: ESPERADA | CY16: REAL | CZ16: ESPERADA | DA16: REAL
A17: 1 | B17: 46234 | C17: Agosto | D17: En tiempo | E17: 7503057496008 | F17: MN.001 | G17: Bálsamo labial con esencia de plátano | I17: 4 g | J17: Minions | K17: Mix de canales | L17: 1 | M17: =0.31+$N$18 -> #VALUE! | N17: USD | O17: 10000 | P17: =+M17*$Q$18 -> #VALUE! | Q17: =+P17*0.36 -> #VALUE! | R17: =+(Q17+P17)*1.3% -> #VALUE! | S17: =+W17*$T$18 -> #VALUE! | T17: =+P17+Q17+R17+S17 -> #VALUE! | U17: Carmex $51 Eos Birthday Cake $44 Labello $79 Azu's My melody $27 Azu's Hello Kitty $25 Disney $39 Hershey's $39 | V17: 49 | W17: =(V17/1.16)*0.6 -> 25.344828 | X17: =T17/W17 -> #VALUE! | Y17: =1-(T17/W17) -> #VALUE! | Z17: =1-(W17/(V17/1.16)) -> 0.4 | AA17: Personal care | AB17: China | AC17: 6 | AD17: =+AC17*12 -> 72 | AE17: Problema en aduana-licencia El lote se va a reproducir | AF17: TBC | AI17: 29 | AJ17: =(AI17/1.16) -> 25 | AK17: =+T17/AJ17 -> #VALUE! | AL17: =1-(T17/AJ17) -> #VALUE! | AM17: =1-(AJ17/(AI17/1.16)) -> 0 | BA17: 1 | BB17: 1 | BC17: 1 | BD17: 1 | BE17: 1 | BF17: 1 | BG17: 1 | BH17: 1 | BJ17: 9 | BK17: =SUM(BA17:BI17) -> 8 | BL17: =+BK17/BJ17 -> 0.88888889 | BR17: =+AE17 -> Problema en aduana-licencia El lote se va a reproducir | BS17: =+AF17 -> TBC | BT17: Eduardo ( compras) | CJ17: 45809 | CK17: 45809
A18: 2 | B18: 46234 | C18: Agosto | D18: En tiempo | E18: 7503057496015 | F18: MN.002 | G18: Bálsamo labial con esencia de algodón de azúcar | I18: 4 g | J18: Minions | K18: Mix de canales | L18: 1 | M18: =0.31+$N$18 -> #VALUE! | N18: USD | O18: 10000 | P18: =+M18*$Q$18 -> #VALUE! | Q18: =+P18*0.36 -> #VALUE! | R18: =+(Q18+P18)*1.3% -> #VALUE! | S18: =+W18*$T$18 -> #VALUE! | T18: =+P18+Q18+R18+S18 -> #VALUE! | U18: Carmex $51 Eos Birthday Cake $44 Labello $79 Azu's My melody $27 Azu's Hello Kitty $25 Disney $39 Hershey's $39 | V18: 49 | W18: =(V18/1.16)*0.6 -> 25.344828 | X18: =T18/W18 -> #VALUE! | Y18: =1-(T18/W18) -> #VALUE! | Z18: =1-(W18/(V18/1.16)) -> 0.4 | AA18: Personal care | AB18: China | AC18: 6 | AD18: =+AC18*12 -> 72 | AE18: Problema en aduana-licencia El lote se va a reproducir | AF18: TBC | AI18: 29 | AJ18: =(AI18/1.16) -> 25 | AK18: =+T18/AJ18 -> #VALUE! | AL18: =1-(T18/AJ18) -> #VALUE! | AM18: =1-(AJ18/(AI18/1.16)) -> 0 | BA18: 1 | BB18: 1 | BC18: 1 | BD18: 1 | BE18: 1 | BF18: 1 | BG18: 1 | BH18: 1 | BJ18: 9 | BK18: =SUM(BA18:BI18) -> 8 | BL18: =+BK18/BJ18 -> 0.88888889 | BR18: =+AE18 -> Problema en aduana-licencia El lote se va a reproducir | BS18: =+AF18 -> TBC | BT18: Eduardo ( compras)
A19: 3 | B19: 46234 | C19: Agosto | D19: En tiempo | E19: 7503057496022 | F19: MN.003 | G19: Set de 3 Bálsamos labiales con esencias de algodón de azúcar, sandía y plátano | I19: 3 x 4 g | J19: Minions | K19: Mix de canales | L19: 1 | M19: =0.97+$N$18 -> #VALUE! | N19: USD | O19: 10000 | P19: =+M19*$Q$18 -> #VALUE! | Q19: =+P19*0.36 -> #VALUE! | R19: =+(Q19+P19)*0.57% -> #VALUE! | S19: =+W19*$T$18 -> #VALUE! | T19: =+P19+Q19+R19+S19 -> #VALUE! | U19: Disney Villanas $119 Disney Toy Story $119 | V19: 119 | W19: =(V19/1.16) -> 102.58621 | X19: =T19/W19 -> #VALUE! | Y19: =1-(T19/W19) -> #VALUE! | Z19: =1-(W19/(V19/1.16)) -> 0 | AA19: Personal care | AB19: China | AC19: 6 | AD19: =+AC19*12 -> 72 | AE19: Problema en aduana-licencia El lote se va a reproducir | AF19: TBC | AI19: 99 | AJ19: =(AI19/1.16) -> 85.344828 | AK19: =+T19/AJ19 -> #VALUE! | AL19: =1-(T19/AJ19) -> #VALUE! | AM19: =1-(AJ19/(AI19/1.16)) -> 0 | BA19: 1 | BB19: 1 | BC19: 1 | BD19: 1 | BE19: 1 | BF19: 1 | BG19: 1 | BH19: 1 | BJ19: 9 | BK19: =SUM(BA19:BI19) -> 8 | BL19: =+BK19/BJ19 -> 0.88888889 | BR19: =+AE19 -> Problema en aduana-licencia El lote se va a reproducir | BS19: =+AF19 -> TBC | BT19: Eduardo ( compras)
A20: 6 | B20: 46234 | C20: Septiembre | D20: En tiempo | E20: 7503057496053 | F20: MN.006 | G20: Jabón líquido para manos con esencia de plátano | I20: 400 mL | J20: Minions | K20: Mega Outlet y Canales Internos | L20: 1 | M20: =0.43+$N$18 -> #VALUE! | N20: USD | O20: 10000 | P20: =+M20*$Q$18 -> #VALUE! | Q20: =+P20*0.25 -> #VALUE! | R20: =+(Q20+P20)*43.94% -> #VALUE! | S20: =+W20*$T$18 -> #VALUE! | T20: =+P20+Q20+R20+S20 -> #VALUE! | U20: Equate $31 Blumen $32 Kleenex $59 Palmolive $60 | V20: 69 | W20: =(V20/1.16)*0.6 -> 35.689655 | X20: =T20/W20 -> #VALUE! | Y20: =1-(T20/W20) -> #VALUE! | Z20: =1-(W20/(V20/1.16)) -> 0.4 | AA20: Skin care | AB20: China | AC20: 6 | AD20: =+AC20*4 -> 24 | AE20: En producción | AF20: 46388 | AI20: 59 | AJ20: =(AI20/1.16) -> 50.862069 | AK20: =+T20/AJ20 -> #VALUE! | AL20: =1-(T20/AJ20) -> #VALUE! | AM20: =1-(AJ20/(AI20/1.16)) -> 0 | BA20: 1 | BB20: 1 | BC20: 1 | BD20: 1 | BE20: 1 | BF20: 1 | BG20: 1 | BJ20: 9 | BK20: =SUM(BA20:BI20) -> 7 | BL20: =+BK20/BJ20 -> 0.77777778 | BR20: =+AE20 -> En producción | BS20: =+AF20 -> 46388 | BT20: NP
A21: 7 | B21: 46234 | C21: Septiembre | D21: En tiempo | E21: 7503057496060 | F21: MN.007 | G21: Jabón liquido para manos con esencia de algodón de azúcar | I21: 400 mL | J21: Minions | K21: Mega Outlet y Canales Internos | L21: 1 | M21: =0.43+$N$18 -> #VALUE! | N21: USD | O21: 10000 | P21: =+M21*$Q$18 -> #VALUE! | Q21: =+P21*0.25 -> #VALUE! | R21: =+(Q21+P21)*43.94% -> #VALUE! | S21: =+W21*$T$18 -> #VALUE! | T21: =+P21+Q21+R21+S21 -> #VALUE! | U21: Equate $31 Blumen $32 Kleenex $59 Palmolive $61 | V21: 69 | W21: =(V21/1.16)*0.6 -> 35.689655 | X21: =T21/W21 -> #VALUE! | Y21: =1-(T21/W21) -> #VALUE! | Z21: =1-(W21/(V21/1.16)) -> 0.4 | AA21: Skin care | AB21: China | AC21: 6 | AD21: =+AC21*4 -> 24 | AE21: En producción | AF21: 46388 | AI21: 59 | AJ21: =(AI21/1.16) -> 50.862069 | AK21: =+T21/AJ21 -> #VALUE! | AL21: =1-(T21/AJ21) -> #VALUE! | AM21: =1-(AJ21/(AI21/1.16)) -> 0 | BA21: 1 | BB21: 1 | BC21: 1 | BD21: 1 | BE21: 1 | BF21: 1 | BG21: 1 | BJ21: 9 | BK21: =SUM(BA21:BI21) -> 7 | BL21: =+BK21/BJ21 -> 0.77777778 | BR21: =+AE21 -> En producción | BS21: =+AF21 -> 46388 | BT21: NP
A22: 8 | B22: 46234 | C22: Septiembre | D22: En tiempo | E22: 7503057496077 | F22: MN.008 | G22: Gel de baño 2 en 1 para cara y cuerpo aroma banana | I22: 400 mL | J22: Minions | K22: Mega Outlet y Canales Internos | L22: 1 | M22: =0.793+$N$18 -> #VALUE! | N22: USD | O22: 10000 | P22: =+M22*$Q$18 -> #VALUE! | Q22: =+P22*0.25 -> #VALUE! | R22: =+(Q22+P22)*26.93% -> #VALUE! | S22: =+W22*$T$18 -> #VALUE! | T22: =+P22+Q22+R22+S22 -> #VALUE! | U22: Johnson $145 Dove baby $140 Raw Sugar $135 Loreal Kids $86 Grissi Hot Wheels $69 Blumen $49 Trolls $125 | V22: 89 | W22: =(V22/1.16)*0.65 -> 49.87069 | X22: =T22/W22 -> #VALUE! | Y22: =1-(T22/W22) -> #VALUE! | Z22: =1-(W22/(V22/1.16)) -> 0.35 | AA22: Skin care | AB22: China | AC22: 6 | AD22: =+AC22*4 -> 24 | AE22: En producción | AF22: 46382 | AI22: 69 | AJ22: =(AI22/1.16) -> 59.482759 | AK22: =+T22/AJ22 -> #VALUE! | AL22: =1-(T22/AJ22) -> #VALUE! | AM22: =1-(AJ22/(AI22/1.16)) -> 0 | BA22: 1 | BB22: 1 | BC22: 1 | BD22: 1 | BE22: 1 | BF22: 1 | BG22: 1 | BJ22: 9 | BK22: =SUM(BA22:BI22) -> 7 | BL22: =+BK22/BJ22 -> 0.77777778 | BR22: =+AE22 -> En producción | BS22: =+AF22 -> 46382 | BT22: NP
A23: 9 | B23: 46234 | C23: Septiembre | D23: En tiempo | E23: 7503057496084 | F23: MN.009 | G23: Crema corporal con aroma a plátano | I23: 400 mL | J23: Minions | K23: Mega Outlet y Canales Internos | L23: 1 | M23: =0.57+$N$18 -> #VALUE! | N23: USD | O23: 10000 | P23: =+M23*$Q$18 -> #VALUE! | Q23: =+P23*0.25 -> #VALUE! | R23: =+(Q23+P23)*33.15% -> #VALUE! | S23: =+W23*$T$18 -> #VALUE! | T23: =+P23+Q23+R23+S23 -> #VALUE! | U23: St Ives $80 HoneyKeeper $81 Vasenol $80 Mustela $276 Jergens $89 Grissi $69 Nivea $80 Dove baby $155 | V23: 69 | W23: =(V23/1.16)*0.6 -> 35.689655 | X23: =T23/W23 -> #VALUE! | Y23: =1-(T23/W23) -> #VALUE! | Z23: =1-(W23/(V23/1.16)) -> 0.4 | AA23: Skin care | AB23: China | AC23: 6 | AD23: =+AC23*4 -> 24 | AE23: En producción | AF23: 46388 | AI23: 69 | AJ23: =(AI23/1.16) -> 59.482759 | AK23: =+T23/AJ23 -> #VALUE! | AL23: =1-(T23/AJ23) -> #VALUE! | AM23: =1-(AJ23/(AI23/1.16)) -> 0 | BA23: 1 | BB23: 1 | BC23: 1 | BD23: 1 | BE23: 1 | BF23: 1 | BG23: 1 | BJ23: 9 | BK23: =SUM(BA23:BI23) -> 7 | BL23: =+BK23/BJ23 -> 0.77777778 | BR23: =+AE23 -> En producción | BS23: =+AF23 -> 46388 | BT23: NP
A24: 11 | B24: 46234 | C24: Septiembre | D24: En tiempo | E24: 7503057496107 | F24: MN.011 | G24: Body Mist Minions "Citrus Banana" | I24: 120 mL | J24: Minions | K24: Mega Outlet y Canales Internos | L24: 1 | N24: MXN | O24: 10000 | P24: #NAME? | Q24: 0 | R24: 0 | S24: =+W24*$T$18 -> #VALUE! | T24: =+P24+Q24+R24+S24 -> #NAME? | U24: Disney $99 Chupa Chups $75 Hot Wheels $69 Essence $57 Coty $90 Bioscents $105 Stitch Zara $319 ISDIN $240 | V24: 99 | W24: =(V24/1.16)*0.6 -> 51.206897 | X24: =T24/W24 -> #NAME? | Y24: =1-(T24/W24) -> #NAME? | Z24: =1-(W24/(V24/1.16)) -> 0.4 | AA24: Skin care | AB24: México | AC24: 6 | AD24: =+AC24*12 -> 72 | AE24: Tema de autorización de fábrica de etiquetas, pendiente vobo de licencia | AF24: tbc | AI24: 59 | AJ24: =(AI24/1.16) -> 50.862069 | AK24: =+T24/AJ24 -> #NAME? | AL24: =1-(T24/AJ24) -> #NAME? | AM24: =1-(AJ24/(AI24/1.16)) -> 0 | BA24: 1 | BB24: 1 | BC24: 1 | BD24: 1 | BE24: 1 | BF24: 1 | BG24: 1 | BH24: 1 | BJ24: 9 | BK24: =SUM(BA24:BI24) -> 8 | BL24: =+BK24/BJ24 -> 0.88888889 | BR24: =+AE24 -> Tema de autorización de fábrica de etiquetas, pendiente vobo de licencia | BS24: =+AF24 -> tbc | BT24: NP
A25: 12 | B25: 46234 | C25: Septiembre | D25: En tiempo | E25: 7503057496091 | F25: MN.012 | G25: Body Mist Minions "Cotton Candy" | I25: 120 mL | J25: Minions | K25: Mega Outlet y Canales Internos | L25: 1 | N25: MXN | O25: 10000 | P25: #NAME? | Q25: 0 | R25: 0 | S25: =+W25*$T$18 -> #VALUE! | T25: =+P25+Q25+R25+S25 -> #NAME? | U25: Disney $99 Chupa Chups $75 Hot Wheels $69 Essence $57 Coty $90 Bioscents $105 Stitch Zara $319 ISDIN $241 | V25: 99 | W25: =(V25/1.16)*0.6 -> 51.206897 | X25: =T25/W25 -> #NAME? | Y25: =1-(T25/W25) -> #NAME? | Z25: =1-(W25/(V25/1.16)) -> 0.4 | AA25: Personal care | AB25: México | AC25: 6 | AD25: =+AC25*12 -> 72 | AE25: Tema de autorización de fábrica de etiquetas, pendiente vobo de licencia | AF25: tbc | AI25: 59 | AJ25: =(AI25/1.16) -> 50.862069 | AK25: =+T25/AJ25 -> #NAME? | AL25: =1-(T25/AJ25) -> #NAME? | AM25: =1-(AJ25/(AI25/1.16)) -> 0 | BA25: 1 | BB25: 1 | BC25: 1 | BD25: 1 | BE25: 1 | BF25: 1 | BG25: 1 | BH25: 1 | BJ25: 9 | BK25: =SUM(BA25:BI25) -> 8 | BL25: =+BK25/BJ25 -> 0.88888889 | BR25: =+AE25 -> Tema de autorización de fábrica de etiquetas, pendiente vobo de licencia | BS25: =+AF25 -> tbc | BT25: NP
A26: 13 | B26: 46234 | C26: Septiembre | D26: En tiempo | E26: 7503057496114 | F26: MN.013 | G26: Cepillo para cabello "Minions" | I26: 1 pza | J26: Minions | K26: Mega Outlet y Canales Internos | L26: 1 | M26: =0.85+$N$18 -> #VALUE! | N26: USD | O26: 10000 | P26: =+M26*$Q$18 -> #VALUE! | Q26: =+P26*0.15 -> #VALUE! | R26: =+(Q26+P26)*15.33% -> #VALUE! | S26: =+W26*$T$18 -> #VALUE! | T26: =+P26+Q26+R26+S26 -> #VALUE! | U26: Disney $99 Conair $65 Goody (HEB) $89 Wet (Chedraui) $176 | V26: 99 | W26: =(V26/1.16)*0.6 -> 51.206897 | X26: =T26/W26 -> #VALUE! | Y26: =1-(T26/W26) -> #VALUE! | Z26: =1-(W26/(V26/1.16)) -> 0.4 | AA26: Personal care | AB26: China | AC26: 6 | AD26: =+AC26*12 -> 72 | AE26: En espera de LIS | AF26: 46361 | AI26: 49 | AJ26: =(AI26/1.16) -> 42.241379 | AK26: =+T26/AJ26 -> #VALUE! | AL26: =1-(T26/AJ26) -> #VALUE! | AM26: =1-(AJ26/(AI26/1.16)) -> 0 | BA26: 1 | BB26: 1 | BC26: 1 | BD26: 1 | BE26: 1 | BF26: 1 | BG26: 1 | BH26: 1 | BJ26: 9 | BK26: =SUM(BA26:BI26) -> 8 | BL26: =+BK26/BJ26 -> 0.88888889 | BR26: =+AE26 -> En espera de LIS | BS26: =+AF26 -> 46361 | BT26: NP
A27: 14 | B27: 46234 | C27: Septiembre | D27: En tiempo | E27: 7503057496121 | F27: MN.014 | G27: Cepillo para cabello "Unicornio" | I27: 1 pza | J27: Minions | K27: Mega Outlet y Canales Internos | L27: 1 | M27: =0.85+$N$18 -> #VALUE! | N27: USD | O27: 10000 | P27: =+M27*$Q$18 -> #VALUE! | Q27: =+P27*0.15 -> #VALUE! | R27: =+(Q27+P27)*15.33% -> #VALUE! | S27: =+W27*$T$18 -> #VALUE! | T27: =+P27+Q27+R27+S27 -> #VALUE! | U27: Disney $99 Conair $65 Goody (HEB) $89 Wet (Chedraui) $177 | V27: 99 | W27: =(V27/1.16)*0.6 -> 51.206897 | X27: =T27/W27 -> #VALUE! | Y27: =1-(T27/W27) -> #VALUE! | Z27: =1-(W27/(V27/1.16)) -> 0.4 | AA27: Personal care | AB27: China | AC27: 6 | AD27: =+AC27*12 -> 72 | AE27: En espera de LIS | AF27: 46361 | AI27: 49 | AJ27: =(AI27/1.16) -> 42.241379 | AK27: =+T27/AJ27 -> #VALUE! | AL27: =1-(T27/AJ27) -> #VALUE! | AM27: =1-(AJ27/(AI27/1.16)) -> 0 | BA27: 1 | BB27: 1 | BC27: 1 | BD27: 1 | BE27: 1 | BF27: 1 | BG27: 1 | BH27: 1 | BJ27: 9 | BK27: =SUM(BA27:BI27) -> 8 | BL27: =+BK27/BJ27 -> 0.88888889 | BR27: =+AE27 -> En espera de LIS | BS27: =+AF27 -> 46361 | BT27: NP

Sheet Playboy 2026 Fase 2
CJ14: SEGUIMIENTO DE FECHAS
CJ15: PPEDIDOS | CL15: PREPRODCCION | CN15: AUTORIZACIÓN MARCA | CP15: DISPONIBILIDAD | CR15: DOCUMENTOS PROVEEDOR | CT15: PICK UP DE MERCANCIA | CV15: SALIDA DE LIS | CX15: LLEGADA A ADUANA | CZ15: DISPONIBILIDAD EN ALMACEN
A16: # | B16: Fecha confirmada de Lanzamiento | C16: Mes de Lanzamiento (Esperado) | D16: Estatus | E16: EAN | F16: Código interno | G16: Nombre Comercial | H16: Imagen | I16: Contenido | J16: Marca | K16: Canales | L16: Fase | M16: Costo real | N16: Moneda | O16: Piezas cotizadas (MOQ) | P16: Costo Esperado en MXN | Q16: IGI | R16: Incrementables | S16: Costo final en MXN (FOB en almacén PT) | T16: Caracteristicas de Fórmula | U16: Costo Autorizado | V16: Moneda | W16: Piezas cotizadas (MOQ) | X16: Costo en MXN | Y16: IGI | Z16: Incrementables | AA16: Regalía | AB16: Costo final en MXN (FOB en almacén PT) | AC16: BENCHMARK DE PRECIO (MARCA) | AD16: Precio Benchmark | AE16: COMPETIDORES CERCANOS (Index de precios) | AF16: Precio publico C/IVA | AG16: Precio público s/IVA | AH16: Facturación por unidad | AI16: Factor costo | AJ16: Margen de utilidad bruta | AK16: MU Cliente | AL16: Categoría | AM16: Pais de origen | AN16: Inner pcs | AO16: Master | AP16: Comentarios | AR16: Precio publico C/IVA | AS16: Facturación por unidad | AT16: Factor costo | AU16: Margen de utilidad bruta | AV16: Margen MO | BA16: Line Up | BB16: Costo Autorizado | BC16: PVP Autorizado | BD16: Formula autorizada | BE16: Vobo CEO + VPs | BF16: Arte Final | BG16: PO | BH16: Salida de LIS | BI16: Disponibilidad en almacén | BJ16: Total | BK16: Estatus | BL16: % de Avance | BR16: Comentarios | BS16: Disponibilidad en Almacén | BT16: Responsable Siguiente paso | CJ16: ESPERADA | CK16: REAL | CL16: ESPERADA | CM16: REAL | CN16: ESPERADA | CO16: REAL | CP16: ESPERADA | CQ16: REAL | CR16: ESPERADA | CS16: REAL | CT16: ESPERADA | CU16: REAL | CV16: ESPERADA | CW16: REAL | CX16: ESPERADA | CY16: REAL | CZ16: ESPERADA | DA16: REAL
A17: 1 | B17: Por confirmar | C17: Por confirmar | D17: Pendiente | E17: 7503057496145 | F17: PB-001 | G17: Shampoo para hombre "Fresh & Clean" | H17: #VALUE! | I17: 400 ml | J17: Playboy | K17: TBC | L17: 2 | M17: https://www.alibaba.com/product-detail/400ml-HDPE-Flat-Shape-Bottle-for_1601526564011.html?spm=a2700.prosearch.normal_offer.d_image.45d867af4CQShv&priceId=1c4b5abd5ee1449cb5593bcec7ada90f | O17: Shampoo Ego Limpieza profunda | Q17: N/A | R17: N/A | S17: N/A | T17: Mentol, Ginseg. Limpieza profunda. Refrescante. Vegano, libre de parabenos con olor a Menta + cítricos (limón, bergamota o mandarina): muy refrescante, con energía vibrante | V17: MXN | W17: 10000 | X17: 14.88 | AA17: =+AH17*$AB$18 -> #VALUE! | AB17: =X17+Y17+Z17+AA17 -> #VALUE! | AC17: EGO | AD17: 70 | AE17: Ego Limpieza Profunda 200 ml $37.50 Ego Limpieza Profunda 400 ml $71.00 Axe Total Fresh 3 en 1 473 ml $69 Axe Apollo 2 en 1 473 ml $89 | AF17: 69 | AG17: =AF17/1.16 -> 59.482759 | AH17: =(AG17)*0.6 -> 35.689655 | AI17: =AB17/AH17 -> #VALUE! | AJ17: =1-(AB17/AH17) -> #VALUE! | AK17: =1-(AH17/(AF17/1.16)) -> 0.4 | AL17: Personal Care | AM17: MX | AN17: TBC | AO17: TBC | AR17: 49 | AS17: =(AR17/1.16) -> 42.241379 | AT17: =+AB17/AS17 -> #VALUE! | AU17: =1-(AB17/AS17) -> #VALUE! | AV17: =1-(AS17/(AR17/1.16)) -> 0 | BA17: 1 | BJ17: 9 | BK17: =SUM(BA17:BG17) -> 1 | BL17: =+BK17/BJ17 -> 0.11111111 | CJ17: 45809 | CK17: 45809
A18: 2 | B18: Por confirmar | C18: Por confirmar | D18: Pendiente | E18: 7503057496152 | F18: PB-002 | G18: Shampoo para hombre "Power Strength" | H18: #VALUE! | I18: 400 ml | J18: Playboy | K18: TBC | L18: 2 | M18: https://www.alibaba.com/product-detail/400ml-HDPE-Flat-Shape-Bottle-for_1601526564011.html?spm=a2700.prosearch.normal_offer.d_image.45d867af4CQShv&priceId=1c4b5abd5ee1449cb5593bcec7ada90f | O18: Shampoo Ego Control Caida | Q18: N/A | R18: N/A | S18: N/A | T18: Cafeína, Biotina. Reduce la caída de cabello. Vegano, libre de parabenos" con olor Eucalipto + hierbas aromáticas (romero, albahaca): sensación de frescor intenso y deportivo. | V18: MXN | W18: 10000 | X18: 15 | AA18: =+AH18*$AB$18 -> #VALUE! | AB18: =X18+Y18+Z18+AA18 -> #VALUE! | AC18: EGO | AD18: 70 | AE18: Nivea Men Strong Power 475 ml $199 Ego Limpieza Profunda 400 ml $71 Axe Total Fresh 3 en 1 473 ml $69 Axe Apollo 2 en 1 473 ml $89 | AF18: 69 | AG18: =AF18/1.16 -> 59.482759 | AH18: =(AG18)*0.6 -> 35.689655 | AI18: =AB18/AH18 -> #VALUE! | AJ18: =1-(AB18/AH18) -> #VALUE! | AK18: =1-(AH18/(AF18/1.16)) -> 0.4 | AL18: Personal Care | AM18: MX | AN18: TBC | AO18: TBC | AR18: 49 | AS18: =(AR18/1.16) -> 42.241379 | AT18: =+AB18/AS18 -> #VALUE! | AU18: =1-(AB18/AS18) -> #VALUE! | AV18: =1-(AS18/(AR18/1.16)) -> 0 | BA18: 1 | BJ18: 9 | BK18: =SUM(BA18:BG18) -> 1 | BL18: =+BK18/BJ18 -> 0.11111111
A19: 3 | B19: Por confirmar | C19: Por confirmar | D19: Pendiente | E19: 7503057496169 | F19: PB-003 | G19: Jabón líquido 3 en 1 "Core Clean" | H19: #VALUE! | I19: 400 mL | J19: Playboy | K19: TBC | L19: 2 | M19: https://www.alibaba.com/product-detail/SOMEWANG-100ml-200ml-400ml-Shampoo-Packaging_1601155361608.html?spm=a2700.find_similar.normal_offer.d_image.82865f93kmONAO | O19: Gel de ducha Nivea Men (Checar si solo es MO) | Q19: N/A | R19: N/A | S19: N/A | T19: Jabón líquido 3 en 1 con Aloe Vera. Para cara, cuerpo y cabello. Limpieza efectiva, diseñado para la piel de hombre. Vegano, libre de parabenos" con olor Pepino + té verde: más moderno y urbano, fresco pero sofisticado | V19: MXN | W19: 10000 | X19: 16.48 | AA19: =+AH19*$AB$18 -> #VALUE! | AB19: =X19+Y19+Z19+AA19 -> #VALUE! | AC19: NIVEA | AD19: 89 | AE19: Axe Total Fresh 3 en 1 473 ml $69 Axe Apollo 2 en 1 473 ml $89 Stefano Jabón Liquido Corporal Black 400 ml $79 | AF19: 69 | AG19: =AF19/1.16 -> 59.482759 | AH19: =(AG19)*0.6 -> 35.689655 | AI19: =AB19/AH19 -> #VALUE! | AJ19: =1-(AB19/AH19) -> #VALUE! | AK19: =1-(AH19/(AF19/1.16)) -> 0.4 | AL19: Personal Care | AM19: MX | AN19: TBC | AO19: TBC | AR19: 49 | AS19: =(AR19/1.16) -> 42.241379 | AT19: =+AB19/AS19 -> #VALUE! | AU19: =1-(AB19/AS19) -> #VALUE! | AV19: =1-(AS19/(AR19/1.16)) -> 0 | BA19: 1 | BJ19: 9 | BK19: =SUM(BA19:BG19) -> 1 | BL19: =+BK19/BJ19 -> 0.11111111
A20: 4 | B20: Por confirmar | C20: Por confirmar | D20: Pendiente | E20: 7503057496176 | F20: PB-004 | G20: Gel fijación media "Hold Motion" | H20: #VALUE! | I20: 220 g | J20: Playboy | K20: TBC | L20: 2 | M20: https://www.alibaba.com/product-detail/5ml-10ml-15ml-30ml-50ml-100ml_1600966550866.html?spm=a2700.galleryofferlist.p_offer.d_image.2d3813a0uGMI4E&s=p | O20: Gel ego | Q20: N/A | R20: N/A | S20: N/A | T20: Gel para cabello fijación media. Definición sin dejar residuos. Vegano, libre de parabenos. Notas oceánicas + madera clara (cedro o ámbar gris) | V20: MXN | W20: 10000 | X20: 13.45 | AA20: =+AH20*$AB$18 -> #VALUE! | AB20: =X20+Y20+Z20+AA20 -> #VALUE! | AC20: EGO | AD20: 59 | AE20: Gel para Cabello Ego Ultra Intense 220 m $44.00 Gel Moco de Gorila Punk 340 g $65.00 Gel de Linaza Árbol Verde 500 g $39.00 | AF20: 49 | AG20: =AF20/1.16 -> 42.241379 | AH20: =(AG20)*0.6 -> 25.344828 | AI20: =AB20/AH20 -> #VALUE! | AJ20: =1-(AB20/AH20) -> #VALUE! | AK20: =1-(AH20/(AF20/1.16)) -> 0.4 | AL20: Personal Care | AM20: MX | AN20: TBC | AO20: TBC | AR20: 49 | AS20: =(AR20/1.16) -> 42.241379 | AT20: =+AB20/AS20 -> #VALUE! | AU20: =1-(AB20/AS20) -> #VALUE! | AV20: =1-(AS20/(AR20/1.16)) -> 0 | BA20: 1 | BJ20: 9 | BK20: =SUM(BA20:BG20) -> 1 | BL20: =+BK20/BJ20 -> 0.11111111
A21: 5 | B21: Por confirmar | C21: Por confirmar | D21: Pendiente | E21: 7503057496190 | F21: PB-006 | G21: Limpiador facial 150 ml "Skin Cleanser" | H21: #VALUE! | I21: 150mL | J21: Playboy | K21: TBC | L21: 2 | M21: https://www.alibaba.com/product-detail/Tubes-Cosmetic-Tube-Concealer-Cream-Foundation_1601454334334.html?spm=a2700.picsearch.normal_offer.d_image.47a75f93CPFDtz | O21: Limpiador facial vitamina C Garnier | Q21: N/A | R21: N/A | S21: N/A | T21: Gel limpiador facial refrescante. Con vitamina C y glicerina. Deja la piel limpia, suave y humectada. Ayuda a unificar el tono de la piel. Vegano, libre de parabenos" con olor Menta + cítricos (limón, bergamota o mandarina): muy refrescante, con energía vibrante | V21: MXN | W21: 10000 | X21: 22.23625 | AA21: =+AH21*$AB$18 -> #VALUE! | AB21: =X21+Y21+Z21+AA21 -> #VALUE! | AC21: Garnier Express Acalara | AD21: 149 | AE21: SIMPLE limpiador facial con efecto Humectante 150 ml $129 L'Oréal Paris Men Expert Limpiador facial en gel Pure Charcoal 100ml $139 Garnier Express Aclara Limpiador profundo exfoliante Anti-imperfecciones 150ml $220 | AF21: 129 | AG21: =AF21/1.16 -> 111.2069 | AH21: =(AG21)*0.6 -> 66.724138 | AI21: =AB21/AH21 -> #VALUE! | AJ21: =1-(AB21/AH21) -> #VALUE! | AK21: =1-(AH21/(AF21/1.16)) -> 0.4 | AL21: Personal Care | AM21: MX | AN21: TBC | AO21: TBC | AR21: 79 | AS21: =(AR21/1.16) -> 68.103448 | AT21: =+AB21/AS21 -> #VALUE! | AU21: =1-(AB21/AS21) -> #VALUE! | AV21: =1-(AS21/(AR21/1.16)) -> 0 | BA21: 1 | BJ21: 9 | BK21: =SUM(BA21:BG21) -> 1 | BL21: =+BK21/BJ21 -> 0.11111111
A22: 11 | B22: Por confirmar | C22: Por confirmar | D22: Pendiente | E22: 7503057496268 | F22: PB-013 | G22: Parches para labios "Pillow Lips" | H22: #VALUE! | I22: 1 pz | J22: Playboy | K22: Mix de canales | L22: 2 | M22: N/A | O22: Parches hidratantes para labios | Q22: Rojos | R22: Pantone 705 C | S22: #VALUE! | T22: N/A | U22: 0.0558 | V22: USD | W22: 30000 | X22: =+U22*$Y$17 -> 0 | Y22: =+X22*0.25 -> 0 | Z22: #VALUE! | AA22: =+AH22*$AB$18 -> #VALUE! | AB22: =X22+Y22+Z22+AA22 -> #VALUE! | AC22: YAAB | AD22: 39 | AE22: Parche para labios Kiss Kiss Lovely Tony Moly $79 Patch de colágeno para labios Yaab $20 | AF22: 19.9 | AG22: =AF22/1.16 -> 17.155172 | AH22: =(AG22)*0.6 -> 10.293103 | AI22: =AB22/AH22 -> #VALUE! | AJ22: =1-(AB22/AH22) -> #VALUE! | AK22: =1-(AH22/(AF22/1.16)) -> 0.4 | AL22: Skin Care | AM22: CN | AN22: 24 | AO22: 48 | AR22: 9 | AS22: =(AR22/1.16) -> 7.7586207 | AT22: =+AB22/AS22 -> #VALUE! | AU22: =1-(AB22/AS22) -> #VALUE! | AV22: =1-(AS22/(AR22/1.16)) -> 0 | BA22: 1 | BB22: 1 | BC22: 1 | BD22: 1 | BE22: 1 | BF22: 1 | BJ22: 9 | BK22: =SUM(BA22:BG22) -> 6 | BL22: =+BK22/BJ22 -> 0.66666667

Sheet Playboy 2026 Fase 1
B1: Estatus | C1: Atrasado
A2: Playboy
A3: Orden de compra | B3: 46101 | C3: 46112
C4: 46118
A5: Autorización Licencia | B5: =B3 -> 46101 | C5: 46135
A6: Produccion / envio | B6: =+B3+40 -> 46141 | C6: =C5+50 -> 46185 | AP6: 46233 | AQ6: =+AP6+65 -> 46298
A7: Fecha Estimada Pago balance | B7: =+B6+45 -> 46186 | C7: =+C6+45 -> 46230 | AP7: 46233 | AQ7: =+AP7+65 -> 46298 | AX7: =+AQ7+10 -> 46308
A8: Llegada Almacén | B8: =+B6+65 -> 46206 | C8: =+C6+65 -> 46250 | AP8: =+AQ8-65 -> 46215 | AQ8: 46280
A9: Lanzamiento | B9: =+B8+7 -> 46213 | C9: =+C8+7 -> 46257
CJ14: SEGUIMIENTO DE FECHAS
CJ15: PPEDIDOS | CL15: PREPRODUCCION | CO15: AUTORIZACIÓN MARCA | CR15: DISPONIBILIDAD | CU15: DOCUMENTOS PROVEEDOR | CW15: PICK UP DE MERCANCIA | CY15: SALIDA DE LIS | DA15: LLEGADA A ADUANA | DC15: DISPONIBILIDAD EN ALMACEN
A16: Fecha confirmada de Lanzamiento | B16: Mes de Lanzamiento (Esperado) | C16: Estatus | D16: EAN | E16: Código interno | F16: Nombre Comercial | G16: Imagen | H16: Contenido | I16: Marca | J16: Canales | K16: Fase | L16: Costo real | M16: Moneda | N16: Piezas cotizadas (MOQ) | O16: Costo Esperado en MXN | P16: IGI | Q16: Incrementables | R16: Costo final en MXN (FOB en almacén PT) | S16: Caracteristicas de Fórmula | T16: Costo Autorizado | U16: Moneda | V16: Piezas cotizadas (MOQ) | W16: Costo en MXN | X16: IGI | Y16: Incrementables | Z16: Regalía | AA16: Costo final en MXN (FOB en almacén PT) | AB16: BENCHMARK DE PRECIO (MARCA) | AC16: Precio Benchmark | AD16: COMPETIDORES CERCANOS (Index de precios) | AE16: Precio publico C/IVA | AF16: Precio público s/IVA | AG16: Facturación por unidad | AH16: Factor costo | AI16: Margen de utilidad bruta | AJ16: MU Cliente | AK16: Categoría | AL16: Pais de origen | AM16: Inner pcs | AN16: Master | AO16: Comentarios | AP16: Disponibilidad en Almacén | AR16: Precio publico C/IVA | AS16: Facturación por unidad | AT16: Factor costo | AU16: Margen de utilidad bruta | AV16: Margen MO | BA16: Line Up | BB16: Costo Autorizado | BC16: PVP Autorizado | BD16: Formula autorizada | BE16: Vobo CEO + VPs | BF16: Arte Final | BG16: PO | BH16: Salida de LIS | BI16: Disponibilidad en almacén | BJ16: Total | BK16: Estatus | BL16: % de Avance | BR16: Comentarios | BS16: Disponibilidad en Almacén | BT16: Responsable Siguiente paso | CJ16: ESPERADA | CK16: REAL | CL16: ESPERADA ORIGINAL | CM16: ESPERADA NUEVA | CN16: REAL | CO16: ESPERADA ORIGINAL | CP16: ESPERADA NUEVA | CQ16: REAL | CR16: ESPERADA ORIGINAL | CS16: ESPERADA NUEVA | CT16: REAL | CU16: ESPERADA | CV16: REAL | CW16: ESPERADA | CX16: REAL | CY16: ESPERADA | CZ16: REAL | DA16: ESPERADA | DB16: REAL | DC16: ESPERADA | DD16: REAL
A17: 46234 | B17: Agosto | C17: En tiempo | D17: 7503057496206 | E17: PB-007 | F17: Mascarilla facial para mujer matificante “Matte Harmony” | G17: #VALUE! | H17: 1 pz | I17: Playboy | J17: Mix de canales | K17: 1 | L17: N/A | N17: Mascarilla YAAB Arroz | P17: N/A | Q17: N/A | R17: N/A | S17: N/A | T17: 0.083333333 | U17: USD | V17: 30000 | W17: =T17*$Y$17 -> #VALUE! | X17: =+W17*0.25 -> #VALUE! | Y17: #VALUE! | Z17: =+AG17*$AB$18 -> #VALUE! | AA17: 0.15 | AB17: YAAB | AC17: 39 | AD17: Mascarilla de arroz orgánico Yaab Beauty $25 TONYMOLY Mascarilla limpiadora de Arroz $63 | AE17: 19.9 | AF17: =AE17/1.16 -> 17.155172 | AG17: =(AF17)*0.6 -> 10.293103 | AH17: =AA17/AG17 -> 0.014572864 | AI17: =1-(AA17/AG17) -> 0.98542714 | AJ17: =1-(AG17/(AE17/1.16)) -> 0.4 | AK17: Skin Care | AL17: CN | AM17: 12 | AN17: 48 | AO17: En tránsito | AP17: 46310 | AR17: 9 | AS17: =(AR17/1.16) -> 7.7586207 | AT17: =+AA17/AS17 -> 0.019333333 | AU17: =1-(AA17/AS17) -> 0.98066667 | AV17: =1-(AS17/(AR17/1.16)) -> 0 | BA17: 1 | BB17: 1 | BC17: 1 | BD17: 1 | BE17: 1 | BF17: 1 | BG17: 1 | BH17: 1 | BJ17: 9 | BK17: =SUM(BA17:BI17) -> 8 | BL17: =+BK17/BJ17 -> 0.88888889 | BR17: =+AO17 -> En tránsito | BS17: =+AP17 -> 46310 | BT17: Pao Salas (logistica) | CJ17: 46112 | CK17: 46118 | CL17: 46133 | CM17: 46132 | CN17: 46171 | CO17: 46151 | CP17: 46189 | CQ17: 46185 | CR17: 46217 | CS17: 46220 | CT17: 46222 | CU17: 46197 | CV17: 46202 | CW17: 46229 | CX17: PENDIENTE | CY17: 46236 | CZ17: PENDIENTE | DA17: 46280 | DB17: PENDIENTE | DC17: 46290 | DD17: PENDIENTE
A18: 46234 | B18: Agosto | C18: En tiempo | D18: 7503057496213 | E18: PB-008 | F18: Mascarilla facial para mujer vitamina C "Glow Crush" | G18: #VALUE! | H18: 1 pz | I18: Playboy | J18: Mix de canales | K18: 1 | L18: N/A | N18: Mascarilla Vitamina C | P18: N/A | Q18: N/A | R18: N/A | S18: N/A | T18: 0.083 | U18: USD | V18: 30000 | W18: =+T18*$Y$17 -> #VALUE! | X18: =+W18*0.25 -> #VALUE! | Y18: #VALUE! | Z18: =+AG18*$AB$18 -> #VALUE! | AA18: 0.15 | AB18: YAAB | AC18: 39 | AD18: Mascarilla de Vitamina C Yaab Beauty $25 Skin Sense con Vitamina C $40 Esfolio Mascarilla Facial Vitamina C $20 Garnier Skin Active Express Aclara Anti-Manchas Vitamina C $50 | AE18: 19.9 | AF18: =AE18/1.16 -> 17.155172 | AG18: =(AF18)*0.6 -> 10.293103 | AH18: =AA18/AG18 -> 0.014572864 | AI18: =1-(AA18/AG18) -> 0.98542714 | AJ18: =1-(AG18/(AE18/1.16)) -> 0.4 | AK18: Skin Care | AL18: CN | AM18: 12 | AN18: 48 | AO18: En tránsito | AP18: 46310 | AR18: 9 | AS18: =(AR18/1.16) -> 7.7586207 | AT18: =+AA18/AS18 -> 0.019333333 | AU18: =1-(AA18/AS18) -> 0.98066667 | AV18: =1-(AS18/(AR18/1.16)) -> 0 | BA18: 1 | BB18: 1 | BC18: 1 | BD18: 1 | BE18: 1 | BF18: 1 | BG18: 1 | BH18: 1 | BJ18: 9 | BK18: =SUM(BA18:BI18) -> 8 | BL18: =+BK18/BJ18 -> 0.88888889 | BR18: =+AO18 -> En tránsito | BS18: =+AP18 -> 46310 | BT18: Pao Salas (logistica) | CJ18: 46112 | CK18: 46118 | CL18: 46127 | CN18: 46162 | CO18: 46145 | CQ18: 46185 | CR18: 46217 | CS18: 140726 | CT18: 46227 | CU18: 46197 | CV18: PENDIENTE | CW18: 46224 | CX18: PENDIENTE | CY18: 46231 | CZ18: PENDIENTE | DA18: 46275 | DB18: PENDIENTE | DC18: 46285 | DD18: PENDIENTE
A19: 46234 | B19: Agosto | C19: En tiempo | D19: 7503057496220 | E19: PB-009 | F19: Mascarilla facial para mujer con extracto de rosas "Petal Seduction" | G19: #VALUE! | H19: 1 pz | I19: Playboy | J19: Mix de canales | K19: 1 | L19: N/A | N19: Mascarillla de rosas | P19: N/A | Q19: N/A | R19: N/A | S19: N/A | T19: 0.083 | U19: USD | V19: 30000 | W19: =+T19*$Y$17 -> #VALUE! | X19: =+W19*0.25 -> #VALUE! | Y19: #VALUE! | Z19: =+AG19*$AB$18 -> #VALUE! | AA19: 0.15 | AB19: YAAB | AC19: 39 | AD19: Mascarilla de extracto de rosas y ácido hialurónico Yaab Beauty $25 Mascarilla Facial Esfolio Agua de Rosas $20 Nivea Mascarilla Agua de Rosas $99 TONYMOLY Mascarilla hidratante de Rosa $65 | AE19: 19.9 | AF19: =AE19/1.16 -> 17.155172 | AG19: =(AF19)*0.6 -> 10.293103 | AH19: =AA19/AG19 -> 0.014572864 | AI19: =1-(AA19/AG19) -> 0.98542714 | AJ19: =1-(AG19/(AE19/1.16)) -> 0.4 | AK19: Skin Care | AL19: CN | AM19: 12 | AN19: 48 | AO19: En tránsito | AP19: 46310 | AR19: 9 | AS19: =(AR19/1.16) -> 7.7586207 | AT19: =+AA19/AS19 -> 0.019333333 | AU19: =1-(AA19/AS19) -> 0.98066667 | AV19: =1-(AS19/(AR19/1.16)) -> 0 | BA19: 1 | BB19: 1 | BC19: 1 | BD19: 1 | BE19: 1 | BF19: 1 | BG19: 1 | BH19: 1 | BJ19: 9 | BK19: =SUM(BA19:BI19) -> 8 | BL19: =+BK19/BJ19 -> 0.88888889 | BR19: =+AO19 -> En tránsito | BS19: =+AP19 -> 46310 | BT19: Pao Salas (logistica) | CJ19: 46112 | CK19: 46118 | CL19: 46127 | CN19: 46171 | CO19: 46145 | CQ19: 46185 | CR19: 46215 | CT19: PENDIENTE | CU19: 46195 | CV19: PENDIENTE | CW19: 46222 | CX19: PENDIENTE | CY19: 46229 | CZ19: PENDIENTE | DA19: 46273 | DB19: PENDIENTE | DC19: 46283 | DD19: PENDIENTE
A20: 46234 | B20: Agosto | C20: En tiempo | D20: 7503057496237 | E20: PB-010 | F20: Mascarilla facial para mujer con extracto de coco "Tropic Tease" | G20: #VALUE! | H20: 1 pz | I20: Playboy | J20: Mix de canales | K20: 1 | L20: N/A | N20: Mascarilla Coco Hidratante | P20: N/A | Q20: N/A | R20: N/A | S20: N/A | T20: 0.083 | U20: USD | V20: 30000 | W20: =+T20*$Y$17 -> #VALUE! | X20: =+W20*0.25 -> #VALUE! | Y20: #VALUE! | Z20: =+AG20*$AB$18 -> #VALUE! | AA20: 0.15 | AB20: YAAB | AC20: 39 | AD20: TONYMOLY Mascarilla hidratante de Coco $65 Mascarilla equate agua de coco $29 Mascarilla Facial Yaab Beauty Coco $25 | AE20: 19.9 | AF20: =AE20/1.16 -> 17.155172 | AG20: =(AF20)*0.6 -> 10.293103 | AH20: =AA20/AG20 -> 0.014572864 | AI20: =1-(AA20/AG20) -> 0.98542714 | AJ20: =1-(AG20/(AE20/1.16)) -> 0.4 | AK20: Skin Care | AL20: CN | AM20: 12 | AN20: 48 | AO20: En tránsito | AP20: 46300 | AR20: 9 | AS20: =(AR20/1.16) -> 7.7586207 | AT20: =+AA20/AS20 -> 0.019333333 | AU20: =1-(AA20/AS20) -> 0.98066667 | AV20: =1-(AS20/(AR20/1.16)) -> 0 | BA20: 1 | BB20: 1 | BC20: 1 | BD20: 1 | BE20: 1 | BF20: 1 | BG20: 1 | BH20: 1 | BJ20: 9 | BK20: =SUM(BA20:BI20) -> 8 | BL20: =+BK20/BJ20 -> 0.88888889 | BR20: =+AO20 -> En tránsito | BS20: =+AP20 -> 46300 | BT20: Pao Salas (logistica) | CJ20: 46112 | CK20: 46118 | CL20: 46127 | CN20: 46162 | CO20: 46145 | CQ20: 46185 | CR20: 46215 | CT20: PENDIENTE | CU20: 46195 | CV20: PENDIENTE | CW20: 46222 | CX20: PENDIENTE | CY20: 46229 | CZ20: PENDIENTE | DA20: 46273 | DB20: PENDIENTE | DC20: 46283 | DD20: PENDIENTE
A21: 46234 | B21: Agosto | C21: En tiempo | D21: 7503057496244 | E21: PB-011 | F21: Mascarilla facial para mujer con oro + ácido hialurónico "Golden Glow Up" | G21: #VALUE! | H21: 1 pz | I21: Playboy | J21: Mix de canales | K21: 1 | L21: N/A | N21: Mascarilla Gold 24k | P21: N/A | Q21: N/A | R21: N/A | S21: N/A | T21: 0.083 | U21: USD | V21: 30000 | W21: =+T21*$Y$17 -> #VALUE! | X21: =+W21*0.25 -> #VALUE! | Y21: #VALUE! | Z21: =+AG21*$AB$18 -> #VALUE! | AA21: 0.15 | AB21: YAAB | AC21: 39 | AD21: Mascarilla 24K Gold y ácido hialurónico Yaab $25 Mascarilla de Oro 24K Y acido hialuronico Bella Durmiente $29 Eternal Secret Mascarilla Facial Oro $34 | AE21: 19.9 | AF21: =AE21/1.16 -> 17.155172 | AG21: =(AF21)*0.6 -> 10.293103 | AH21: =AA21/AG21 -> 0.014572864 | AI21: =1-(AA21/AG21) -> 0.98542714 | AJ21: =1-(AG21/(AE21/1.16)) -> 0.4 | AK21: Skin Care | AL21: CN | AM21: 12 | AN21: 48 | AO21: En tránsito | AP21: 46310 | AR21: 9 | AS21: =(AR21/1.16) -> 7.7586207 | AT21: =+AA21/AS21 -> 0.019333333 | AU21: =1-(AA21/AS21) -> 0.98066667 | AV21: =1-(AS21/(AR21/1.16)) -> 0 | BA21: 1 | BB21: 1 | BC21: 1 | BD21: 1 | BE21: 1 | BF21: 1 | BG21: 1 | BH21: 1 | BJ21: 9 | BK21: =SUM(BA21:BI21) -> 8 | BL21: =+BK21/BJ21 -> 0.88888889 | BR21: =+AO21 -> En tránsito | BS21: =+AP21 -> 46310 | BT21: Pao Salas (logistica) | CJ21: 46112 | CK21: 46118 | CL21: 46127 | CN21: 46171 | CO21: 46145 | CQ21: 46185 | CR21: 46215 | CT21: PENDIENTE | CU21: 46195 | CV21: PENDIENTE | CW21: 46222 | CX21: PENDIENTE | CY21: 46229 | CZ21: PENDIENTE | DA21: 46273 | DB21: PENDIENTE | DC21: 46283 | DD21: PENDIENTE
A22: 46234 | B22: Agosto | C22: En tiempo | D22: 7503057496275 | E22: PB-014 | F22: Mascarilla facial para mujer suavizante "Cool Me Down" | G22: #VALUE! | H22: 1 pz | I22: Playboy | J22: Mix de canales | K22: 1 | L22: N/A | N22: Mascarilla Calmante | Antiinflamatoria | P22: N/A | Q22: N/A | R22: N/A | S22: N/A | T22: 0.083 | U22: USD | V22: 30000 | W22: =+T22*$Y$17 -> #VALUE! | X22: =+W22*0.25 -> #VALUE! | Y22: #VALUE! | Z22: =+AG22*$AB$18 -> #VALUE! | AA22: 0.15 | AB22: RC | AC22: 39 | AD22: Skin Sense Mascarilla Facial con Miel $42 Mascarilla de miel orgánica RC $39 TONYMOLY Mascarilla nutritiva de Miel $65 | AE22: 19.9 | AF22: =AE22/1.16 -> 17.155172 | AG22: =(AF22)*0.6 -> 10.293103 | AH22: =AA22/AG22 -> 0.014572864 | AI22: =1-(AA22/AG22) -> 0.98542714 | AJ22: =1-(AG22/(AE22/1.16)) -> 0.4 | AK22: Skin Care | AL22: CN | AM22: 12 | AN22: 48 | AO22: En tránsito | AP22: 46310 | AR22: =+AE22*0.65 -> 12.935 | AS22: =(AR22/1.16) -> 11.150862 | AT22: =+AA22/AS22 -> 0.013451875 | AU22: =1-(AA22/AS22) -> 0.98654813 | AV22: =1-(AS22/(AR22/1.16)) -> 0 | BA22: 1 | BB22: 1 | BC22: 1 | BD22: 1 | BE22: 1 | BF22: 1 | BG22: 1 | BH22: 1 | BJ22: 9 | BK22: =SUM(BA22:BI22) -> 8 | BL22: =+BK22/BJ22 -> 0.88888889 | BR22: =+AO22 -> En tránsito | BS22: =+AP22 -> 46310 | BT22: Pao Salas (logistica) | CJ22: 46112 | CK22: 46118 | CL22: 46127 | CN22: 46162 | CO22: 46145 | CQ22: 46175 | CR22: 46205 | CT22: PENDIENTE | CU22: 46185 | CV22: PENDIENTE | CW22: 46212 | CX22: PENDIENTE | CY22: 46219 | CZ22: PENDIENTE | DA22: 46263 | DB22: PENDIENTE | DC22: 46273 | DD22: PENDIENTE
A23: 46234 | B23: Agosto | C23: En tiempo | D23: 7503057496282 | E23: PB-015 | F23: Mascarilla facial para mujer ácido hialurónico y té verde "Plump Glow Obsession" | G23: #VALUE! | H23: 1 pz | I23: Playboy | J23: Mix de canales | K23: 1 | L23: N/A | N23: Mascarilla facial acido te verde yaab | P23: N/A | Q23: N/A | R23: N/A | S23: N/A | T23: 0.083 | U23: USD | V23: 30000 | W23: =+T23*$Y$17 -> #VALUE! | X23: =+W23*0.25 -> #VALUE! | Y23: #VALUE! | Z23: =+AG23*$AB$18 -> #VALUE! | AA23: 0.15 | AB23: GARNIER | AC23: 39 | AD23: TE VERDE SKIN ACTIVE HIDRA BOMB GARNIER $50 TONYMOLY Mascarilla purificante de Te Verde $65 Skin Sense Mascarilla Facial con Té Verde $45 | AE23: 19.9 | AF23: =AE23/1.16 -> 17.155172 | AG23: =(AF23)*0.6 -> 10.293103 | AH23: =AA23/AG23 -> 0.014572864 | AI23: =1-(AA23/AG23) -> 0.98542714 | AJ23: =1-(AG23/(AE23/1.16)) -> 0.4 | AK23: Skin Care | AL23: CN | AM23: 12 | AN23: 48 | AO23: En tránsito | AP23: 46310 | AR23: =+AE23*0.65 -> 12.935 | AS23: =(AR23/1.16) -> 11.150862 | AT23: =+AA23/AS23 -> 0.013451875 | AU23: =1-(AA23/AS23) -> 0.98654813 | AV23: =1-(AS23/(AR23/1.16)) -> 0 | BA23: 1 | BB23: 1 | BC23: 1 | BD23: 1 | BE23: 1 | BF23: 1 | BG23: 1 | BH23: 1 | BJ23: 9 | BK23: =SUM(BA23:BI23) -> 8 | BL23: =+BK23/BJ23 -> 0.88888889 | BR23: =+AO23 -> En tránsito | BS23: =+AP23 -> 46310 | BT23: Pao Salas (logistica) | CJ23: 46112 | CK23: 46118 | CL23: 46127 | CN23: 46162 | CO23: 46145 | CQ23: 46188 | CR23: 46218 | CT23: PENDIENTE | CU23: 46198 | CV23: PENDIENTE | CW23: 46225 | CX23: PENDIENTE | CY23: 46232 | CZ23: PENDIENTE | DA23: 46276 | DB23: PENDIENTE | DC23: 46286 | DD23: PENDIENTE
A24: 46234 | B24: Agosto | C24: En tiempo | D24: 7503057496299 | E24: PB-016 | F24: Mascarilla facial para mujer colágeno "Collagen Luxe Radiance" | G24: #VALUE! | H24: 1 pz | I24: Playboy | J24: Mix de canales | K24: 1 | L24: N/A | N24: Mascarilla facial con colageno | P24: N/A | Q24: N/A | R24: N/A | S24: N/A | T24: 0.083 | U24: USD | V24: 30000 | W24: =+T24*$Y$17 -> #VALUE! | X24: =+W24*0.25 -> #VALUE! | Y24: #VALUE! | Z24: =+AG24*$AB$18 -> #VALUE! | AA24: 0.15 | AC24: 39 | AD24: Skin Sense Mascarilla Facial con Colágeno $45 TONYMOLY Mascarilla de Colágeno Master Lab $85 | AE24: 19.9 | AF24: =AE24/1.16 -> 17.155172 | AG24: =(AF24)*0.6 -> 10.293103 | AH24: =AA24/AG24 -> 0.014572864 | AI24: =1-(AA24/AG24) -> 0.98542714 | AJ24: =1-(AG24/(AE24/1.16)) -> 0.4 | AK24: Skin Care | AL24: CN | AM24: 12 | AN24: 48 | AO24: En tránsito | AP24: 46310 | AR24: =+AE24*0.65 -> 12.935 | AS24: =(AR24/1.16) -> 11.150862 | AT24: =+AA24/AS24 -> 0.013451875 | AU24: =1-(AA24/AS24) -> 0.98654813 | AV24: =1-(AS24/(AR24/1.16)) -> 0 | BA24: 1 | BB24: 1 | BC24: 1 | BD24: 1 | BE24: 1 | BF24: 1 | BG24: 1 | BH24: 1 | BJ24: 9 | BK24: =SUM(BA24:BI24) -> 8 | BL24: =+BK24/BJ24 -> 0.88888889 | BR24: =+AO24 -> En tránsito | BS24: =+AP24 -> 46310 | BT24: Pao Salas (logistica) | CJ24: 46112 | CK24: 46118 | CL24: 46127 | CN24: 46162 | CO24: 46145 | CQ24: 46149 | CR24: 46179 | CT24: PENDIENTE | CU24: 46159 | CV24: PENDIENTE | CW24: 46186 | CX24: PENDIENTE | CY24: 46193 | CZ24: PENDIENTE | DA24: 46237 | DB24: PENDIENTE | DC24: 46247 | DD24: PENDIENTE
A25: 46234 | B25: Agosto | C25: En tiempo | D25: 7503057496305 | E25: PB-017 | F25: Mascarilla para busto "Blossom Me Duo" | G25: #VALUE! | H25: 2 piezas | I25: Playboy | J25: Mix de canales | K25: 1 | L25: https://www.alibaba.com/product-detail/24K-Gold-Collagen-Breast-Patch-Firming_60785116844.html?spm=a2700.details.you_may_like.1.71b24e39IGn6Yy | N25: Mascarilla para senos | P25: N/A | Q25: N/A | R25: N/A | S25: N/A | T25: 0.11166667 | U25: USD | V25: 30000 | W25: =+T25*$Y$17 -> #VALUE! | X25: =+W25*0.25 -> #VALUE! | Y25: #VALUE! | Z25: =+AG25*$AB$18 -> #VALUE! | AA25: 0.2 | AC25: 39 | AD25: Mom to Mom Mascarilla de Tela para Senos $203 FRIDA MOM Mascarilla para la Congestión de Senos $219 Mascarilla Corporal Busto Tonificante Freeman $69 | AE25: 49 | AF25: =AE25/1.16 -> 42.241379 | AG25: =(AF25)*0.6 -> 25.344828 | AH25: =AA25/AG25 -> 0.0078911565 | AI25: =1-(AA25/AG25) -> 0.99210884 | AJ25: =1-(AG25/(AE25/1.16)) -> 0.4 | AK25: Skin Care | AL25: CN | AM25: 12 | AN25: 48 | AO25: En tránsito | AP25: 46310 | AR25: =+AE25*0.65 -> 31.85 | AS25: =(AR25/1.16) -> 27.456897 | AT25: =+AA25/AS25 -> 0.0072841444 | AU25: =1-(AA25/AS25) -> 0.99271586 | AV25: =1-(AS25/(AR25/1.16)) -> 0 | BA25: 1 | BB25: 1 | BC25: 1 | BD25: 1 | BE25: 1 | BF25: 1 | BG25: 1 | BH25: 1 | BJ25: 9 | BK25: =SUM(BA25:BI25) -> 8 | BL25: =+BK25/BJ25 -> 0.88888889 | BR25: =+AO25 -> En tránsito | BS25: =+AP25 -> 46310 | BT25: Pao Salas (logistica) | CJ25: 46112 | CK25: 46118 | CL25: 46127 | CN25: 46162 | CO25: 46145 | CQ25: 46175 | CR25: 46205 | CT25: PENDIENTE | CU25: 46185 | CV25: PENDIENTE | CW25: 46212 | CX25: PENDIENTE | CY25: 46219 | CZ25: PENDIENTE | DA25: 46263 | DB25: PENDIENTE | DC25: 46273 | DD25: PENDIENTE
A26: 46234 | B26: Agosto | C26: En tiempo | D26: 7503057496312 | E26: PB-018 | F26: Mascarilla para glúteos "Peachy Me" | G26: #VALUE! | H26: 2 piezas | I26: Playboy | J26: Mix de canales | K26: 1 | L26: https://www.alibaba.com/product-detail/Custom-Logo-Firming-Lifting-Moisturizing-Hip_1600479709904.html?spm=a2700.galleryofferlist.normal_offer.d_image.690b13a0z8sXhw&selectedCarrierCode=SEMI_MANAGED_ECONOMIC@@ECONOMY | N26: Mascarilla para gluteos | P26: N/A | Q26: N/A | R26: N/A | S26: N/A | T26: 0.325 | U26: USD | V26: 30000 | W26: =+T26*$Y$17 -> #VALUE! | X26: =+W26*0.25 -> #VALUE! | Y26: #VALUE! | Z26: =+AG26*$AB$18 -> #VALUE! | AA26: 0.58 | AC26: 39 | AD26: Mascarilla Miracle Shape-Up Buttocks Mask Freeman $64 SEPHORA COLLECTION body mask $174 | AE26: 69 | AF26: =AE26/1.16 -> 59.482759 | AG26: =(AF26)*0.6 -> 35.689655 | AH26: =AA26/AG26 -> 0.016251208 | AI26: =1-(AA26/AG26) -> 0.98374879 | AJ26: =1-(AG26/(AE26/1.16)) -> 0.4 | AK26: Skin Care | AL26: CN | AM26: 12 | AN26: 48 | AO26: En tránsito | AP26: 46310 | AR26: =+AE26*0.65 -> 44.85 | AS26: =(AR26/1.16) -> 38.663793 | AT26: =+AA26/AS26 -> 0.015001115 | AU26: =1-(AA26/AS26) -> 0.98499889 | AV26: =1-(AS26/(AR26/1.16)) -> 0 | BA26: 1 | BB26: 1 | BC26: 1 | BD26: 1 | BE26: 1 | BF26: 1 | BG26: 1 | BH26: 1 | BJ26: 9 | BK26: =SUM(BA26:BI26) -> 8 | BL26: =+BK26/BJ26 -> 0.88888889 | BR26: =+AO26 -> En tránsito | BS26: =+AP26 -> 46310 | BT26: Pao Salas (logistica) | CJ26: 46112 | CK26: 46118 | CL26: 46127 | CN26: 46162 | CO26: 46145 | CQ26: 46175 | CR26: 46205 | CT26: PENDIENTE | CU26: 46185 | CV26: PENDIENTE | CW26: 46212 | CX26: PENDIENTE | CY26: 46219 | CZ26: PENDIENTE | DA26: 46263 | DB26: PENDIENTE | DC26: 46273 | DD26: PENDIENTE
